Workbook
Name ___INDEX_SHEET___ASAP_Utilities: 'Index sheet'!$A$1
Name __aaa2: COLUMN()
Name __DATE1: "TRIGGER.MSFOR|203|501"
Name __Dumpster: 0
Name _DCFLastMonth: OFFSET('P&Ls_Consolidated_OLD'!_DCFFirstMonth,0,#REF!*12-1)
Name _RLATools_Live: 0
Name _RLATools_PortfolioRefresh: 0
Name _VALIDATE_NOICAP: OFFSET(#REF!,1,0,#REF!,1)
Name _VALIDATE_NOIEXIT: OFFSET(#REF!,1,0,#REF!,1)
Name aaaCol: COLUMN()
Name aaaRow: ROW()
Name ACC: "$Original.$A$#REF!"
Name Actual_Being_Paid_Series: OFFSET(#REF!,0,0,#REF!,1)
Name AddALinePartnerships: 'Sales & Percentage Rent'!AddALinePartnerships
Name Admin_no: 1
Name ALC_DRILL_1: "GL Transactions by Account Drill 2-0 (SP60 - SQL)||SP60-SQL-XL02-2-0||ACCOUNTNO;XLGENIE_CURRENT_PERIOD;SelectedYear;CompanyNo||IS - Actual Budget Prior - IFRS||1"
Name ALCHEMEX_DRILL_SET: "GL_001"
Name AllProjPages: #REF!,#REF!,#REF!,#REF!
Name amort.ExpCount: ROW(INDEX(#REF!,MATCH(9.99999999999999E+307,#REF!)))
Name amort.Table: #REF!:INDEX(#REF!,MATCH(9.99999999999999E+307,#REF!)+7)
Name Amounts_in: "1000"
Name Annual_Budget_Interest_Expense: SUM(#REF!)
Name Annual_Budget_Total_Amort_Recov_Capital: SUM(#REF!)
Name Annual_Budget_Total_Taxes: SUM(#REF!)
Name ARCPUBURL: ""
Name BacktoPartnership: 'Sales & Percentage Rent'!BacktoPartnership
Name BLDG.__410: "CAMSCH"
Name BonusNames: #REF!,#REF!
Name BPAGE: "1"
Name BUDGET_utili_REAIS: #REF!,#REF!,#REF!,#REF!
Name BUDGET_WORKSHEET___REAIS: #REF!,#REF!,#REF!,#REF!,#REF!
Name BUDGET_WORKSHEET_US: #REF!,#REF!,#REF!,#REF!,#REF!
Name Bugget_w: #REF!,#REF!,#REF!,#REF!,#REF!
Name Building: "One University Avenue"
Name Button_1: "CalifornianCasa_UnitDetails_List"
Name Button_80: "The_Bonavista_UnitDetails_List"
Name CellContents: _xlfn.FORMULATEXT(INDIRECT(ADDRESS(ROW(), COLUMN())))
Name Choices_Wrapper: Proforma!Choices_Wrapper
Name Choices_Wrapper5: Proforma!Choices_Wrapper5
Name CI: "HEAD"
Name COL1STYR: 7
Name Company_name: "SLOV - KAUFRING"
Name Contract_NRI_Series: OFFSET(#REF!,0,0,#REF!,1)
Name Corporate_tax_rate: 0.4
Name CPAGE: "37"
Name CPNMB: "1"
Name cSum: 9
Name CTIM2: "122917"
Name Current_Forecast_Series: OFFSET(#REF!,0,0,#REF!,1)
Name DataDisplayed: "user"
Name Date_Series: OFFSET(#REF!,0,0,#REF!,1)
Name DeleteAccumAmort: #REF!,#REF!
Name DeleteFA: #REF!,#REF!,#REF!
Name DeleteIntangibleAssets: #REF!,#REF!
Name DeleteLand: #REF!,#REF!
Name DeleteTaxRollforward: #REF!,#REF!,#REF!,#REF!,#REF!,#REF!
Name DelLevClear: #REF!,#REF!,#REF!,#REF!,#REF!,#REF!,#REF!
Name delLevClearExec: #REF!,#REF!
Name devsummprint: #REF!,#REF!+#REF!,#REF!,#REF!
Name DVNAM: "XF175E"

Sheet Index sheet
A1: Sheet index:
A2: Title Page
A3: DD Req List
A4: UW Notes
A5: UW-->
A6: Pres Summ
A7: Exec Summ
A8: Return Metrics
A9: Exhibits-->
A10: Global
A11: Proforma
A12: P&Ls_Con
... A48: COA

Sheet CAM Assumptions
B2: Misc Notes & Questions:
B3: - Assumed all tenants roll to options and recoveries continue prior
B4: - Assumed Ross continues paying % rent in lieu of actual rent & recoveries throughout option period
B5: - Assumed GSA expenses were not included in historicals, as in SIG OM
B6: - G&A shows up in CAM recs but not in P&Ls
B7: - Mgmt fee show up in CAM recs but not in P&Ls
B8: - Which tax parcels are included in the common area? Do you happen to have the annual tax values for Chipotle and Building T?
B9: - Where are the vacant units that don't appear on stie plan?
B10: Why are the taxes for Boulder Tap House are showing $38,038 actual taxes , while the P&L only reflects approximately $5K in tax expense
B12: Tenant | C12: CAM Recs | D12: Notes / Comments
B13: Chipotle | D13: No CAM Recs, used $22PSF estimated recoveries from Lease Agreement as placeholder
B14: Burlington | C14: Yes
B15: Petsmart | C15: Yes
B16: Boulder Tap | C16: Yes | D16: Line item "General Administrative/Office" in the CAM Recs cannot be found on the 2025 Expenses. Modeled as reference only expenses line item in Argus for the meantime
B17: Ulta | D17: No CAM Recs, used $6.10PSF estimated recoveries from Lease Agreement as placeholder
B18: Five Below | D18: No CAM Recs, used $6.10PSF estimated recoveries from Lease Agreement as placeholder
B19: Bath and Body | D19: No CAM Recs, used $6.10PSF estimated recoveries from Lease Agreement as placeholder
B20: Maurice's | D20: No CAM Recs, used $6.10PSF estimated recoveries from Lease Agreement as placeholder
B21: Ross* | C21: n/a | D21: In percentage rent, no CAM Recs needed
B22: Michael's | C22: Yes | D22: Line item "General Administrative/Office" in the CAM Recs cannot be found on the 2025 Expenses. Modeled as reference only expenses line item in Argus for the meantime
B23: GSA | C23: n/a | D23: Gross
B24: JCPenney | C24: n/a | D24: Full Service
B26: NAP Tenants
B27: U-Haul | C27: Yes | D27: Line item "General Administrative/Office" in the CAM Recs cannot be found on the 2025 Expenses. Modeled as reference only expenses line item in Argus for the meantime
B28: Christian Brothers | C28: Yes | D28: Line item "General Administrative/Office" in the CAM Recs cannot be found on the 2025 Expenses. Modeled as reference only expenses line item in Argus for the meantime
B29: Westdale Residential Housing CAM | D29: No CAM Recs, used 2025+3% amount from 2025 WCRV#1 Revenue Summary
B30: Ironside Apparel | D30: No CAM Recs, used 2025+3% amount from 2025 WCRV#1 Revenue Summary
B31: Mandarin Spice | D31: No CAM Recs, used 2025+3% amount from 2025 WCRV#1 Revenue Summary
B32: Home2 | C32: Yes | D32: Line item "General Administrative/Office" in the CAM Recs cannot be found on the 2025 Expenses. Modeled as reference only expenses line item in Argus for the meantime
B33: First Federal Credit Union CAM | C33: Yes | D33: Line item "General Administrative/Office" in the CAM Recs cannot be found on the 2025 Expenses. Modeled as reference only expenses line item in Argus for the meantime
B34: Westdale Hotel Associates CAM | D34: No CAM Recs, used 2025+3% amount from 2025 WCRV#1 Revenue Summary
B35: Edgewood Station CAM | C35: Yes | D35: Line item "General Administrative/Office" in the CAM Recs cannot be found on the 2025 Expenses. Modeled as reference only expenses line item in Argus for the meantime
B36: US Bank CAM | C36: Yes | D36: Line item "General Administrative/Office" in the CAM Recs cannot be found on the 2025 Expenses. Modeled as reference only expenses line item in Argus for the meantime
B37: Take5 | C37: Yes | D37: Line item "General Administrative/Office" in the CAM Recs cannot be found on the 2025 Expenses. Modeled as reference only expenses line item in Argus for the meantime
B38: 7 Brew/Sugarfire | D38: No CAM Recs, used 2025+3% amount from 2025 WCRV#1 Revenue Summary
B39: Lamb Land- Lot 2 CAM (Noodles) | D39: No CAM Recs, used 2025+3% amount from 2025 WCRV#1 Revenue Summary
B40: RNR Tire (formerly EP 3-4 CAM (Old Chicago)) | D40: No CAM Recs, used 2025+3% amount from 2025 WCRV#1 Revenue Summary
B41: Slow, LLC - Lot 5 CAM (Freddy's) | D41: No CAM Recs, used 2025+3% amount from 2025 WCRV#1 Revenue Summary
B42: Mr. Car Wash - Lot P | D42: No CAM Recs, used 2025+3% amount from 2025 WCRV#1 Revenue Summary
B43: EP - Lot 7 CAM (CFA) | D43: No CAM Recs, used 2025+3% amount from 2025 WCRV#1 Revenue Summary
B44: EP - Lot Q CAM | D44: No CAM Recs, used 2025+3% amount from 2025 WCRV#1 Revenue Summary
B45: Parway West Apartments | D45: No CAM Recs, used 2025+3% amount from 2025 WCRV#1 Revenue Summary
B46: Tru Hilton CAM | C46: Yes

Sheet RR Assumptions
C3: ASSUMPTIONS | X3: =Global!$G$7 | Z3: ='Rent Roll-Detailed'!$H$65
D4: **Note: This is a summary of the general assumptions, rent roll, and MLA tabs combined to make it easier to provide feedback. If you make any updates, please change the highlight color so we can identify what changed.**
C5: GENERAL | J5: MARKET LEASING ASSUMPTIONS
D6: General Growth Rate: | E6: =Global!G28 | K6: Market Rent | R6: Free Rent | T6: Tenant Improvement | V6: Leasing Commission
D7: Market Growth Rate: | E7: =Global!G32 | J7: Assigned Name | K7: New | L7: Renew | M7: Escalation | N7: Reimbursement | O7: Lease Term | P7: Renewal Prob. | Q7: Downtime | R7: New | S7: Renew | T7: New | U7: Renew | V7: New | W7: Renew
D8: Expense Growth Rate: | E8: =Global!G29 | J8: $22.00 PSF NNN | K8: =INDEX(MLAs!$E$8:$N$8,MATCH('RR Assumptions'!$J8,MLAs!$E$5:$N$5,0)) | L8: =INDEX(MLAs!$E$9:$N$9,MATCH('RR Assumptions'!$J8,MLAs!$E$5:$N$5,0)) | M8: =INDEX(MLAs!$E$10:$N$10,MATCH('RR Assumptions'!$J8,MLAs!$E$5:$N$5,0)) | N8: =INDEX(MLAs!$E$13:$N$13,MATCH('RR Assumptions'!$J8,MLAs!$E$5:$N$5,0)) | O8: =INDEX(MLAs!$E$14:$N$14,MATCH('RR Assumptions'!$J8,MLAs!$E$5:$N$5,0)) | P8: =INDEX(MLAs!$E$15:$N$15,MATCH('RR Assumptions'!$J8,MLAs!$E$5:$N$5,0)) | Q8: =INDEX(MLAs!$E$16:$N$16,MATCH('RR Assumptions'!$J8,MLAs!$E$5:$N$5,0)) | R8: =INDEX(MLAs!$E$19:$N$19,MATCH('RR Assumptions'!$J8,MLAs!$E$5:$N$5,0)) | S8: =INDEX(MLAs!$E$20:$N$20,MATCH('RR Assumptions'!$J8,MLAs!$E$5:$N$5,0)) | T8: =INDEX(MLAs!$E$24:$N$24,MATCH('RR Assumptions'!$J8,MLAs!$E$5:$N$5,0)) | U8: =INDEX(MLAs!$E$25:$N$25,MATCH('RR Assumptions'!$J8,MLAs!$E$5:$N$5,0)) | V8: =INDEX(MLAs!$E$29:$N$29,MATCH('RR Assumptions'!$J8,MLAs!$E$5:$N$5,0)) | W8: =INDEX(MLAs!$E$30:$N$30,MATCH('RR Assumptions'!$J8,MLAs!$E$5:$N$5,0))
D9: Vacancy: | E9: =Global!G22 | J9: $27.00 PSF NNN | K9: =INDEX(MLAs!$E$8:$N$8,MATCH('RR Assumptions'!$J9,MLAs!$E$5:$N$5,0)) | L9: =INDEX(MLAs!$E$9:$N$9,MATCH('RR Assumptions'!$J9,MLAs!$E$5:$N$5,0)) | M9: =INDEX(MLAs!$E$10:$N$10,MATCH('RR Assumptions'!$J9,MLAs!$E$5:$N$5,0)) | N9: =INDEX(MLAs!$E$13:$N$13,MATCH('RR Assumptions'!$J9,MLAs!$E$5:$N$5,0)) | O9: =INDEX(MLAs!$E$14:$N$14,MATCH('RR Assumptions'!$J9,MLAs!$E$5:$N$5,0)) | P9: =INDEX(MLAs!$E$15:$N$15,MATCH('RR Assumptions'!$J9,MLAs!$E$5:$N$5,0)) | Q9: =INDEX(MLAs!$E$16:$N$16,MATCH('RR Assumptions'!$J9,MLAs!$E$5:$N$5,0)) | R9: =INDEX(MLAs!$E$19:$N$19,MATCH('RR Assumptions'!$J9,MLAs!$E$5:$N$5,0)) | S9: =INDEX(MLAs!$E$20:$N$20,MATCH('RR Assumptions'!$J9,MLAs!$E$5:$N$5,0)) | T9: =INDEX(MLAs!$E$24:$N$24,MATCH('RR Assumptions'!$J9,MLAs!$E$5:$N$5,0)) | U9: =INDEX(MLAs!$E$25:$N$25,MATCH('RR Assumptions'!$J9,MLAs!$E$5:$N$5,0)) | V9: =INDEX(MLAs!$E$29:$N$29,MATCH('RR Assumptions'!$J9,MLAs!$E$5:$N$5,0)) | W9: =INDEX(MLAs!$E$30:$N$30,MATCH('RR Assumptions'!$J9,MLAs!$E$5:$N$5,0))
D10: Excluded Tenants: | E10: Yes | F10: if "Yes" please indicate in the provided RR below | J10: $30.00 PSF NNN | K10: =INDEX(MLAs!$E$8:$N$8,MATCH('RR Assumptions'!$J10,MLAs!$E$5:$N$5,0)) | L10: =INDEX(MLAs!$E$9:$N$9,MATCH('RR Assumptions'!$J10,MLAs!$E$5:$N$5,0)) | M10: =INDEX(MLAs!$E$10:$N$10,MATCH('RR Assumptions'!$J10,MLAs!$E$5:$N$5,0)) | N10: =INDEX(MLAs!$E$13:$N$13,MATCH('RR Assumptions'!$J10,MLAs!$E$5:$N$5,0)) | O10: =INDEX(MLAs!$E$14:$N$14,MATCH('RR Assumptions'!$J10,MLAs!$E$5:$N$5,0)) | P10: =INDEX(MLAs!$E$15:$N$15,MATCH('RR Assumptions'!$J10,MLAs!$E$5:$N$5,0)) | Q10: =INDEX(MLAs!$E$16:$N$16,MATCH('RR Assumptions'!$J10,MLAs!$E$5:$N$5,0)) | R10: =INDEX(MLAs!$E$19:$N$19,MATCH('RR Assumptions'!$J10,MLAs!$E$5:$N$5,0)) | S10: =INDEX(MLAs!$E$20:$N$20,MATCH('RR Assumptions'!$J10,MLAs!$E$5:$N$5,0)) | T10: =INDEX(MLAs!$E$24:$N$24,MATCH('RR Assumptions'!$J10,MLAs!$E$5:$N$5,0)) | U10: =INDEX(MLAs!$E$25:$N$25,MATCH('RR Assumptions'!$J10,MLAs!$E$5:$N$5,0)) | V10: =INDEX(MLAs!$E$29:$N$29,MATCH('RR Assumptions'!$J10,MLAs!$E$5:$N$5,0)) | W10: =INDEX(MLAs!$E$30:$N$30,MATCH('RR Assumptions'!$J10,MLAs!$E$5:$N$5,0))
J11: $27.00 PSF NNN | K11: =INDEX(MLAs!$E$8:$N$8,MATCH('RR Assumptions'!$J11,MLAs!$E$5:$N$5,0)) | L11: =INDEX(MLAs!$E$9:$N$9,MATCH('RR Assumptions'!$J11,MLAs!$E$5:$N$5,0)) | M11: =INDEX(MLAs!$E$10:$N$10,MATCH('RR Assumptions'!$J11,MLAs!$E$5:$N$5,0)) | N11: =INDEX(MLAs!$E$13:$N$13,MATCH('RR Assumptions'!$J11,MLAs!$E$5:$N$5,0)) | O11: =INDEX(MLAs!$E$14:$N$14,MATCH('RR Assumptions'!$J11,MLAs!$E$5:$N$5,0)) | P11: =INDEX(MLAs!$E$15:$N$15,MATCH('RR Assumptions'!$J11,MLAs!$E$5:$N$5,0)) | Q11: =INDEX(MLAs!$E$16:$N$16,MATCH('RR Assumptions'!$J11,MLAs!$E$5:$N$5,0)) | R11: =INDEX(MLAs!$E$19:$N$19,MATCH('RR Assumptions'!$J11,MLAs!$E$5:$N$5,0)) | S11: =INDEX(MLAs!$E$20:$N$20,MATCH('RR Assumptions'!$J11,MLAs!$E$5:$N$5,0)) | T11: =INDEX(MLAs!$E$24:$N$24,MATCH('RR Assumptions'!$J11,MLAs!$E$5:$N$5,0)) | U11: =INDEX(MLAs!$E$25:$N$25,MATCH('RR Assumptions'!$J11,MLAs!$E$5:$N$5,0)) | V11: =INDEX(MLAs!$E$29:$N$29,MATCH('RR Assumptions'!$J11,MLAs!$E$5:$N$5,0)) | W11: =INDEX(MLAs!$E$30:$N$30,MATCH('RR Assumptions'!$J11,MLAs!$E$5:$N$5,0))
J12: Retail D - ATM $3,333/ mo | K12: =INDEX(MLAs!$E$8:$N$8,MATCH('RR Assumptions'!$J12,MLAs!$E$5:$N$5,0)) | L12: =INDEX(MLAs!$E$9:$N$9,MATCH('RR Assumptions'!$J12,MLAs!$E$5:$N$5,0)) | M12: =INDEX(MLAs!$E$10:$N$10,MATCH('RR Assumptions'!$J12,MLAs!$E$5:$N$5,0)) | N12: =INDEX(MLAs!$E$13:$N$13,MATCH('RR Assumptions'!$J12,MLAs!$E$5:$N$5,0)) | O12: =INDEX(MLAs!$E$14:$N$14,MATCH('RR Assumptions'!$J12,MLAs!$E$5:$N$5,0)) | P12: =INDEX(MLAs!$E$15:$N$15,MATCH('RR Assumptions'!$J12,MLAs!$E$5:$N$5,0)) | Q12: =INDEX(MLAs!$E$16:$N$16,MATCH('RR Assumptions'!$J12,MLAs!$E$5:$N$5,0)) | R12: =INDEX(MLAs!$E$19:$N$19,MATCH('RR Assumptions'!$J12,MLAs!$E$5:$N$5,0)) | S12: =INDEX(MLAs!$E$20:$N$20,MATCH('RR Assumptions'!$J12,MLAs!$E$5:$N$5,0)) | T12: =INDEX(MLAs!$E$24:$N$24,MATCH('RR Assumptions'!$J12,MLAs!$E$5:$N$5,0)) | U12: =INDEX(MLAs!$E$25:$N$25,MATCH('RR Assumptions'!$J12,MLAs!$E$5:$N$5,0)) | V12: =INDEX(MLAs!$E$29:$N$29,MATCH('RR Assumptions'!$J12,MLAs!$E$5:$N$5,0)) | W12: =INDEX(MLAs!$E$30:$N$30,MATCH('RR Assumptions'!$J12,MLAs!$E$5:$N$5,0))
D13: EXPENSES
D14: Mgmt Fee (% of EGR): | E14: =Global!G41
D15: Real Estate Tax: | E15: =Global!G42
D16: Capital Reserve: | E16: =Global!G45
D17: Other Expenses: | E17: =Global!G40 | J17: OTHER ASSUMPTIONS
J18: ='Rent Roll-Detailed'!C69
J19: ='Rent Roll-Detailed'!C70
J20: ='Rent Roll-Detailed'!C71
J21: ='Rent Roll-Detailed'!C72
J22: ='Rent Roll-Detailed'!C75
C23: ONE-LINE RENT ROLL WITH MLA ASSIGNMENT
K24: Market Rent | R24: Free Rent | T24: Tenant Improvement | V24: Leasing Commission
D25: Suite | E25: Tenant | F25: Area (SF) | G25: PRS | H25: Contr. Base Rent PSF | I25: Exclude from Vacancy | J25: MLA Assigned | K25: New | L25: Renew | M25: Escalation | N25: Reimbursement | O25: Lease Term | P25: Renewal Prob. | Q25: Downtime | R25: New | S25: Renew | T25: New | U25: Renew | V25: New | W25: Renew | AB25: ISODD? | AC25: Bldg No
D26: {=_xlfn._xlws.FILTER('Rent Roll-Detailed'!$F$8:$F$60,'Rent Roll-Detailed'!$F$8:$F$60<>"")} | E26: =_xlfn.XLOOKUP($D26,'Rent Roll-Detailed'!$F$8:$F$60,'Rent Roll-Detailed'!$G$8:$G$60) | F26: =_xlfn.XLOOKUP($D26,'Rent Roll-Detailed'!$F$8:$F$60,'Rent Roll-Detailed'!H$8:H$60) | G26: =F26/$F$52 | H26: =IF(E26="Vacant","",_xlfn.XLOOKUP($D26,'Rent Roll-Detailed'!$F$8:$F$60,'Rent Roll-Detailed'!R$8:R$60)) | I26: Yes | J26: =INDEX('One-line RR'!$V$7:$V$12,MATCH('RR Assumptions'!$E26,'One-line RR'!$G$7:$G$12,0)) | K26: =INDEX(K$8:K$20,MATCH($J26,$J$8:$J$20,0)) | L26: =INDEX(L$8:L$23,MATCH($J26,$J$8:$J$23,0)) | M26: =INDEX(M$8:M$23,MATCH($J26,$J$8:$J$23,0)) | N26: =INDEX(N$8:N$23,MATCH($J26,$J$8:$J$23,0)) | O26: =INDEX(O$8:O$23,MATCH($J26,$J$8:$J$23,0)) | P26: =INDEX(P$8:P$23,MATCH($J26,$J$8:$J$23,0)) | Q26: =INDEX(Q$8:Q$23,MATCH($J26,$J$8:$J$23,0)) | R26: =INDEX(R$8:R$23,MATCH($J26,$J$8:$J$23,0)) | S26: =INDEX(S$8:S$23,MATCH($J26,$J$8:$J$23,0)) | ... W26: =INDEX(W$8:W$23,MATCH($J26,$J$8:$J$23,0)) | AB26: =ISODD(MAX(COUNTA($D$26:D26)))
D27: 2 | E27: =_xlfn.XLOOKUP($D27,'Rent Roll-Detailed'!$F$8:$F$60,'Rent Roll-Detailed'!$G$8:$G$60) | F27: =_xlfn.XLOOKUP($D27,'Rent Roll-Detailed'!$F$8:$F$60,'Rent Roll-Detailed'!H$8:H$60) | G27: =F27/$F$52 | H27: =IF(E27="Vacant","",_xlfn.XLOOKUP($D27,'Rent Roll-Detailed'!$F$8:$F$60,'Rent Roll-Detailed'!R$8:R$60)) | I27: Yes | J27: =INDEX('One-line RR'!$V$7:$V$12,MATCH('RR Assumptions'!$E27,'One-line RR'!$G$7:$G$12,0)) | K27: =INDEX(K$8:K$23,MATCH($J27,$J$8:$J$23,0)) | L27: =INDEX(L$8:L$23,MATCH($J27,$J$8:$J$23,0)) | M27: =INDEX(M$8:M$23,MATCH($J27,$J$8:$J$23,0)) | N27: =INDEX(N$8:N$23,MATCH($J27,$J$8:$J$23,0)) | O27: =INDEX(O$8:O$23,MATCH($J27,$J$8:$J$23,0)) | P27: =INDEX(P$8:P$23,MATCH($J27,$J$8:$J$23,0)) | Q27: =INDEX(Q$8:Q$23,MATCH($J27,$J$8:$J$23,0)) | R27: =INDEX(R$8:R$23,MATCH($J27,$J$8:$J$23,0)) | ... W27: =INDEX(W$8:W$23,MATCH($J27,$J$8:$J$23,0)) | AB27: =ISODD(MAX(COUNTA($D$26:D27)))
D28: 3 | E28: =_xlfn.XLOOKUP($D28,'Rent Roll-Detailed'!$F$8:$F$60,'Rent Roll-Detailed'!$G$8:$G$60) | F28: =_xlfn.XLOOKUP($D28,'Rent Roll-Detailed'!$F$8:$F$60,'Rent Roll-Detailed'!H$8:H$60) | G28: =F28/$F$52 | H28: =IF(E28="Vacant","",_xlfn.XLOOKUP($D28,'Rent Roll-Detailed'!$F$8:$F$60,'Rent Roll-Detailed'!R$8:R$60)) | I28: Yes | J28: =INDEX('One-line RR'!$V$7:$V$12,MATCH('RR Assumptions'!$E28,'One-line RR'!$G$7:$G$12,0)) | K28: =INDEX(K$8:K$23,MATCH($J28,$J$8:$J$23,0)) | L28: =INDEX(L$8:L$23,MATCH($J28,$J$8:$J$23,0)) | M28: =INDEX(M$8:M$23,MATCH($J28,$J$8:$J$23,0)) | N28: =INDEX(N$8:N$23,MATCH($J28,$J$8:$J$23,0)) | O28: =INDEX(O$8:O$23,MATCH($J28,$J$8:$J$23,0)) | P28: =INDEX(P$8:P$23,MATCH($J28,$J$8:$J$23,0)) | Q28: =INDEX(Q$8:Q$23,MATCH($J28,$J$8:$J$23,0)) | R28: =INDEX(R$8:R$23,MATCH($J28,$J$8:$J$23,0)) | ... W28: =INDEX(W$8:W$23,MATCH($J28,$J$8:$J$23,0)) | AB28: =ISODD(MAX(COUNTA($D$26:D28)))
D29: 4 | E29: =_xlfn.XLOOKUP($D29,'Rent Roll-Detailed'!$F$8:$F$60,'Rent Roll-Detailed'!$G$8:$G$60) | F29: =_xlfn.XLOOKUP($D29,'Rent Roll-Detailed'!$F$8:$F$60,'Rent Roll-Detailed'!H$8:H$60) | G29: =F29/$F$52 | H29: =IF(E29="Vacant","",_xlfn.XLOOKUP($D29,'Rent Roll-Detailed'!$F$8:$F$60,'Rent Roll-Detailed'!R$8:R$60)) | I29: No | J29: =INDEX('One-line RR'!$V$7:$V$12,MATCH('RR Assumptions'!$E29,'One-line RR'!$G$7:$G$12,0)) | K29: =INDEX(K$8:K$23,MATCH($J29,$J$8:$J$23,0)) | L29: =INDEX(L$8:L$23,MATCH($J29,$J$8:$J$23,0)) | M29: =INDEX(M$8:M$23,MATCH($J29,$J$8:$J$23,0)) | N29: =INDEX(N$8:N$23,MATCH($J29,$J$8:$J$23,0)) | O29: =INDEX(O$8:O$23,MATCH($J29,$J$8:$J$23,0)) | P29: =INDEX(P$8:P$23,MATCH($J29,$J$8:$J$23,0)) | Q29: =INDEX(Q$8:Q$23,MATCH($J29,$J$8:$J$23,0)) | R29: =INDEX(R$8:R$23,MATCH($J29,$J$8:$J$23,0)) | ... W29: =INDEX(W$8:W$23,MATCH($J29,$J$8:$J$23,0)) | AB29: =ISODD(MAX(COUNTA($D$26:D29)))
D30: 112 | E30: =_xlfn.XLOOKUP($D30,'Rent Roll-Detailed'!$F$8:$F$60,'Rent Roll-Detailed'!$G$8:$G$60) | F30: =_xlfn.XLOOKUP($D30,'Rent Roll-Detailed'!$F$8:$F$60,'Rent Roll-Detailed'!H$8:H$60) | G30: =F30/$F$52 | H30: =IF(E30="Vacant","",_xlfn.XLOOKUP($D30,'Rent Roll-Detailed'!$F$8:$F$60,'Rent Roll-Detailed'!R$8:R$60)) | I30: Yes | J30: =INDEX('One-line RR'!$V$7:$V$12,MATCH('RR Assumptions'!$E30,'One-line RR'!$G$7:$G$12,0)) | K30: =INDEX(K$8:K$23,MATCH($J30,$J$8:$J$23,0)) | L30: =INDEX(L$8:L$23,MATCH($J30,$J$8:$J$23,0)) | M30: =INDEX(M$8:M$23,MATCH($J30,$J$8:$J$23,0)) | N30: =INDEX(N$8:N$23,MATCH($J30,$J$8:$J$23,0)) | O30: =INDEX(O$8:O$23,MATCH($J30,$J$8:$J$23,0)) | P30: =INDEX(P$8:P$23,MATCH($J30,$J$8:$J$23,0)) | Q30: =INDEX(Q$8:Q$23,MATCH($J30,$J$8:$J$23,0)) | R30: =INDEX(R$8:R$23,MATCH($J30,$J$8:$J$23,0)) | ... W30: =INDEX(W$8:W$23,MATCH($J30,$J$8:$J$23,0)) | AB30: =ISODD(MAX(COUNTA($D$26:D30)))
D31: 6 | E31: =_xlfn.XLOOKUP($D31,'Rent Roll-Detailed'!$F$8:$F$60,'Rent Roll-Detailed'!$G$8:$G$60) | F31: =_xlfn.XLOOKUP($D31,'Rent Roll-Detailed'!$F$8:$F$60,'Rent Roll-Detailed'!H$8:H$60) | G31: =F31/$F$52 | H31: =IF(E31="Vacant","",_xlfn.XLOOKUP($D31,'Rent Roll-Detailed'!$F$8:$F$60,'Rent Roll-Detailed'!R$8:R$60)) | I31: Yes | J31: =INDEX('One-line RR'!$V$7:$V$12,MATCH('RR Assumptions'!$E31,'One-line RR'!$G$7:$G$12,0)) | K31: =INDEX(K$8:K$23,MATCH($J31,$J$8:$J$23,0)) | L31: =INDEX(L$8:L$23,MATCH($J31,$J$8:$J$23,0)) | M31: =INDEX(M$8:M$23,MATCH($J31,$J$8:$J$23,0)) | N31: =INDEX(N$8:N$23,MATCH($J31,$J$8:$J$23,0)) | O31: =INDEX(O$8:O$23,MATCH($J31,$J$8:$J$23,0)) | P31: =INDEX(P$8:P$23,MATCH($J31,$J$8:$J$23,0)) | Q31: =INDEX(Q$8:Q$23,MATCH($J31,$J$8:$J$23,0)) | R31: =INDEX(R$8:R$23,MATCH($J31,$J$8:$J$23,0)) | ... W31: =INDEX(W$8:W$23,MATCH($J31,$J$8:$J$23,0)) | AB31: =ISODD(MAX(COUNTA($D$26:D31)))
E32: =_xlfn.XLOOKUP($D32,'Rent Roll-Detailed'!$F$8:$F$60,'Rent Roll-Detailed'!$G$8:$G$60) | F32: =_xlfn.XLOOKUP($D32,'Rent Roll-Detailed'!$F$8:$F$60,'Rent Roll-Detailed'!H$8:H$60) | G32: =F32/$F$52 | H32: =IF(E32="Vacant","",_xlfn.XLOOKUP($D32,'Rent Roll-Detailed'!$F$8:$F$60,'Rent Roll-Detailed'!R$8:R$60)) | I32: Yes | J32: =INDEX('One-line RR'!$V$7:$V$12,MATCH('RR Assumptions'!$E32,'One-line RR'!$G$7:$G$12,0)) | K32: =INDEX(K$8:K$23,MATCH($J32,$J$8:$J$23,0)) | L32: =INDEX(L$8:L$23,MATCH($J32,$J$8:$J$23,0)) | M32: =INDEX(M$8:M$23,MATCH($J32,$J$8:$J$23,0)) | N32: =INDEX(N$8:N$23,MATCH($J32,$J$8:$J$23,0)) | O32: =INDEX(O$8:O$23,MATCH($J32,$J$8:$J$23,0)) | P32: =INDEX(P$8:P$23,MATCH($J32,$J$8:$J$23,0)) | Q32: =INDEX(Q$8:Q$23,MATCH($J32,$J$8:$J$23,0)) | R32: =INDEX(R$8:R$23,MATCH($J32,$J$8:$J$23,0)) | ... W32: =INDEX(W$8:W$23,MATCH($J32,$J$8:$J$23,0)) | AB32: =ISODD(MAX(COUNTA($D$26:D32)))
E33: =_xlfn.XLOOKUP($D33,'Rent Roll-Detailed'!$F$8:$F$60,'Rent Roll-Detailed'!$G$8:$G$60) | F33: =_xlfn.XLOOKUP($D33,'Rent Roll-Detailed'!$F$8:$F$60,'Rent Roll-Detailed'!H$8:H$60) | G33: =F33/$F$52 | H33: =IF(E33="Vacant","",_xlfn.XLOOKUP($D33,'Rent Roll-Detailed'!$F$8:$F$60,'Rent Roll-Detailed'!R$8:R$60)) | I33: No | J33: =INDEX('One-line RR'!$V$7:$V$12,MATCH('RR Assumptions'!$E33,'One-line RR'!$G$7:$G$12,0)) | K33: =INDEX(K$8:K$23,MATCH($J33,$J$8:$J$23,0)) | L33: =INDEX(L$8:L$23,MATCH($J33,$J$8:$J$23,0)) | M33: =INDEX(M$8:M$23,MATCH($J33,$J$8:$J$23,0)) | N33: =INDEX(N$8:N$23,MATCH($J33,$J$8:$J$23,0)) | O33: =INDEX(O$8:O$23,MATCH($J33,$J$8:$J$23,0)) | P33: =INDEX(P$8:P$23,MATCH($J33,$J$8:$J$23,0)) | Q33: =INDEX(Q$8:Q$23,MATCH($J33,$J$8:$J$23,0)) | R33: =INDEX(R$8:R$23,MATCH($J33,$J$8:$J$23,0)) | ... W33: =INDEX(W$8:W$23,MATCH($J33,$J$8:$J$23,0)) | AB33: =ISODD(MAX(COUNTA($D$26:D33)))
E34: =_xlfn.XLOOKUP($D34,'Rent Roll-Detailed'!$F$8:$F$60,'Rent Roll-Detailed'!$G$8:$G$60) | F34: =_xlfn.XLOOKUP($D34,'Rent Roll-Detailed'!$F$8:$F$60,'Rent Roll-Detailed'!H$8:H$60) | G34: =F34/$F$52 | H34: =IF(E34="Vacant","",_xlfn.XLOOKUP($D34,'Rent Roll-Detailed'!$F$8:$F$60,'Rent Roll-Detailed'!R$8:R$60)) | I34: Yes | J34: =INDEX('One-line RR'!$V$7:$V$12,MATCH('RR Assumptions'!$E34,'One-line RR'!$G$7:$G$12,0)) | K34: =INDEX(K$8:K$23,MATCH($J34,$J$8:$J$23,0)) | L34: =INDEX(L$8:L$23,MATCH($J34,$J$8:$J$23,0)) | M34: =INDEX(M$8:M$23,MATCH($J34,$J$8:$J$23,0)) | N34: =INDEX(N$8:N$23,MATCH($J34,$J$8:$J$23,0)) | O34: =INDEX(O$8:O$23,MATCH($J34,$J$8:$J$23,0)) | P34: =INDEX(P$8:P$23,MATCH($J34,$J$8:$J$23,0)) | Q34: =INDEX(Q$8:Q$23,MATCH($J34,$J$8:$J$23,0)) | R34: =INDEX(R$8:R$23,MATCH($J34,$J$8:$J$23,0)) | ... W34: =INDEX(W$8:W$23,MATCH($J34,$J$8:$J$23,0)) | AB34: =ISODD(MAX(COUNTA($D$26:D34)))
E35: =_xlfn.XLOOKUP($D35,'Rent Roll-Detailed'!$F$8:$F$60,'Rent Roll-Detailed'!$G$8:$G$60) | F35: =_xlfn.XLOOKUP($D35,'Rent Roll-Detailed'!$F$8:$F$60,'Rent Roll-Detailed'!H$8:H$60) | G35: =F35/$F$52 | H35: =IF(E35="Vacant","",_xlfn.XLOOKUP($D35,'Rent Roll-Detailed'!$F$8:$F$60,'Rent Roll-Detailed'!R$8:R$60)) | I35: Yes | J35: =INDEX('One-line RR'!$V$7:$V$12,MATCH('RR Assumptions'!$E35,'One-line RR'!$G$7:$G$12,0)) | K35: =INDEX(K$8:K$23,MATCH($J35,$J$8:$J$23,0)) | L35: =INDEX(L$8:L$23,MATCH($J35,$J$8:$J$23,0)) | M35: =INDEX(M$8:M$23,MATCH($J35,$J$8:$J$23,0)) | N35: =INDEX(N$8:N$23,MATCH($J35,$J$8:$J$23,0)) | O35: =INDEX(O$8:O$23,MATCH($J35,$J$8:$J$23,0)) | P35: =INDEX(P$8:P$23,MATCH($J35,$J$8:$J$23,0)) | Q35: =INDEX(Q$8:Q$23,MATCH($J35,$J$8:$J$23,0)) | R35: =INDEX(R$8:R$23,MATCH($J35,$J$8:$J$23,0)) | ... W35: =INDEX(W$8:W$23,MATCH($J35,$J$8:$J$23,0)) | AB35: =ISODD(MAX(COUNTA($D$26:D35)))
E36: =_xlfn.XLOOKUP($D36,'Rent Roll-Detailed'!$F$8:$F$60,'Rent Roll-Detailed'!$G$8:$G$60) | F36: =_xlfn.XLOOKUP($D36,'Rent Roll-Detailed'!$F$8:$F$60,'Rent Roll-Detailed'!H$8:H$60) | G36: =F36/$F$52 | H36: =IF(E36="Vacant","",_xlfn.XLOOKUP($D36,'Rent Roll-Detailed'!$F$8:$F$60,'Rent Roll-Detailed'!R$8:R$60)) | I36: Yes | J36: =INDEX('One-line RR'!$V$7:$V$12,MATCH('RR Assumptions'!$E36,'One-line RR'!$G$7:$G$12,0)) | K36: =INDEX(K$8:K$23,MATCH($J36,$J$8:$J$23,0)) | L36: =INDEX(L$8:L$23,MATCH($J36,$J$8:$J$23,0)) | M36: =INDEX(M$8:M$23,MATCH($J36,$J$8:$J$23,0)) | N36: =INDEX(N$8:N$23,MATCH($J36,$J$8:$J$23,0)) | O36: =INDEX(O$8:O$23,MATCH($J36,$J$8:$J$23,0)) | P36: =INDEX(P$8:P$23,MATCH($J36,$J$8:$J$23,0)) | Q36: =INDEX(Q$8:Q$23,MATCH($J36,$J$8:$J$23,0)) | R36: =INDEX(R$8:R$23,MATCH($J36,$J$8:$J$23,0)) | ... W36: =INDEX(W$8:W$23,MATCH($J36,$J$8:$J$23,0)) | AB36: =ISODD(MAX(COUNTA($D$26:D36)))
E37: =_xlfn.XLOOKUP($D37,'Rent Roll-Detailed'!$F$8:$F$60,'Rent Roll-Detailed'!$G$8:$G$60) | F37: =_xlfn.XLOOKUP($D37,'Rent Roll-Detailed'!$F$8:$F$60,'Rent Roll-Detailed'!H$8:H$60) | G37: =F37/$F$52 | H37: =IF(E37="Vacant","",_xlfn.XLOOKUP($D37,'Rent Roll-Detailed'!$F$8:$F$60,'Rent Roll-Detailed'!R$8:R$60)) | I37: Yes | AB37: =ISODD(MAX(COUNTA($D$26:D37)))
E38: =_xlfn.XLOOKUP($D38,'Rent Roll-Detailed'!$F$8:$F$60,'Rent Roll-Detailed'!$G$8:$G$60) | F38: =_xlfn.XLOOKUP($D38,'Rent Roll-Detailed'!$F$8:$F$60,'Rent Roll-Detailed'!H$8:H$60) | G38: =F38/$F$52 | H38: =IF(E38="Vacant","",_xlfn.XLOOKUP($D38,'Rent Roll-Detailed'!$F$8:$F$60,'Rent Roll-Detailed'!R$8:R$60)) | I38: Yes | J38: =INDEX('One-line RR'!$V$7:$V$12,MATCH('RR Assumptions'!$E38,'One-line RR'!$G$7:$G$12,0)) | K38: =INDEX(K$8:K$23,MATCH($J38,$J$8:$J$23,0)) | L38: =INDEX(L$8:L$23,MATCH($J38,$J$8:$J$23,0)) | M38: =INDEX(M$8:M$23,MATCH($J38,$J$8:$J$23,0)) | N38: =INDEX(N$8:N$23,MATCH($J38,$J$8:$J$23,0)) | O38: =INDEX(O$8:O$23,MATCH($J38,$J$8:$J$23,0)) | P38: =INDEX(P$8:P$23,MATCH($J38,$J$8:$J$23,0)) | Q38: =INDEX(Q$8:Q$23,MATCH($J38,$J$8:$J$23,0)) | R38: =INDEX(R$8:R$23,MATCH($J38,$J$8:$J$23,0)) | ... W38: =INDEX(W$8:W$23,MATCH($J38,$J$8:$J$23,0)) | AB38: =ISODD(MAX(COUNTA($D$26:D38)))
E39: =_xlfn.XLOOKUP($D39,'Rent Roll-Detailed'!$F$8:$F$60,'Rent Roll-Detailed'!$G$8:$G$60) | F39: =_xlfn.XLOOKUP($D39,'Rent Roll-Detailed'!$F$8:$F$60,'Rent Roll-Detailed'!H$8:H$60) | G39: =F39/$F$52 | H39: =IF(E39="Vacant","",_xlfn.XLOOKUP($D39,'Rent Roll-Detailed'!$F$8:$F$60,'Rent Roll-Detailed'!R$8:R$60)) | I39: Yes | J39: =INDEX('One-line RR'!$V$7:$V$12,MATCH('RR Assumptions'!$E39,'One-line RR'!$G$7:$G$12,0)) | K39: =INDEX(K$8:K$23,MATCH($J39,$J$8:$J$23,0)) | L39: =INDEX(L$8:L$23,MATCH($J39,$J$8:$J$23,0)) | M39: =INDEX(M$8:M$23,MATCH($J39,$J$8:$J$23,0)) | N39: =INDEX(N$8:N$23,MATCH($J39,$J$8:$J$23,0)) | O39: =INDEX(O$8:O$23,MATCH($J39,$J$8:$J$23,0)) | P39: =INDEX(P$8:P$23,MATCH($J39,$J$8:$J$23,0)) | Q39: =INDEX(Q$8:Q$23,MATCH($J39,$J$8:$J$23,0)) | R39: =INDEX(R$8:R$23,MATCH($J39,$J$8:$J$23,0)) | ... W39: =INDEX(W$8:W$23,MATCH($J39,$J$8:$J$23,0)) | AB39: =ISODD(MAX(COUNTA($D$26:D39)))
E40: =_xlfn.XLOOKUP($D40,'Rent Roll-Detailed'!$F$8:$F$60,'Rent Roll-Detailed'!$G$8:$G$60) | F40: =_xlfn.XLOOKUP($D40,'Rent Roll-Detailed'!$F$8:$F$60,'Rent Roll-Detailed'!H$8:H$60) | G40: =F40/$F$52 | H40: =IF(E40="Vacant","",_xlfn.XLOOKUP($D40,'Rent Roll-Detailed'!$F$8:$F$60,'Rent Roll-Detailed'!R$8:R$60)) | I40: Yes | J40: =INDEX('One-line RR'!$V$7:$V$12,MATCH('RR Assumptions'!$E40,'One-line RR'!$G$7:$G$12,0)) | K40: =INDEX(K$8:K$23,MATCH($J40,$J$8:$J$23,0)) | L40: =INDEX(L$8:L$23,MATCH($J40,$J$8:$J$23,0)) | M40: =INDEX(M$8:M$23,MATCH($J40,$J$8:$J$23,0)) | N40: =INDEX(N$8:N$23,MATCH($J40,$J$8:$J$23,0)) | O40: =INDEX(O$8:O$23,MATCH($J40,$J$8:$J$23,0)) | P40: =INDEX(P$8:P$23,MATCH($J40,$J$8:$J$23,0)) | Q40: =INDEX(Q$8:Q$23,MATCH($J40,$J$8:$J$23,0)) | R40: =INDEX(R$8:R$23,MATCH($J40,$J$8:$J$23,0)) | S40: =INDEX(S$8:S$23,MATCH($J40,$J$8:$J$23,0)) | T40: 25 | U40: 0 | V40: =INDEX(V$8:V$23,MATCH($J40,$J$8:$J$23,0)) | W40: =INDEX(W$8:W$23,MATCH($J40,$J$8:$J$23,0)) | AB40: =ISODD(MAX(COUNTA($D$26:D40)))
E41: =_xlfn.XLOOKUP($D41,'Rent Roll-Detailed'!$F$8:$F$60,'Rent Roll-Detailed'!$G$8:$G$60) | F41: =_xlfn.XLOOKUP($D41,'Rent Roll-Detailed'!$F$8:$F$60,'Rent Roll-Detailed'!H$8:H$60) | G41: =F41/$F$52 | H41: =IF(E41="Vacant","",_xlfn.XLOOKUP($D41,'Rent Roll-Detailed'!$F$8:$F$60,'Rent Roll-Detailed'!R$8:R$60)) | I41: Yes | J41: =INDEX('One-line RR'!$V$7:$V$12,MATCH('RR Assumptions'!$E41,'One-line RR'!$G$7:$G$12,0)) | K41: =INDEX(K$8:K$23,MATCH($J41,$J$8:$J$23,0)) | L41: =INDEX(L$8:L$23,MATCH($J41,$J$8:$J$23,0)) | M41: =INDEX(M$8:M$23,MATCH($J41,$J$8:$J$23,0)) | N41: =INDEX(N$8:N$23,MATCH($J41,$J$8:$J$23,0)) | O41: =INDEX(O$8:O$23,MATCH($J41,$J$8:$J$23,0)) | P41: =INDEX(P$8:P$23,MATCH($J41,$J$8:$J$23,0)) | Q41: =INDEX(Q$8:Q$23,MATCH($J41,$J$8:$J$23,0)) | R41: =INDEX(R$8:R$23,MATCH($J41,$J$8:$J$23,0)) | S41: =INDEX(S$8:S$23,MATCH($J41,$J$8:$J$23,0)) | T41: 25 | U41: 0 | V41: =INDEX(V$8:V$23,MATCH($J41,$J$8:$J$23,0)) | W41: =INDEX(W$8:W$23,MATCH($J41,$J$8:$J$23,0)) | AB41: =ISODD(MAX(COUNTA($D$26:D41)))
E42: =_xlfn.XLOOKUP($D42,'Rent Roll-Detailed'!$F$8:$F$60,'Rent Roll-Detailed'!$G$8:$G$60) | F42: =_xlfn.XLOOKUP($D42,'Rent Roll-Detailed'!$F$8:$F$60,'Rent Roll-Detailed'!H$8:H$60) | G42: =F42/$F$52 | H42: =IF(E42="Vacant","",_xlfn.XLOOKUP($D42,'Rent Roll-Detailed'!$F$8:$F$60,'Rent Roll-Detailed'!R$8:R$60)) | I42: Yes | J42: =INDEX('One-line RR'!$V$7:$V$12,MATCH('RR Assumptions'!$E42,'One-line RR'!$G$7:$G$12,0)) | K42: =INDEX(K$8:K$23,MATCH($J42,$J$8:$J$23,0)) | L42: =INDEX(L$8:L$23,MATCH($J42,$J$8:$J$23,0)) | M42: =INDEX(M$8:M$23,MATCH($J42,$J$8:$J$23,0)) | N42: =INDEX(N$8:N$23,MATCH($J42,$J$8:$J$23,0)) | O42: =INDEX(O$8:O$23,MATCH($J42,$J$8:$J$23,0)) | P42: =INDEX(P$8:P$23,MATCH($J42,$J$8:$J$23,0)) | Q42: =INDEX(Q$8:Q$23,MATCH($J42,$J$8:$J$23,0)) | R42: =INDEX(R$8:R$23,MATCH($J42,$J$8:$J$23,0)) | S42: =INDEX(S$8:S$23,MATCH($J42,$J$8:$J$23,0)) | T42: 25 | U42: 0 | V42: =INDEX(V$8:V$23,MATCH($J42,$J$8:$J$23,0)) | W42: =INDEX(W$8:W$23,MATCH($J42,$J$8:$J$23,0)) | AB42: =ISODD(MAX(COUNTA($D$26:D42)))
E43: =_xlfn.XLOOKUP($D43,'Rent Roll-Detailed'!$F$8:$F$60,'Rent Roll-Detailed'!$G$8:$G$60) | F43: =_xlfn.XLOOKUP($D43,'Rent Roll-Detailed'!$F$8:$F$60,'Rent Roll-Detailed'!H$8:H$60) | G43: =F43/$F$52 | H43: =IF(E43="Vacant","",_xlfn.XLOOKUP($D43,'Rent Roll-Detailed'!$F$8:$F$60,'Rent Roll-Detailed'!R$8:R$60)) | I43: Yes | J43: =INDEX('One-line RR'!$V$7:$V$12,MATCH('RR Assumptions'!$E43,'One-line RR'!$G$7:$G$12,0)) | K43: =INDEX(K$8:K$23,MATCH($J43,$J$8:$J$23,0)) | L43: =INDEX(L$8:L$23,MATCH($J43,$J$8:$J$23,0)) | M43: =INDEX(M$8:M$23,MATCH($J43,$J$8:$J$23,0)) | N43: =INDEX(N$8:N$23,MATCH($J43,$J$8:$J$23,0)) | O43: =INDEX(O$8:O$23,MATCH($J43,$J$8:$J$23,0)) | P43: =INDEX(P$8:P$23,MATCH($J43,$J$8:$J$23,0)) | Q43: =INDEX(Q$8:Q$23,MATCH($J43,$J$8:$J$23,0)) | R43: =INDEX(R$8:R$23,MATCH($J43,$J$8:$J$23,0)) | S43: =INDEX(S$8:S$23,MATCH($J43,$J$8:$J$23,0)) | T43: 25 | U43: 0 | V43: =INDEX(V$8:V$23,MATCH($J43,$J$8:$J$23,0)) | W43: =INDEX(W$8:W$23,MATCH($J43,$J$8:$J$23,0)) | AB43: =ISODD(MAX(COUNTA($D$26:D43)))
E44: =_xlfn.XLOOKUP($D44,'Rent Roll-Detailed'!$F$8:$F$60,'Rent Roll-Detailed'!$G$8:$G$60) | F44: =_xlfn.XLOOKUP($D44,'Rent Roll-Detailed'!$F$8:$F$60,'Rent Roll-Detailed'!H$8:H$60) | G44: =F44/$F$52 | H44: =IF(E44="Vacant","",_xlfn.XLOOKUP($D44,'Rent Roll-Detailed'!$F$8:$F$60,'Rent Roll-Detailed'!R$8:R$60)) | I44: Yes | J44: =INDEX('One-line RR'!$V$7:$V$12,MATCH('RR Assumptions'!$E44,'One-line RR'!$G$7:$G$12,0)) | K44: =INDEX(K$8:K$23,MATCH($J44,$J$8:$J$23,0)) | L44: =INDEX(L$8:L$23,MATCH($J44,$J$8:$J$23,0)) | M44: =INDEX(M$8:M$23,MATCH($J44,$J$8:$J$23,0)) | N44: =INDEX(N$8:N$23,MATCH($J44,$J$8:$J$23,0)) | O44: =INDEX(O$8:O$23,MATCH($J44,$J$8:$J$23,0)) | P44: =INDEX(P$8:P$23,MATCH($J44,$J$8:$J$23,0)) | Q44: =INDEX(Q$8:Q$23,MATCH($J44,$J$8:$J$23,0)) | R44: =INDEX(R$8:R$23,MATCH($J44,$J$8:$J$23,0)) | S44: =INDEX(S$8:S$23,MATCH($J44,$J$8:$J$23,0)) | T44: 25 | U44: 0 | V44: =INDEX(V$8:V$23,MATCH($J44,$J$8:$J$23,0)) | W44: =INDEX(W$8:W$23,MATCH($J44,$J$8:$J$23,0)) | AB44: =ISODD(MAX(COUNTA($D$26:D44)))
E45: =_xlfn.XLOOKUP($D45,'Rent Roll-Detailed'!$F$8:$F$60,'Rent Roll-Detailed'!$G$8:$G$60) | F45: =_xlfn.XLOOKUP($D45,'Rent Roll-Detailed'!$F$8:$F$60,'Rent Roll-Detailed'!H$8:H$60) | G45: =F45/$F$52 | H45: =IF(E45="Vacant","",_xlfn.XLOOKUP($D45,'Rent Roll-Detailed'!$F$8:$F$60,'Rent Roll-Detailed'!R$8:R$60)) | I45: Yes | J45: =INDEX('One-line RR'!$V$7:$V$12,MATCH('RR Assumptions'!$E45,'One-line RR'!$G$7:$G$12,0)) | K45: =INDEX(K$8:K$23,MATCH($J45,$J$8:$J$23,0)) | L45: =INDEX(L$8:L$23,MATCH($J45,$J$8:$J$23,0)) | M45: =INDEX(M$8:M$23,MATCH($J45,$J$8:$J$23,0)) | N45: =INDEX(N$8:N$23,MATCH($J45,$J$8:$J$23,0)) | O45: =INDEX(O$8:O$23,MATCH($J45,$J$8:$J$23,0)) | P45: =INDEX(P$8:P$23,MATCH($J45,$J$8:$J$23,0)) | Q45: =INDEX(Q$8:Q$23,MATCH($J45,$J$8:$J$23,0)) | R45: =INDEX(R$8:R$23,MATCH($J45,$J$8:$J$23,0)) | S45: =INDEX(S$8:S$23,MATCH($J45,$J$8:$J$23,0)) | T45: 25 | U45: 0 | V45: =INDEX(V$8:V$23,MATCH($J45,$J$8:$J$23,0)) | W45: =INDEX(W$8:W$23,MATCH($J45,$J$8:$J$23,0)) | AB45: =ISODD(MAX(COUNTA($D$26:D45)))
E46: =_xlfn.XLOOKUP($D46,'Rent Roll-Detailed'!$F$8:$F$60,'Rent Roll-Detailed'!$G$8:$G$60) | F46: =_xlfn.XLOOKUP($D46,'Rent Roll-Detailed'!$F$8:$F$60,'Rent Roll-Detailed'!H$8:H$60) | G46: =F46/$F$52 | H46: =IF(E46="Vacant","",_xlfn.XLOOKUP($D46,'Rent Roll-Detailed'!$F$8:$F$60,'Rent Roll-Detailed'!R$8:R$60)) | I46: Yes | J46: =INDEX('One-line RR'!$V$7:$V$12,MATCH('RR Assumptions'!$E46,'One-line RR'!$G$7:$G$12,0)) | K46: =INDEX(K$8:K$23,MATCH($J46,$J$8:$J$23,0)) | L46: =INDEX(L$8:L$23,MATCH($J46,$J$8:$J$23,0)) | M46: =INDEX(M$8:M$23,MATCH($J46,$J$8:$J$23,0)) | N46: =INDEX(N$8:N$23,MATCH($J46,$J$8:$J$23,0)) | O46: =INDEX(O$8:O$23,MATCH($J46,$J$8:$J$23,0)) | P46: =INDEX(P$8:P$23,MATCH($J46,$J$8:$J$23,0)) | Q46: =INDEX(Q$8:Q$23,MATCH($J46,$J$8:$J$23,0)) | R46: =INDEX(R$8:R$23,MATCH($J46,$J$8:$J$23,0)) | S46: =INDEX(S$8:S$23,MATCH($J46,$J$8:$J$23,0)) | T46: 25 | U46: 0 | V46: =INDEX(V$8:V$23,MATCH($J46,$J$8:$J$23,0)) | W46: =INDEX(W$8:W$23,MATCH($J46,$J$8:$J$23,0)) | AB46: =ISODD(MAX(COUNTA($D$26:D46)))
E47: =_xlfn.XLOOKUP($D47,'Rent Roll-Detailed'!$F$8:$F$60,'Rent Roll-Detailed'!$G$8:$G$60) | F47: =_xlfn.XLOOKUP($D47,'Rent Roll-Detailed'!$F$8:$F$60,'Rent Roll-Detailed'!H$8:H$60) | G47: =F47/$F$52 | H47: =IF(E47="Vacant","",_xlfn.XLOOKUP($D47,'Rent Roll-Detailed'!$F$8:$F$60,'Rent Roll-Detailed'!R$8:R$60)) | I47: Yes | J47: =INDEX('One-line RR'!$V$7:$V$12,MATCH('RR Assumptions'!$E47,'One-line RR'!$G$7:$G$12,0)) | K47: =INDEX(K$8:K$23,MATCH($J47,$J$8:$J$23,0)) | L47: =INDEX(L$8:L$23,MATCH($J47,$J$8:$J$23,0)) | M47: =INDEX(M$8:M$23,MATCH($J47,$J$8:$J$23,0)) | N47: =INDEX(N$8:N$23,MATCH($J47,$J$8:$J$23,0)) | O47: =INDEX(O$8:O$23,MATCH($J47,$J$8:$J$23,0)) | P47: =INDEX(P$8:P$23,MATCH($J47,$J$8:$J$23,0)) | Q47: =INDEX(Q$8:Q$23,MATCH($J47,$J$8:$J$23,0)) | R47: =INDEX(R$8:R$23,MATCH($J47,$J$8:$J$23,0)) | S47: =INDEX(S$8:S$23,MATCH($J47,$J$8:$J$23,0)) | T47: 25 | U47: 0 | V47: =INDEX(V$8:V$23,MATCH($J47,$J$8:$J$23,0)) | W47: =INDEX(W$8:W$23,MATCH($J47,$J$8:$J$23,0)) | AB47: =ISODD(MAX(COUNTA($D$26:D47)))
E48: =_xlfn.XLOOKUP($D48,'Rent Roll-Detailed'!$F$8:$F$60,'Rent Roll-Detailed'!$G$8:$G$60) | F48: =_xlfn.XLOOKUP($D48,'Rent Roll-Detailed'!$F$8:$F$60,'Rent Roll-Detailed'!H$8:H$60) | G48: =F48/$F$52 | H48: =IF(E48="Vacant","",_xlfn.XLOOKUP($D48,'Rent Roll-Detailed'!$F$8:$F$60,'Rent Roll-Detailed'!R$8:R$60)) | I48: Yes | J48: =INDEX('One-line RR'!$V$7:$V$12,MATCH('RR Assumptions'!$E48,'One-line RR'!$G$7:$G$12,0)) | K48: =INDEX(K$8:K$23,MATCH($J48,$J$8:$J$23,0)) | L48: =INDEX(L$8:L$23,MATCH($J48,$J$8:$J$23,0)) | M48: =INDEX(M$8:M$23,MATCH($J48,$J$8:$J$23,0)) | N48: =INDEX(N$8:N$23,MATCH($J48,$J$8:$J$23,0)) | O48: =INDEX(O$8:O$23,MATCH($J48,$J$8:$J$23,0)) | P48: =INDEX(P$8:P$23,MATCH($J48,$J$8:$J$23,0)) | Q48: =INDEX(Q$8:Q$23,MATCH($J48,$J$8:$J$23,0)) | R48: =INDEX(R$8:R$23,MATCH($J48,$J$8:$J$23,0)) | S48: =INDEX(S$8:S$23,MATCH($J48,$J$8:$J$23,0)) | T48: 25 | U48: 0 | V48: =INDEX(V$8:V$23,MATCH($J48,$J$8:$J$23,0)) | W48: =INDEX(W$8:W$23,MATCH($J48,$J$8:$J$23,0)) | AB48: =ISODD(MAX(COUNTA($D$26:D48)))
E49: =_xlfn.XLOOKUP($D49,'Rent Roll-Detailed'!$F$8:$F$60,'Rent Roll-Detailed'!$G$8:$G$60) | F49: =_xlfn.XLOOKUP($D49,'Rent Roll-Detailed'!$F$8:$F$60,'Rent Roll-Detailed'!H$8:H$60) | G49: =F49/$F$52 | H49: =IF(E49="Vacant","",_xlfn.XLOOKUP($D49,'Rent Roll-Detailed'!$F$8:$F$60,'Rent Roll-Detailed'!R$8:R$60)) | I49: Yes | J49: =INDEX('One-line RR'!$V$7:$V$12,MATCH('RR Assumptions'!$E49,'One-line RR'!$G$7:$G$12,0)) | K49: =INDEX(K$8:K$23,MATCH($J49,$J$8:$J$23,0)) | L49: =INDEX(L$8:L$23,MATCH($J49,$J$8:$J$23,0)) | M49: =INDEX(M$8:M$23,MATCH($J49,$J$8:$J$23,0)) | N49: =INDEX(N$8:N$23,MATCH($J49,$J$8:$J$23,0)) | O49: =INDEX(O$8:O$23,MATCH($J49,$J$8:$J$23,0)) | P49: =INDEX(P$8:P$23,MATCH($J49,$J$8:$J$23,0)) | Q49: =INDEX(Q$8:Q$23,MATCH($J49,$J$8:$J$23,0)) | R49: =INDEX(R$8:R$23,MATCH($J49,$J$8:$J$23,0)) | S49: =INDEX(S$8:S$23,MATCH($J49,$J$8:$J$23,0)) | T49: 25 | U49: 0 | V49: =INDEX(V$8:V$23,MATCH($J49,$J$8:$J$23,0)) | W49: =INDEX(W$8:W$23,MATCH($J49,$J$8:$J$23,0)) | AB49: =ISODD(MAX(COUNTA($D$26:D49)))
E50: =_xlfn.XLOOKUP($D50,'Rent Roll-Detailed'!$F$8:$F$60,'Rent Roll-Detailed'!$G$8:$G$60) | F50: =_xlfn.XLOOKUP($D50,'Rent Roll-Detailed'!$F$8:$F$60,'Rent Roll-Detailed'!H$8:H$60) | G50: =F50/$F$52 | H50: =IF(E50="Vacant","",_xlfn.XLOOKUP($D50,'Rent Roll-Detailed'!$F$8:$F$60,'Rent Roll-Detailed'!R$8:R$60)) | I50: Yes | J50: =INDEX('One-line RR'!$V$7:$V$12,MATCH('RR Assumptions'!$E50,'One-line RR'!$G$7:$G$12,0)) | K50: =INDEX(K$8:K$23,MATCH($J50,$J$8:$J$23,0)) | L50: =INDEX(L$8:L$23,MATCH($J50,$J$8:$J$23,0)) | M50: =INDEX(M$8:M$23,MATCH($J50,$J$8:$J$23,0)) | N50: =INDEX(N$8:N$23,MATCH($J50,$J$8:$J$23,0)) | O50: =INDEX(O$8:O$23,MATCH($J50,$J$8:$J$23,0)) | P50: =INDEX(P$8:P$23,MATCH($J50,$J$8:$J$23,0)) | Q50: =INDEX(Q$8:Q$23,MATCH($J50,$J$8:$J$23,0)) | R50: =INDEX(R$8:R$23,MATCH($J50,$J$8:$J$23,0)) | S50: =INDEX(S$8:S$23,MATCH($J50,$J$8:$J$23,0)) | T50: 25 | U50: 0 | V50: =INDEX(V$8:V$23,MATCH($J50,$J$8:$J$23,0)) | W50: =INDEX(W$8:W$23,MATCH($J50,$J$8:$J$23,0)) | AB50: =ISODD(MAX(COUNTA($D$26:D50)))
E51: =_xlfn.XLOOKUP($D51,'Rent Roll-Detailed'!$F$8:$F$60,'Rent Roll-Detailed'!$G$8:$G$60) | F51: =_xlfn.XLOOKUP($D51,'Rent Roll-Detailed'!$F$8:$F$60,'Rent Roll-Detailed'!H$8:H$60) | G51: =F51/$F$52 | H51: =IF(E51="Vacant","",_xlfn.XLOOKUP($D51,'Rent Roll-Detailed'!$F$8:$F$60,'Rent Roll-Detailed'!R$8:R$60)) | I51: Yes | J51: =INDEX('One-line RR'!$V$7:$V$12,MATCH('RR Assumptions'!$E51,'One-line RR'!$G$7:$G$12,0)) | K51: =INDEX(K$8:K$23,MATCH($J51,$J$8:$J$23,0)) | L51: =INDEX(L$8:L$23,MATCH($J51,$J$8:$J$23,0)) | M51: =INDEX(M$8:M$23,MATCH($J51,$J$8:$J$23,0)) | N51: =INDEX(N$8:N$23,MATCH($J51,$J$8:$J$23,0)) | O51: =INDEX(O$8:O$23,MATCH($J51,$J$8:$J$23,0)) | P51: =INDEX(P$8:P$23,MATCH($J51,$J$8:$J$23,0)) | Q51: =INDEX(Q$8:Q$23,MATCH($J51,$J$8:$J$23,0)) | R51: =INDEX(R$8:R$23,MATCH($J51,$J$8:$J$23,0)) | S51: =INDEX(S$8:S$23,MATCH($J51,$J$8:$J$23,0)) | T51: 25 | U51: 0 | V51: =INDEX(V$8:V$23,MATCH($J51,$J$8:$J$23,0)) | W51: =INDEX(W$8:W$23,MATCH($J51,$J$8:$J$23,0)) | AB51: =ISODD(MAX(COUNTA($D$26:D51)))
D52: Total/Wtd. Avg. | F52: =SUM(F26:F51) | G52: =SUM(G26:G51) | H52: {=SUMPRODUCT(IF(E26:E51<>"Vacant",1,0),H26:H51,$F$26:$F$51)/$F$54}
D54: Leased | F54: =SUMIFS(F26:F51,$E$26:$E$51,"<>"&"Vacant") | G54: =F54/F52
F58: =F52='Rent Roll-Detailed'!H65 | G58: =G52='Rent Roll-Detailed'!J65
F59: =F54='Rent Roll-Detailed'!H63 | G59: =G54='Rent Roll-Detailed'!J63

Sheet Title Page
C4: Acuity Captal Partners
C12: =Global!G7
C14: =Global!$G$8
C15: =Global!$G$9
C17: =TODAY()

Sheet UW-->

Sheet Annual Cash Flow (2)
C3: ANNUAL CASH FLOW | N3: =Global!G7
E5: 1 | F5: =E5+1 | G5: =F5+1 | H5: =G5+1 | I5: =H5+1 | J5: =I5+1 | K5: =J5+1 | L5: =K5+1 | M5: =L5+1 | N5: =M5+1 | O5: x
E6: 46295 | F6: =EOMONTH(E6,12) | G6: =EOMONTH(F6,12) | H6: =EOMONTH(G6,12) | I6: =EOMONTH(H6,12) | J6: =EOMONTH(I6,12) | K6: =EOMONTH(J6,12) | L6: =EOMONTH(K6,12) | M6: =EOMONTH(L6,12) | N6: =EOMONTH(M6,12) | O6: x
O7: x
D8: INCOME
D9: Base Rental Revenue | E9: #VALUE! | F9: 1437073.8 | G9: 1476520.3 | H9: 1517067.8 | I9: 1558747.3 | J9: 1632879.7 | K9: 1661379.8 | L9: 1707124.2 | M9: 1754148.7 | N9: 1802489.7
D10: Absorption and Turnover Vacancy | E10: 0 | F10: 0 | G10: 0 | H10: 0 | I10: 0 | J10: -549313.44 | K10: 0 | L10: 0 | M10: 0 | N10: 0
D11: Total Scheduled Base Rent | E11: =SUM(E9:E10) | F11: =SUM(F9:F10) | G11: =SUM(G9:G10) | H11: =SUM(H9:H10) | I11: =SUM(I9:I10) | J11: =SUM(J9:J10) | K11: =SUM(K9:K10) | L11: =SUM(L9:L10) | ... N11: =SUM(N9:N10)
D12: CAM Recovery | E12: 0 | F12: 0 | G12: 0 | H12: 0 | I12: 0 | J12: 0 | K12: 0 | L12: 0 | M12: 0 | N12: 0
D13: Realty Tax Recovery | E13: 511673.44 | F13: 527023.68 | G13: 542834.44 | H13: 559119.48 | I13: 575893.04 | J13: 420975.68 | K13: 610964.92 | L13: 629293.8 | M13: 648172.64 | N13: 667617.84
D14: Total Expense Reimbursements | E14: =SUM(E11:E13) | F14: =SUM(F11:F13) | G14: =SUM(G11:G13) | H14: =SUM(H11:H13) | I14: =SUM(I11:I13) | J14: =SUM(J11:J13) | K14: =SUM(K11:K13) | L14: =SUM(L11:L13) | ... N14: =SUM(N11:N13)
D15: Vacancy Loss | E15: -76414.9 | F15: -78563.91 | G15: -80774.21 | H15: -83047.46 | I15: -85385.59 | J15: 0 | K15: -90893.78 | L15: -93456.74 | M15: -96092.89 | N15: -98804.3
D16: Collection Loss | E16: =-E14*0.01 | F16: =-F14*0.01 | G16: =-G14*0.01 | H16: =-H14*0.01 | I16: =-I14*0.01 | J16: =-J14*0.01 | K16: =-K14*0.01 | L16: =-L14*0.01 | ... N16: =-N14*0.01
D17: EFFECTIVE GROSS INCOME | E17: =SUM(E14:E16) | F17: =SUM(F14:F16) | G17: =SUM(G14:G16) | H17: =SUM(H14:H16) | I17: =SUM(I14:I16) | J17: =SUM(J14:J16) | K17: =SUM(K14:K16) | L17: =SUM(L14:L16) | ... N17: =SUM(N14:N16)
E18: 0 | F18: 0 | G18: 0 | H18: 0 | I18: 0 | J18: 0 | K18: 0 | L18: 0 | M18: 0 | N18: 0
D19: OPERATING EXPENSES
D20: Municipal Taxes | E20: 13215 | F20: 30135 | G20: 41952 | H20: 95891 | I20: 17926 | J20: 37915 | K20: 11710 | L20: 27566 | M20: 74283 | N20: 98660
D21: Insurance | E21: 67202 | F21: 59169 | G21: 80194 | H21: 78438 | I21: 20732 | J21: 32059 | K21: 43254 | L21: 61190 | M21: 97266 | N21: 98996
D22: Repairs and Maintenance | E22: 16637 | F22: 16322 | G22: 31147 | H22: 40893 | I22: 74145 | J22: 31668 | K22: 74178 | L22: 75866 | M22: 19263 | N22: 30516
D23: Utilities (Gas) | E23: 89255 | F23: 36123 | G23: 93706 | H23: 14274 | I23: 97467 | J23: 80641 | K23: 35927 | L23: 60622 | M23: 44395 | N23: 59486
D24: Cleaning | E24: 45395 | F24: 22307 | G24: 64842 | H24: 18005 | I24: 95351 | J24: 95944 | K24: 93252 | L24: 97762 | M24: 60413 | N24: 61898
D25: HVAC | E25: 70255 | F25: 69129 | G25: 89995 | H25: 69521 | I25: 23653 | J25: 10319 | K25: 13322 | L25: 67109 | M25: 79706 | N25: 29463
D26: Salaries and Professionals | E26: 29980 | F26: 42152 | G26: 87334 | H26: 74205 | I26: 88937 | J26: 66260 | K26: 54295 | L26: 17869 | M26: 53953 | N26: 51299
D27: Elevator | E27: 34868 | F27: 84190 | G27: 82162 | H27: 15530 | I27: 40924 | J27: 50438 | K27: 18089 | L27: 68001 | M27: 76958 | N27: 89889
D28: Management | E28: 85190 | F28: 77434 | G28: 42582 | H28: 82526 | I28: 24210 | J28: 63921 | K28: 82594 | L28: 76407 | M28: 26649 | N28: 22478
D29: TOTAL OPERATING EXPENSES | E29: =SUM(E20:E28) | F29: =SUM(F20:F28) | G29: =SUM(G20:G28) | H29: =SUM(H20:H28) | I29: =SUM(I20:I28) | J29: =SUM(J20:J28) | K29: =SUM(K20:K28) | L29: =SUM(L20:L28) | ... N29: =SUM(N20:N28)
D31: NET OPERATING INCOME | E31: =E17-E29 | F31: =F17-F29 | G31: =G17-G29 | H31: =H17-H29 | I31: =I17-I29 | J31: =J17-J29 | K31: =K17-K29 | L31: =L17-L29 | ... N31: =N17-N29
E32: 0 | F32: 0 | G32: 0 | H32: 0 | I32: 0 | J32: 0 | K32: 0 | L32: 0 | M32: 0 | N32: 0
D33: LEASING & CAPITAL COSTS
D34: Tenant Improvements | E34: 0 | F34: 0 | G34: 0 | H34: 0 | I34: 0 | J34: 435648.24 | K34: 0 | L34: 0 | M34: 0 | N34: 0
D35: Leasing Commissions | E35: 0 | F35: 0 | G35: 0 | H35: 0 | I35: 0 | J35: 897485.83 | K35: 0 | L35: 0 | M35: 0 | N35: 0
D36: Capital Improvements | E36: 250000 | F36: 250000 | G36: 0 | H36: 0 | I36: 0 | J36: 0 | K36: 0 | L36: 0 | M36: 0 | N36: 0
D37: Capital Reserves | E37: 91697.82 | F37: 94276.7 | G37: 96929.02 | H37: 99656.98 | I37: 102462.73 | J37: 75227.11 | K37: 109072.57 | L37: 112148.04 | M37: 115311.43 | N37: 118565.18
D38: TOTAL LEASING & CAPITAL COSTS | E38: =SUM(E34:E37) | F38: =SUM(F34:F37) | G38: =SUM(G34:G37) | H38: =SUM(H34:H37) | I38: =SUM(I34:I37) | J38: =SUM(J34:J37) | K38: =SUM(K34:K37) | L38: =SUM(L34:L37) | ... N38: =SUM(N34:N37)
D40: UNLEVERAGED CASH FLOW | E40: =E31-E38 | F40: =F31-F38 | G40: =G31-G38 | H40: =H31-H38 | I40: =I31-I38 | J40: =J31-J38 | K40: =K31-K38 | L40: =L31-L38 | ... N40: =N31-N38
E41: 0 | F41: 0 | G41: 0 | H41: 0 | I41: 0 | J41: 0 | K41: 0 | L41: 0 | M41: 0 | N41: 0
D42: DEBT SERVICE
D43: Interest | E43: 123456 | F43: =E43-5900 | G43: =F43-5900 | H43: =G43-5900 | I43: =H43-5900 | J43: =I43-5900 | K43: =J43-5900 | L43: =K43-5900 | M43: =L43-5900 | N43: =M43-5900
D44: Principle | E44: 235985 | F44: =E44+5900 | G44: =F44+5900 | H44: =G44+5900 | I44: =H44+5900 | J44: =I44+5900 | K44: =J44+5900 | L44: =K44+5900 | M44: =L44+5900 | N44: =M44+5900
D45: TOTAL DEBT SERVICE | E45: =SUM(E43:E44) | F45: =SUM(F43:F44) | G45: =SUM(G43:G44) | H45: =SUM(H43:H44) | I45: =SUM(I43:I44) | J45: =SUM(J43:J44) | K45: =SUM(K43:K44) | L45: =SUM(L43:L44) | ... N45: =SUM(N43:N44)
D47: LEVERAGED CASH FLOW | E47: =E40-E45 | F47: =F40-F45 | G47: =G40-G45 | H47: =H40-H45 | I47: =I40-I45 | J47: =J40-J45 | K47: =K40-K45 | L47: =L40-L45 | ... N47: =N40-N45
E48: 0 | F48: 0 | G48: 0 | H48: 0 | I48: 0 | J48: 0 | K48: 0 | L48: 0 | M48: 0 | N48: 0

Sheet Pres Summ
C3: UW PRESENTATION SUMMARY | H3: =Global!$G$7
F5: VALUATION RANGE
F6: Low | G6: Target | H6: High
D7: Purchase Price | F7: ='Exec Summ'!G21 | G7: ='Exec Summ'!H21 | H7: ='Exec Summ'!I21
D8: Per Square Foot | F8: ='Exec Summ'!G22 | G8: ='Exec Summ'!H22 | H8: ='Exec Summ'!I22
D9: Equity | F9: =F7-$E$27*F7 | G9: =G7-$E$27*G7 | H9: =H7-$E$27*H7
D10: Unleveraged IRR | F10: =VLOOKUP($E$23,'Exec Summ'!$D$30:$I$35,4,0) | G10: =VLOOKUP($E$23,'Exec Summ'!$D$30:$I$35,5,0) | H10: =VLOOKUP($E$23,'Exec Summ'!$D$30:$I$35,6,0)
D11: Leveraged IRR | F11: =VLOOKUP($E$23,'Exec Summ'!$D$38:$I$43,4,0) | G11: =VLOOKUP($E$23,'Exec Summ'!$D$38:$I$43,5,0) | H11: =VLOOKUP($E$23,'Exec Summ'!$D$38:$I$43,6,0)
D12: Year 1 Cash on Cash | F12: ='Sensitivity-Low'!E42 | G12: ='Return Metrics'!H42 | H12: ='Sensitivity-High'!E42
D13: Average Cash on Cash | F13: =AVERAGEIFS('Sensitivity-Low'!$E$42:$N$42,'Sensitivity-Low'!$E$5:$N$5,"<="&$E$23) | G13: =AVERAGEIFS('Return Metrics'!$H$42:$Q$42,'Return Metrics'!$H$5:$Q$5,"<="&$E$23) | H13: =AVERAGEIFS('Sensitivity-High'!$E$42:$N$42,'Sensitivity-High'!$E$5:$N$5,"<="&$E$23)
D15: Cap Rates
D16: In-Place Cap Rate | F16: ='Exec Summ'!G25 | G16: ='Exec Summ'!H25 | H16: ='Exec Summ'!I25
D17: Year 1 Cap Rate | F17: ='Exec Summ'!G26 | G17: ='Exec Summ'!H26 | H17: ='Exec Summ'!I26
D18: Stabilized Year 3 YOC | F18: ='Exec Summ'!G27 | G18: ='Exec Summ'!H27 | H18: ='Exec Summ'!I27
D20: Purchase/Exit Assumptions: | G20: General Assumptions:
D21: Exit Cap Rate | E21: ='Exec Summ'!F7 | G21: Rentable SF | H21: ='Exec Summ'!J7
D22: Cost of Exit Sale | E22: ='Exec Summ'!F9 | G22: In-Place Occupancy | H22: ='Exec Summ'!J8
D23: Hold Period | E23: ='Exec Summ'!F10 | G23: Yr. 1 Occupancy | H23: ='Exec Summ'!J9
G24: In-Place NOI (Month 1) | H24: ='Exec Summ'!J10
D26: Financing: | G26: Purchase Price / Funding
D27: Loan to Value | E27: ='Exec Summ'!F13 | G27: Purchase Price | H27: =G7
D28: Mid-Range Value | E28: ='Exec Summ'!F14 | G28: Debt | H28: =-E29
D29: Loan Amount | E29: ='Exec Summ'!F15 | G29: Equity | H29: =SUM(H27:H28)
D30: Amortization (Months) | E30: ='Exec Summ'!F16
D31: Interest Rate | E31: ='Exec Summ'!F17
D32: Interest Only (Months) | E32: ='Exec Summ'!F18

Sheet Exec Summ
D3: EXECUTIVE SUMMARY | P3: =Global!$G$7
E6: Purchase/Exit Assumptions: | H6: General Assumptions: | L6: Exit Cap Rate Sensitivity | N6: =O6-0.005 | O6: =F7 | P6: =O6+0.005
E7: Exit Cap Rate | F7: 0.085 | H7: Rentable SF | J7: =Global!G18 | L7: =$H$21
E8: Closing/Acq Costs | F8: 0.01 | H8: In-Place Occupancy | J8: =Global!G19 | L8: 3-Year UIRR | N8: =Z262 | O8: =H30 | P8: =AA262
E9: Cost of Exit Sale | F9: 0.02 | H9: Yr. 1 Occupancy | J9: ='Lease Audit '!C16 | L9: 5-Year UIRR | N9: =Z264 | O9: =H32 | P9: =AA264
E10: Hold Period | F10: 5 | H10: In-Place NOI (Month 1) | J10: =SUMIFS('Cash flow'!P:P,'Cash flow'!$A:$A,"Net Operating Income")*12 | L10: 7-Year UIRR | N10: =Z266 | O10: =H34 | P10: =AA266
E12: Financing: | H12: Loan Funding Schedule:
E13: Loan to Value | F13: 0.6 | H13: At Purchase | J13: ='Loan Calculation'!C6
E14: Mid-Range Value | F14: =H21 | H14: Year 1 (From Escrow) | J14: ='Loan Calculation'!K27
E15: Loan Amount | F15: =F14*F13 | H15: Year 2 (From Escrow) | J15: ='Loan Calculation'!K39
E16: Amortization (Months) | F16: =30*12 | H16: Year 3 (From Escrow) | J16: ='Loan Calculation'!K51
E17: Interest Rate | F17: 0.0675 | H17: Year 4 (From Escrow) | J17: ='Loan Calculation'!K63
E18: Interest Only (Months) | F18: 0 | H18: Total | J18: =SUM(J13:J17)
E21: PURCHASE PRICE | G21: =H21-$J$22 | H21: 16250000 | I21: =H21+$J$22 | J21: Increments:
E22: Per Square Foot | G22: =G21/$J$7 | H22: =H21/$J$7 | I22: =I21/$J$7 | J22: 250000
E24: Cap Rates
E25: In-Place Cap Rate | G25: =$J$10/G21 | H25: =$J$10/H21 | I25: =$J$10/I21
E26: Year 1 Cap Rate | G26: =$G$47/G21 | H26: =$G$47/H21 | I26: =$G$47/I21
E27: Year 3 Cap Rate | G27: =Proforma!$H$44/'Exec Summ'!G21 | H27: =Proforma!$H$44/'Exec Summ'!H21 | I27: =Proforma!$H$44/'Exec Summ'!I21
J28: IRR Breakdown:
E29: IRR Range - Unleveraged | J29: Cash Flow | K29: Exit Sale
D30: 3 | E30: 3-Year IRR | G30: =VLOOKUP($D30,'Sensitivity-Low'!$A$26:$C$31,3,0) | H30: =VLOOKUP($D30,'Return Metrics'!$D$26:$F$31,3,0) | I30: =VLOOKUP($D30,'Sensitivity-High'!$A$26:$C$31,3,0) | J30: =M82 | K30: =P82
D31: 4 | E31: 4-Year IRR | G31: =VLOOKUP($D31,'Sensitivity-Low'!$A$26:$C$31,3,0) | H31: =VLOOKUP($D31,'Return Metrics'!$D$26:$F$31,3,0) | I31: =VLOOKUP($D31,'Sensitivity-High'!$A$26:$C$31,3,0) | J31: =M93 | K31: =P93
D32: 5 | E32: 5-Year IRR | G32: =VLOOKUP($D32,'Sensitivity-Low'!$A$26:$C$31,3,0) | H32: =VLOOKUP($D32,'Return Metrics'!$D$26:$F$31,3,0) | I32: =VLOOKUP($D32,'Sensitivity-High'!$A$26:$C$31,3,0) | J32: =M105 | K32: =P105
D33: 6 | E33: 6-Year IRR | G33: =VLOOKUP($D33,'Sensitivity-Low'!$A$26:$C$31,3,0) | H33: =VLOOKUP($D33,'Return Metrics'!$D$26:$F$31,3,0) | I33: =VLOOKUP($D33,'Sensitivity-High'!$A$26:$C$31,3,0) | J33: =M118 | K33: =P118
D34: 7 | E34: 7-Year IRR | G34: =VLOOKUP($D34,'Sensitivity-Low'!$A$26:$C$31,3,0) | H34: =VLOOKUP($D34,'Return Metrics'!$D$26:$F$31,3,0) | I34: =VLOOKUP($D34,'Sensitivity-High'!$A$26:$C$31,3,0) | J34: =M132 | K34: =P132
D35: 10 | E35: 10-Year IRR | G35: =VLOOKUP($D35,'Sensitivity-Low'!$A$26:$C$31,3,0) | H35: =VLOOKUP($D35,'Return Metrics'!$D$26:$F$31,3,0) | I35: =VLOOKUP($D35,'Sensitivity-High'!$A$26:$C$31,3,0) | J35: =M149 | K35: =P149
E37: IRR Range - Leveraged
D38: 3 | E38: 3-Year IRR | G38: =VLOOKUP($D38,'Sensitivity-Low'!$A$48:$C$53,3,0) | H38: =VLOOKUP($D38,'Return Metrics'!$D$48:$F$53,3,0) | I38: =VLOOKUP($D38,'Sensitivity-High'!$A$48:$C$53,3,0)
D39: 4 | E39: 4-Year IRR | G39: =VLOOKUP($D39,'Sensitivity-Low'!$A$48:$C$53,3,0) | H39: =VLOOKUP($D39,'Return Metrics'!$D$48:$F$53,3,0) | I39: =VLOOKUP($D39,'Sensitivity-High'!$A$48:$C$53,3,0)
D40: 5 | E40: 5-Year IRR | G40: =VLOOKUP($D40,'Sensitivity-Low'!$A$48:$C$53,3,0) | H40: =VLOOKUP($D40,'Return Metrics'!$D$48:$F$53,3,0) | I40: =VLOOKUP($D40,'Sensitivity-High'!$A$48:$C$53,3,0)
D41: 6 | E41: 6-Year IRR | G41: =VLOOKUP($D41,'Sensitivity-Low'!$A$48:$C$53,3,0) | H41: =VLOOKUP($D41,'Return Metrics'!$D$48:$F$53,3,0) | I41: =VLOOKUP($D41,'Sensitivity-High'!$A$48:$C$53,3,0)
D42: 7 | E42: 7-Year IRR | G42: =VLOOKUP($D42,'Sensitivity-Low'!$A$48:$C$53,3,0) | H42: =VLOOKUP($D42,'Return Metrics'!$D$48:$F$53,3,0) | I42: =VLOOKUP($D42,'Sensitivity-High'!$A$48:$C$53,3,0)
D43: 10 | E43: 10-Year IRR | G43: =VLOOKUP($D43,'Sensitivity-Low'!$A$48:$C$53,3,0) | H43: =VLOOKUP($D43,'Return Metrics'!$D$48:$F$53,3,0) | I43: =VLOOKUP($D43,'Sensitivity-High'!$A$48:$C$53,3,0)
E45: CASH FLOW | F45: Purchase | G45: Year 1 | H45: Year 2 | I45: Year 3 | J45: Year 4 | K45: Year 5 | L45: Year 6 | M45: Year 7 | N45: Year 8 | O45: Year 9 | P45: Year 10 | R45: Year 11
E46: Purchase Price | F46: =-H21*(1+F8)
E47: Net Operating Income | G47: =SUMIFS('Cash flow'!C:C,'Cash flow'!$A:$A,$E$47) | H47: =SUMIFS('Cash flow'!D:D,'Cash flow'!$A:$A,$E$47) | I47: =SUMIFS('Cash flow'!E:E,'Cash flow'!$A:$A,$E$47) | J47: =SUMIFS('Cash flow'!F:F,'Cash flow'!$A:$A,$E$47) | K47: =SUMIFS('Cash flow'!G:G,'Cash flow'!$A:$A,$E$47) | L47: =SUMIFS('Cash flow'!H:H,'Cash flow'!$A:$A,$E$47) | M47: =SUMIFS('Cash flow'!I:I,'Cash flow'!$A:$A,$E$47) | N47: =SUMIFS('Cash flow'!J:J,'Cash flow'!$A:$A,$E$47) | O47: =SUMIFS('Cash flow'!K:K,'Cash flow'!$A:$A,$E$47) | P47: =SUMIFS('Cash flow'!L:L,'Cash flow'!$A:$A,$E$47) | R47: =SUMIFS('Cash flow'!M:M,'Cash flow'!$A:$A,$E$47)
E48: Total Leasing & Capital Costs | G48: =SUMIFS('Cash flow'!C:C,'Cash flow'!$A:$A,$E$48) | H48: =SUMIFS('Cash flow'!D:D,'Cash flow'!$A:$A,$E$48) | I48: =SUMIFS('Cash flow'!E:E,'Cash flow'!$A:$A,$E$48) | J48: =SUMIFS('Cash flow'!F:F,'Cash flow'!$A:$A,$E$48) | K48: =SUMIFS('Cash flow'!G:G,'Cash flow'!$A:$A,$E$48) | L48: =SUMIFS('Cash flow'!H:H,'Cash flow'!$A:$A,$E$48) | M48: =SUMIFS('Cash flow'!I:I,'Cash flow'!$A:$A,$E$48) | N48: =SUMIFS('Cash flow'!J:J,'Cash flow'!$A:$A,$E$48) | O48: =SUMIFS('Cash flow'!K:K,'Cash flow'!$A:$A,$E$48) | P48: =SUMIFS('Cash flow'!L:L,'Cash flow'!$A:$A,$E$48)
E49: Unleveraged Cash Flow | G49: =G47-G48 | H49: =H47-H48 | I49: =I47-I48 | J49: =J47-J48 | K49: =K47-K48 | L49: =L47-L48 | M49: =M47-M48 | N49: =N47-N48 | ... P49: =P47-P48
E50: Loan Funding | F50: ='Return Metrics'!G39 | G50: ='Return Metrics'!H39 | H50: ='Return Metrics'!I39 | I50: ='Return Metrics'!J39 | J50: ='Return Metrics'!K39
E51: Debt Service | G51: =-'Loan Calculation'!$I$27 | H51: =-'Loan Calculation'!$I$39 | I51: =-'Loan Calculation'!$I$51 | J51: =-'Loan Calculation'!$I$63 | K51: =-'Loan Calculation'!$I$75 | L51: =-'Loan Calculation'!$I$87 | M51: =-'Loan Calculation'!$I$99 | N51: =-'Loan Calculation'!$I$111 | O51: =-'Loan Calculation'!$I$123 | P51: =-'Loan Calculation'!$I$135
E52: Leveraged Cash Flow | F52: =SUM(F46:F51) | G52: =G49+G51 | H52: =H49+H51 | I52: =I49+I51 | J52: =J49+J51 | K52: =K49+K51 | L52: =L49+L51 | M52: =M49+M51 | N52: =N49+N51 | ... P52: =P49+P51
E53: Cash on Cash | G53: =-G52/$F52 | H53: =-H52/$F52 | I53: =-I52/$F52 | J53: =-J52/$F52 | K53: =-K52/$F52 | L53: =-L52/$F52 | M53: =-M52/$F52 | N53: =-N52/$F52 | ... P53: =-P52/$F52
E55: Exit Sale Prices | I55: =H75 | J55: =H85 | K55: =H96 | L55: =H108 | M55: =H121 | N55: =ROUND(O47/$F$7,-4) | O55: =ROUND(P47/$F$7,-4) | P55: =H135
E56: PSF | I56: =I55/$J$7 | J56: =J55/$J$7 | K56: =K55/$J$7 | L56: =L55/$J$7 | M56: =M55/$J$7 | N56: =N55/$J$7 | O56: =O55/$J$7 | P56: =P55/$J$7
E57: Cost of Sale | I57: =-H76 | J57: =-H86 | K57: =-H97 | L57: =-H109 | M57: =-H122 | N57: =-N55*$F$9 | O57: =-O55*$F$9 | P57: =-H136
E58: Loan Payoff | I58: =-'Loan Calculation'!G51 | J58: =-'Loan Calculation'!G63 | K58: =-'Loan Calculation'!G75 | L58: =-'Loan Calculation'!G87 | M58: =-'Loan Calculation'!G99 | N58: =-'Loan Calculation'!G111 | O58: =-'Loan Calculation'!G123 | P58: =-'Loan Calculation'!G135
E59: Net Exit Proceeds | I59: =I55+I57+I58 | J59: =J55+J57+J58 | K59: =K55+K57+K58 | L59: =L55+L57+L58 | M59: =M55+M57+M58 | N59: =N55+N57+N58 | O59: =O55+O57+O58 | P59: =P55+P57+P58
F66: Checks:
F67: Check Unleveraged Cash Flow: | G67: =G49-Proforma!F60 | H67: =H49-Proforma!G60 | I67: =I49-Proforma!H60 | J67: =J49-Proforma!I60 | K67: =K49-Proforma!J60 | L67: =L49-Proforma!K60 | M67: =M49-Proforma!L60 | N67: =N49-Proforma!M60 | ... P67: =P49-Proforma!O60 | R67: =IF(R47='Return Metrics'!R7,"ok","error")
F68: Check Leveraged Cash Flow: | G68: =G50-Proforma!F61 | H68: =H52-'Return Metrics'!I41 | I68: =I52-'Return Metrics'!J41 | J68: =J52-'Return Metrics'!K41 | K68: =K52-'Return Metrics'!L41 | L68: =L52-'Return Metrics'!M41 | M68: =M52-'Return Metrics'!N41 | N68: =N52-'Return Metrics'!O41 | O68: =O52-'Return Metrics'!P41 | P68: =P52-'Return Metrics'!Q41
F69: Check Net Exit Proceeds: | I69: =I59-'Return Metrics'!J45 | J69: =J59-'Return Metrics'!K45 | K69: =K59-'Return Metrics'!L45 | L69: =L59-'Return Metrics'!M45 | M69: =M59-'Return Metrics'!N45 | N69: =N59-'Return Metrics'!O45 | O69: =O59-'Return Metrics'!P45 | P69: =P59-'Return Metrics'!Q45
E72: UNLEVERAGED IRR
E73: 3-Year IRR
E74: Purchase Price | G74: =G$21 | H74: =H$21 | I74: =I$21 | L74: =Z$259 | M74: =AB$275 | U74: =AD$275 | V74: =AA$259 | W74: =AF$275
E75: Exit Sale Price | G75: =ROUND($J47/$F$7,-4) | H75: =ROUND($J47/$F$7,-4) | I75: =ROUND($J47/$F$7,-4) | K75: =$J47/$Z$257 | L75: =$J47/$Z$257 | M75: =$J47/$Z$257 | U75: =$J47/$AA$257 | V75: =$J47/$AA$257 | W75: =$J47/$AA$257
E76: Cost of Exit Sale | G76: =G75*$F$9 | H76: =H75*$F$9 | I76: =I75*$F$9 | K76: =K75*$F$9 | L76: =L75*$F$9 | R76: Total | U76: =U75*$F$9 | V76: =V75*$F$9 | W76: =W75*$F$9 | Y76: =$J49 | Z76: =$J49 | AA76: =$J49
K77: Cash Flow Only | L77: Discounted | N77: Exit Sale Only | O77: Discounted | R77: Discounted | Y77: =$K49 | Z77: =$K49 | AA77: =$K49
F78: Purchase | G78: =-G74 | H78: =-H74 | I78: =-I74 | U78: =-U74 | V78: =-V74 | W78: =-W74 | Y78: =$L49 | Z78: =$L49 | AA78: =$L49
F79: 1 | G79: =$G49 | H79: =$G49 | I79: =$G49 | K79: =H79 | L79: =K79/(1+$H$30) | N79: 0 | O79: =N79/(1+$H$30) | R79: =L79+O79 | U79: =$G49 | V79: =$G49 | W79: =$G49 | Y79: =$M49+#REF!-X69 | Z79: =$M49+#REF!-Y69 | AA79: =$M49+#REF!-Z69
F80: 2 | G80: =$H49 | H80: =$H49 | I80: =$H49 | K80: =H80 | L80: =K80/(1+$H$30)^F80 | N80: 0 | O80: =N80/(1+$H$30)^F80 | R80: =L80+O80
F81: 3 | G81: =$I49+G75-G76 | H81: =$I49+H75-H76 | I81: =$I49+I75-I76 | K81: =H81-H75+H76 | L81: =K81/(1+$H$30)^F81 | N81: =H81-K81 | O81: =N81/(1+$H$30)^F81 | R81: =L81+O81
L82: =SUM(L78:L81) | M82: =L82/R82 | O82: =SUM(O78:O81) | P82: =O82/R82 | R82: =SUM(R79:R81)
E83: 4-Year IRR
E84: Purchase Price | G84: =G$21 | H84: =H$21 | I84: =I$21 | L84: =Z$259 | M84: =AB$275
E85: Exit Sale Price | G85: =ROUND($K47/$F$7,-4) | H85: =ROUND($K47/$F$7,-4) | I85: =ROUND($K47/$F$7,-4) | K85: =$K47/$Z$257 | L85: =$K47/$Z$257 | M85: =$K47/$Z$257
E86: Cost of Exit Sale | G86: =G85*$F$9 | H86: =H85*$F$9 | I86: =I85*$F$9 | K86: =K85*$F$9 | L86: =L85*$F$9 | R86: Total
K87: Cash Flow Only | L87: Discounted | N87: Exit Sale Only | O87: Discounted | R87: Discounted
F88: Purchase | G88: =-G84 | H88: =-H84 | I88: =-I84
F89: 1 | G89: =$G49 | H89: =$G49 | I89: =$G49 | K89: =H89 | L89: =K89/(1+$H$31) | N89: 0 | O89: =N89/(1+$H$31) | R89: =L89+O89
F90: 2 | G90: =$H49 | H90: =$H49 | I90: =$H49 | K90: =H90 | L90: =K90/(1+$H$31)^F90 | N90: 0 | O90: =N90/(1+$H$31)^F90 | R90: =L90+O90
F91: 3 | G91: =$I49 | H91: =$I49 | I91: =$I49 | K91: =H91 | L91: =K91/(1+$H$31)^F91 | N91: 0 | O91: =N91/(1+$H$31)^F91 | R91: =L91+O91
F92: 4 | G92: =$J49+G85-G86 | H92: =$J49+H85-H86 | I92: =$J49+I85-I86 | K92: =H92-H$85+H$86 | L92: =K92/(1+$H$31)^F92 | N92: =H92-K92 | O92: =N92/(1+$H$31)^F92 | R92: =L92+O92
L93: =SUM(L89:L92) | M93: =L93/R93 | O93: =SUM(O89:O92) | P93: =O93/R93 | R93: =SUM(R89:R92)
E94: 5-Year IRR
E95: Purchase Price | G95: =G$21 | H95: =H$21 | I95: =I$21 | L95: =Z$259 | M95: =AB$275
E96: Exit Sale Price | G96: =ROUND($L47/$F$7,-4) | H96: =ROUND($L47/$F$7,-4) | I96: =ROUND($L47/$F$7,-4) | K96: =$L47/$Z$257 | L96: =$L47/$Z$257 | M96: =$L47/$Z$257
E97: Cost of Exit Sale | G97: =G96*$F$9 | H97: =H96*$F$9 | I97: =I96*$F$9 | R97: Total
K98: Cash Flow Only | L98: Discounted | N98: Exit Sale Only | O98: Discounted | R98: Discounted
F99: Purchase | G99: =-G95 | H99: =-H95 | I99: =-I95
F100: 1 | G100: =$G49 | H100: =$G49 | I100: =$G49 | K100: =H100 | L100: =K100/(1+$H$32) | N100: 0 | O100: =N100/(1+$H$32) | R100: =L100+O100
F101: 2 | G101: =$H49 | H101: =$H49 | I101: =$H49 | K101: =H101 | L101: =K101/(1+$H$32)^F101 | N101: 0 | O101: =N101/(1+$H$32)^F101 | R101: =L101+O101
F102: 3 | G102: =$I49 | H102: =$I49 | I102: =$I49 | K102: =H102 | L102: =K102/(1+$H$32)^F102 | N102: 0 | O102: =N102/(1+$H$32)^F102 | R102: =L102+O102
F103: 4 | G103: =$J49 | H103: =$J49 | I103: =$J49 | K103: =H103 | L103: =K103/(1+$H$32)^F103 | N103: 0 | O103: =N103/(1+$H$32)^F103 | R103: =L103+O103
F104: 5 | G104: =$K49+G96-G97 | H104: =$K49+H96-H97 | I104: =$K49+I96-I97 | K104: =H104-H96+H97 | L104: =K104/(1+$H$32)^F104 | N104: =H96-H97 | O104: =N104/(1+$H$32)^F104 | R104: =L104+O104
L105: =SUM(L100:L104) | M105: =L105/R105 | O105: =SUM(O100:O104) | P105: =O105/R105 | R105: =SUM(R100:R104)
E106: 6-Year IRR
E107: Purchase Price | G107: =G$21 | H107: =H$21 | I107: =I$21
E108: Exit Sale Price | G108: =ROUND($M$47/$F$7,-4) | H108: =ROUND($M$47/$F$7,-4) | I108: =ROUND($M$47/$F$7,-4)
E109: Cost of Exit Sale | G109: =G108*$F$9 | H109: =H108*$F$9 | I109: =I108*$F$9 | R109: Total
K110: Cash Flow Only | L110: Discounted | N110: Exit Sale Only | O110: Discounted | R110: Discounted
F111: Purchase | G111: =-G107 | H111: =-H107 | I111: =-I107
F112: 1 | G112: =$G49 | H112: =$G49 | I112: =$G49 | K112: =H112 | L112: =K112/(1+$H$33) | N112: 0 | O112: =N112/(1+$H$33) | R112: =L112+O112
F113: 2 | G113: =$H49 | H113: =$H49 | I113: =$H49 | K113: =H113 | L113: =K113/(1+$H$33)^F113 | N113: 0 | O113: =N113/(1+$H$33)^F113 | R113: =L113+O113
F114: 3 | G114: =$I49 | H114: =$I49 | I114: =$I49 | K114: =H114 | L114: =K114/(1+$H$33)^F114 | N114: 0 | O114: =N114/(1+$H$33)^F114 | R114: =L114+O114
F115: 4 | G115: =$J49 | H115: =$J49 | I115: =$J49 | K115: =H115 | L115: =K115/(1+$H$33)^F115 | N115: 0 | O115: =N115/(1+$H$33)^F115 | R115: =L115+O115
F116: 5 | G116: =$K49 | H116: =$K49 | I116: =$K49 | K116: =H116 | L116: =K116/(1+$H$33)^F116 | N116: 0 | O116: =N116/(1+$H$33)^F116 | R116: =L116+O116
F117: 6 | G117: =$L49+G108-G109 | H117: =$L49+H108-H109 | I117: =$L49+I108-I109 | K117: =H117-H108+H109 | L117: =K117/(1+$H$33)^F117 | N117: =H117-K117 | O117: =N117/(1+$H$33)^F117 | R117: =L117+O117
L118: =SUM(L112:L117) | M118: =L118/R118 | O118: =SUM(O112:O117) | P118: =O118/R118 | R118: =SUM(R112:R117)
E119: 7-Year IRR
...

Sheet Annual Cash Flow (3)
C3: ANNUAL CASH FLOW | N3: =Global!G7
E5: 1 | F5: =E5+1 | G5: =F5+1 | H5: =G5+1 | I5: =H5+1 | J5: =I5+1 | K5: =J5+1 | L5: =K5+1 | M5: =L5+1 | N5: =M5+1 | O5: x
E6: 46295 | F6: =EOMONTH(E6,12) | G6: =EOMONTH(F6,12) | H6: =EOMONTH(G6,12) | I6: =EOMONTH(H6,12) | J6: =EOMONTH(I6,12) | K6: =EOMONTH(J6,12) | L6: =EOMONTH(K6,12) | M6: =EOMONTH(L6,12) | N6: =EOMONTH(M6,12) | O6: x
O7: x
D8: INCOME
D9: Base Rental Revenue | E9: =SUMIFS(Proforma!F:F,Proforma!$D:$D,'Annual Cash Flow (3)'!$D9) | F9: =SUMIFS(Proforma!G:G,Proforma!$D:$D,'Annual Cash Flow (3)'!$D9) | G9: =SUMIFS(Proforma!H:H,Proforma!$D:$D,'Annual Cash Flow (3)'!$D9) | H9: =SUMIFS(Proforma!I:I,Proforma!$D:$D,'Annual Cash Flow (3)'!$D9) | I9: =SUMIFS(Proforma!J:J,Proforma!$D:$D,'Annual Cash Flow (3)'!$D9) | J9: =SUMIFS(Proforma!K:K,Proforma!$D:$D,'Annual Cash Flow (3)'!$D9) | K9: =SUMIFS(Proforma!L:L,Proforma!$D:$D,'Annual Cash Flow (3)'!$D9) | L9: =SUMIFS(Proforma!M:M,Proforma!$D:$D,'Annual Cash Flow (3)'!$D9) | M9: =SUMIFS(Proforma!N:N,Proforma!$D:$D,'Annual Cash Flow (3)'!$D9) | N9: =SUMIFS(Proforma!O:O,Proforma!$D:$D,'Annual Cash Flow (3)'!$D9)
D10: Absorption and Turnover Vacancy | E10: =SUMIFS(Proforma!F:F,Proforma!$D:$D,'Annual Cash Flow (3)'!$D10) | F10: =SUMIFS(Proforma!G:G,Proforma!$D:$D,'Annual Cash Flow (3)'!$D10) | G10: =SUMIFS(Proforma!H:H,Proforma!$D:$D,'Annual Cash Flow (3)'!$D10) | H10: =SUMIFS(Proforma!I:I,Proforma!$D:$D,'Annual Cash Flow (3)'!$D10) | I10: =SUMIFS(Proforma!J:J,Proforma!$D:$D,'Annual Cash Flow (3)'!$D10) | J10: =SUMIFS(Proforma!K:K,Proforma!$D:$D,'Annual Cash Flow (3)'!$D10) | K10: =SUMIFS(Proforma!L:L,Proforma!$D:$D,'Annual Cash Flow (3)'!$D10) | L10: =SUMIFS(Proforma!M:M,Proforma!$D:$D,'Annual Cash Flow (3)'!$D10) | M10: =SUMIFS(Proforma!N:N,Proforma!$D:$D,'Annual Cash Flow (3)'!$D10) | N10: =SUMIFS(Proforma!O:O,Proforma!$D:$D,'Annual Cash Flow (3)'!$D10)
D11: Total Scheduled Base Rent | E11: =SUM(E9:E10) | F11: =SUM(F9:F10) | G11: =SUM(G9:G10) | H11: =SUM(H9:H10) | I11: =SUM(I9:I10) | J11: =SUM(J9:J10) | K11: =SUM(K9:K10) | L11: =SUM(L9:L10) | ... N11: =SUM(N9:N10)
D12: CAM Recovery | E12: =SUMIFS(Proforma!F:F,Proforma!$D:$D,'Annual Cash Flow (3)'!$D12) | F12: =SUMIFS(Proforma!G:G,Proforma!$D:$D,'Annual Cash Flow (3)'!$D12) | G12: =SUMIFS(Proforma!H:H,Proforma!$D:$D,'Annual Cash Flow (3)'!$D12) | H12: =SUMIFS(Proforma!I:I,Proforma!$D:$D,'Annual Cash Flow (3)'!$D12) | I12: =SUMIFS(Proforma!J:J,Proforma!$D:$D,'Annual Cash Flow (3)'!$D12) | J12: =SUMIFS(Proforma!K:K,Proforma!$D:$D,'Annual Cash Flow (3)'!$D12) | K12: =SUMIFS(Proforma!L:L,Proforma!$D:$D,'Annual Cash Flow (3)'!$D12) | L12: =SUMIFS(Proforma!M:M,Proforma!$D:$D,'Annual Cash Flow (3)'!$D12) | M12: =SUMIFS(Proforma!N:N,Proforma!$D:$D,'Annual Cash Flow (3)'!$D12) | N12: =SUMIFS(Proforma!O:O,Proforma!$D:$D,'Annual Cash Flow (3)'!$D12)
D13: Realty Tax Recovery | E13: =SUMIFS(Proforma!F:F,Proforma!$D:$D,'Annual Cash Flow (3)'!$D13) | F13: =SUMIFS(Proforma!G:G,Proforma!$D:$D,'Annual Cash Flow (3)'!$D13) | G13: =SUMIFS(Proforma!H:H,Proforma!$D:$D,'Annual Cash Flow (3)'!$D13) | H13: =SUMIFS(Proforma!I:I,Proforma!$D:$D,'Annual Cash Flow (3)'!$D13) | I13: =SUMIFS(Proforma!J:J,Proforma!$D:$D,'Annual Cash Flow (3)'!$D13) | J13: =SUMIFS(Proforma!K:K,Proforma!$D:$D,'Annual Cash Flow (3)'!$D13) | K13: =SUMIFS(Proforma!L:L,Proforma!$D:$D,'Annual Cash Flow (3)'!$D13) | L13: =SUMIFS(Proforma!M:M,Proforma!$D:$D,'Annual Cash Flow (3)'!$D13) | M13: =SUMIFS(Proforma!N:N,Proforma!$D:$D,'Annual Cash Flow (3)'!$D13) | N13: =SUMIFS(Proforma!O:O,Proforma!$D:$D,'Annual Cash Flow (3)'!$D13)
D14: Total Expense Reimbursements | E14: =SUM(E11:E13) | F14: =SUM(F11:F13) | G14: =SUM(G11:G13) | H14: =SUM(H11:H13) | I14: =SUM(I11:I13) | J14: =SUM(J11:J13) | K14: =SUM(K11:K13) | L14: =SUM(L11:L13) | ... N14: =SUM(N11:N13)
D15: Parking Revenue | E15: =SUMIFS(Proforma!F:F,Proforma!$D:$D,'Annual Cash Flow (3)'!$D15) | F15: =SUMIFS(Proforma!G:G,Proforma!$D:$D,'Annual Cash Flow (3)'!$D15) | G15: =SUMIFS(Proforma!H:H,Proforma!$D:$D,'Annual Cash Flow (3)'!$D15) | H15: =SUMIFS(Proforma!I:I,Proforma!$D:$D,'Annual Cash Flow (3)'!$D15) | I15: =SUMIFS(Proforma!J:J,Proforma!$D:$D,'Annual Cash Flow (3)'!$D15) | J15: =SUMIFS(Proforma!K:K,Proforma!$D:$D,'Annual Cash Flow (3)'!$D15) | K15: =SUMIFS(Proforma!L:L,Proforma!$D:$D,'Annual Cash Flow (3)'!$D15) | L15: =SUMIFS(Proforma!M:M,Proforma!$D:$D,'Annual Cash Flow (3)'!$D15) | M15: =SUMIFS(Proforma!N:N,Proforma!$D:$D,'Annual Cash Flow (3)'!$D15) | N15: =SUMIFS(Proforma!O:O,Proforma!$D:$D,'Annual Cash Flow (3)'!$D15)
D16: Total Gross Revenue | E16: =SUM(E14:E15) | F16: =SUM(F14:F15) | G16: =SUM(G14:G15) | H16: =SUM(H14:H15) | I16: =SUM(I14:I15) | J16: =SUM(J14:J15) | K16: =SUM(K14:K15) | L16: =SUM(L14:L15) | ... N16: =SUM(N14:N15)
D17: General Vacancy Loss | E17: =SUMIFS(Proforma!F:F,Proforma!$D:$D,'Annual Cash Flow (3)'!$D17) | F17: =SUMIFS(Proforma!G:G,Proforma!$D:$D,'Annual Cash Flow (3)'!$D17) | G17: =SUMIFS(Proforma!H:H,Proforma!$D:$D,'Annual Cash Flow (3)'!$D17) | H17: =SUMIFS(Proforma!I:I,Proforma!$D:$D,'Annual Cash Flow (3)'!$D17) | I17: =SUMIFS(Proforma!J:J,Proforma!$D:$D,'Annual Cash Flow (3)'!$D17) | J17: =SUMIFS(Proforma!K:K,Proforma!$D:$D,'Annual Cash Flow (3)'!$D17) | K17: =SUMIFS(Proforma!L:L,Proforma!$D:$D,'Annual Cash Flow (3)'!$D17) | L17: =SUMIFS(Proforma!M:M,Proforma!$D:$D,'Annual Cash Flow (3)'!$D17) | M17: =SUMIFS(Proforma!N:N,Proforma!$D:$D,'Annual Cash Flow (3)'!$D17) | N17: =SUMIFS(Proforma!O:O,Proforma!$D:$D,'Annual Cash Flow (3)'!$D17)
D18: EFFECTIVE GROSS INCOME | E18: =SUM(E16:E17) | F18: =SUM(F16:F17) | G18: =SUM(G16:G17) | H18: =SUM(H16:H17) | I18: =SUM(I16:I17) | J18: =SUM(J16:J17) | K18: =SUM(K16:K17) | L18: =SUM(L16:L17) | ... N18: =SUM(N16:N17)
E19: 0 | F19: 0 | G19: 0 | H19: 0 | I19: 0 | J19: 0 | K19: 0 | L19: 0 | M19: 0 | N19: 0
D20: OPERATING EXPENSES
D21: Municipal Taxes | E21: =SUMIFS(Proforma!F:F,Proforma!$D:$D,'Annual Cash Flow (3)'!$D21) | F21: =SUMIFS(Proforma!G:G,Proforma!$D:$D,'Annual Cash Flow (3)'!$D21) | G21: =SUMIFS(Proforma!H:H,Proforma!$D:$D,'Annual Cash Flow (3)'!$D21) | H21: =SUMIFS(Proforma!I:I,Proforma!$D:$D,'Annual Cash Flow (3)'!$D21) | I21: =SUMIFS(Proforma!J:J,Proforma!$D:$D,'Annual Cash Flow (3)'!$D21) | J21: =SUMIFS(Proforma!K:K,Proforma!$D:$D,'Annual Cash Flow (3)'!$D21) | K21: =SUMIFS(Proforma!L:L,Proforma!$D:$D,'Annual Cash Flow (3)'!$D21) | L21: =SUMIFS(Proforma!M:M,Proforma!$D:$D,'Annual Cash Flow (3)'!$D21) | M21: =SUMIFS(Proforma!N:N,Proforma!$D:$D,'Annual Cash Flow (3)'!$D21) | N21: =SUMIFS(Proforma!O:O,Proforma!$D:$D,'Annual Cash Flow (3)'!$D21)
D22: Insurance | E22: =SUMIFS(Proforma!F:F,Proforma!$D:$D,'Annual Cash Flow (3)'!$D22) | F22: =SUMIFS(Proforma!G:G,Proforma!$D:$D,'Annual Cash Flow (3)'!$D22) | G22: =SUMIFS(Proforma!H:H,Proforma!$D:$D,'Annual Cash Flow (3)'!$D22) | H22: =SUMIFS(Proforma!I:I,Proforma!$D:$D,'Annual Cash Flow (3)'!$D22) | I22: =SUMIFS(Proforma!J:J,Proforma!$D:$D,'Annual Cash Flow (3)'!$D22) | J22: =SUMIFS(Proforma!K:K,Proforma!$D:$D,'Annual Cash Flow (3)'!$D22) | K22: =SUMIFS(Proforma!L:L,Proforma!$D:$D,'Annual Cash Flow (3)'!$D22) | L22: =SUMIFS(Proforma!M:M,Proforma!$D:$D,'Annual Cash Flow (3)'!$D22) | M22: =SUMIFS(Proforma!N:N,Proforma!$D:$D,'Annual Cash Flow (3)'!$D22) | N22: =SUMIFS(Proforma!O:O,Proforma!$D:$D,'Annual Cash Flow (3)'!$D22)
D23: Repairs and Maintenance | E23: =SUMIFS(Proforma!F:F,Proforma!$D:$D,'Annual Cash Flow (3)'!$D23) | F23: =SUMIFS(Proforma!G:G,Proforma!$D:$D,'Annual Cash Flow (3)'!$D23) | G23: =SUMIFS(Proforma!H:H,Proforma!$D:$D,'Annual Cash Flow (3)'!$D23) | H23: =SUMIFS(Proforma!I:I,Proforma!$D:$D,'Annual Cash Flow (3)'!$D23) | I23: =SUMIFS(Proforma!J:J,Proforma!$D:$D,'Annual Cash Flow (3)'!$D23) | J23: =SUMIFS(Proforma!K:K,Proforma!$D:$D,'Annual Cash Flow (3)'!$D23) | K23: =SUMIFS(Proforma!L:L,Proforma!$D:$D,'Annual Cash Flow (3)'!$D23) | L23: =SUMIFS(Proforma!M:M,Proforma!$D:$D,'Annual Cash Flow (3)'!$D23) | M23: =SUMIFS(Proforma!N:N,Proforma!$D:$D,'Annual Cash Flow (3)'!$D23) | N23: =SUMIFS(Proforma!O:O,Proforma!$D:$D,'Annual Cash Flow (3)'!$D23)
D24: Utilities (Gas) | E24: =SUMIFS(Proforma!F:F,Proforma!$D:$D,'Annual Cash Flow (3)'!$D24) | F24: =SUMIFS(Proforma!G:G,Proforma!$D:$D,'Annual Cash Flow (3)'!$D24) | G24: =SUMIFS(Proforma!H:H,Proforma!$D:$D,'Annual Cash Flow (3)'!$D24) | H24: =SUMIFS(Proforma!I:I,Proforma!$D:$D,'Annual Cash Flow (3)'!$D24) | I24: =SUMIFS(Proforma!J:J,Proforma!$D:$D,'Annual Cash Flow (3)'!$D24) | J24: =SUMIFS(Proforma!K:K,Proforma!$D:$D,'Annual Cash Flow (3)'!$D24) | K24: =SUMIFS(Proforma!L:L,Proforma!$D:$D,'Annual Cash Flow (3)'!$D24) | L24: =SUMIFS(Proforma!M:M,Proforma!$D:$D,'Annual Cash Flow (3)'!$D24) | M24: =SUMIFS(Proforma!N:N,Proforma!$D:$D,'Annual Cash Flow (3)'!$D24) | N24: =SUMIFS(Proforma!O:O,Proforma!$D:$D,'Annual Cash Flow (3)'!$D24)
D25: Cleaning | E25: =SUMIFS(Proforma!F:F,Proforma!$D:$D,'Annual Cash Flow (3)'!$D25) | F25: =SUMIFS(Proforma!G:G,Proforma!$D:$D,'Annual Cash Flow (3)'!$D25) | G25: =SUMIFS(Proforma!H:H,Proforma!$D:$D,'Annual Cash Flow (3)'!$D25) | H25: =SUMIFS(Proforma!I:I,Proforma!$D:$D,'Annual Cash Flow (3)'!$D25) | I25: =SUMIFS(Proforma!J:J,Proforma!$D:$D,'Annual Cash Flow (3)'!$D25) | J25: =SUMIFS(Proforma!K:K,Proforma!$D:$D,'Annual Cash Flow (3)'!$D25) | K25: =SUMIFS(Proforma!L:L,Proforma!$D:$D,'Annual Cash Flow (3)'!$D25) | L25: =SUMIFS(Proforma!M:M,Proforma!$D:$D,'Annual Cash Flow (3)'!$D25) | M25: =SUMIFS(Proforma!N:N,Proforma!$D:$D,'Annual Cash Flow (3)'!$D25) | N25: =SUMIFS(Proforma!O:O,Proforma!$D:$D,'Annual Cash Flow (3)'!$D25)
D26: HVAC | E26: =SUMIFS(Proforma!F:F,Proforma!$D:$D,'Annual Cash Flow (3)'!$D26) | F26: =SUMIFS(Proforma!G:G,Proforma!$D:$D,'Annual Cash Flow (3)'!$D26) | G26: =SUMIFS(Proforma!H:H,Proforma!$D:$D,'Annual Cash Flow (3)'!$D26) | H26: =SUMIFS(Proforma!I:I,Proforma!$D:$D,'Annual Cash Flow (3)'!$D26) | I26: =SUMIFS(Proforma!J:J,Proforma!$D:$D,'Annual Cash Flow (3)'!$D26) | J26: =SUMIFS(Proforma!K:K,Proforma!$D:$D,'Annual Cash Flow (3)'!$D26) | K26: =SUMIFS(Proforma!L:L,Proforma!$D:$D,'Annual Cash Flow (3)'!$D26) | L26: =SUMIFS(Proforma!M:M,Proforma!$D:$D,'Annual Cash Flow (3)'!$D26) | M26: =SUMIFS(Proforma!N:N,Proforma!$D:$D,'Annual Cash Flow (3)'!$D26) | N26: =SUMIFS(Proforma!O:O,Proforma!$D:$D,'Annual Cash Flow (3)'!$D26)
D27: Salaries and Professionals | E27: =SUMIFS(Proforma!F:F,Proforma!$D:$D,'Annual Cash Flow (3)'!$D27) | F27: =SUMIFS(Proforma!G:G,Proforma!$D:$D,'Annual Cash Flow (3)'!$D27) | G27: =SUMIFS(Proforma!H:H,Proforma!$D:$D,'Annual Cash Flow (3)'!$D27) | H27: =SUMIFS(Proforma!I:I,Proforma!$D:$D,'Annual Cash Flow (3)'!$D27) | I27: =SUMIFS(Proforma!J:J,Proforma!$D:$D,'Annual Cash Flow (3)'!$D27) | J27: =SUMIFS(Proforma!K:K,Proforma!$D:$D,'Annual Cash Flow (3)'!$D27) | K27: =SUMIFS(Proforma!L:L,Proforma!$D:$D,'Annual Cash Flow (3)'!$D27) | L27: =SUMIFS(Proforma!M:M,Proforma!$D:$D,'Annual Cash Flow (3)'!$D27) | M27: =SUMIFS(Proforma!N:N,Proforma!$D:$D,'Annual Cash Flow (3)'!$D27) | N27: =SUMIFS(Proforma!O:O,Proforma!$D:$D,'Annual Cash Flow (3)'!$D27)
D28: Elevator | E28: =SUMIFS(Proforma!F:F,Proforma!$D:$D,'Annual Cash Flow (3)'!$D28) | F28: =SUMIFS(Proforma!G:G,Proforma!$D:$D,'Annual Cash Flow (3)'!$D28) | G28: =SUMIFS(Proforma!H:H,Proforma!$D:$D,'Annual Cash Flow (3)'!$D28) | H28: =SUMIFS(Proforma!I:I,Proforma!$D:$D,'Annual Cash Flow (3)'!$D28) | I28: =SUMIFS(Proforma!J:J,Proforma!$D:$D,'Annual Cash Flow (3)'!$D28) | J28: =SUMIFS(Proforma!K:K,Proforma!$D:$D,'Annual Cash Flow (3)'!$D28) | K28: =SUMIFS(Proforma!L:L,Proforma!$D:$D,'Annual Cash Flow (3)'!$D28) | L28: =SUMIFS(Proforma!M:M,Proforma!$D:$D,'Annual Cash Flow (3)'!$D28) | M28: =SUMIFS(Proforma!N:N,Proforma!$D:$D,'Annual Cash Flow (3)'!$D28) | N28: =SUMIFS(Proforma!O:O,Proforma!$D:$D,'Annual Cash Flow (3)'!$D28)
D29: Management | E29: =SUMIFS(Proforma!F:F,Proforma!$D:$D,'Annual Cash Flow (3)'!$D29) | F29: =SUMIFS(Proforma!G:G,Proforma!$D:$D,'Annual Cash Flow (3)'!$D29) | G29: =SUMIFS(Proforma!H:H,Proforma!$D:$D,'Annual Cash Flow (3)'!$D29) | H29: =SUMIFS(Proforma!I:I,Proforma!$D:$D,'Annual Cash Flow (3)'!$D29) | I29: =SUMIFS(Proforma!J:J,Proforma!$D:$D,'Annual Cash Flow (3)'!$D29) | J29: =SUMIFS(Proforma!K:K,Proforma!$D:$D,'Annual Cash Flow (3)'!$D29) | K29: =SUMIFS(Proforma!L:L,Proforma!$D:$D,'Annual Cash Flow (3)'!$D29) | L29: =SUMIFS(Proforma!M:M,Proforma!$D:$D,'Annual Cash Flow (3)'!$D29) | M29: =SUMIFS(Proforma!N:N,Proforma!$D:$D,'Annual Cash Flow (3)'!$D29) | N29: =SUMIFS(Proforma!O:O,Proforma!$D:$D,'Annual Cash Flow (3)'!$D29)
D30: TOTAL OPERATING EXPENSES | E30: =SUM(E21:E29) | F30: =SUM(F21:F29) | G30: =SUM(G21:G29) | H30: =SUM(H21:H29) | I30: =SUM(I21:I29) | J30: =SUM(J21:J29) | K30: =SUM(K21:K29) | L30: =SUM(L21:L29) | ... N30: =SUM(N21:N29)
D32: NET OPERATING INCOME | E32: =E18-E30 | F32: =F18-F30 | G32: =G18-G30 | H32: =H18-H30 | I32: =I18-I30 | J32: =J18-J30 | K32: =K18-K30 | L32: =L18-L30 | ... N32: =N18-N30
E33: 0 | F33: 0 | G33: 0 | H33: 0 | I33: 0 | J33: 0 | K33: 0 | L33: 0 | M33: 0 | N33: 0
D34: LEASING & CAPITAL COSTS
D35: Tenant Improvements | E35: =SUMIFS(Proforma!F:F,Proforma!$D:$D,'Annual Cash Flow (3)'!$D35) | F35: =SUMIFS(Proforma!G:G,Proforma!$D:$D,'Annual Cash Flow (3)'!$D35) | G35: =SUMIFS(Proforma!H:H,Proforma!$D:$D,'Annual Cash Flow (3)'!$D35) | H35: =SUMIFS(Proforma!I:I,Proforma!$D:$D,'Annual Cash Flow (3)'!$D35) | I35: =SUMIFS(Proforma!J:J,Proforma!$D:$D,'Annual Cash Flow (3)'!$D35) | J35: =SUMIFS(Proforma!K:K,Proforma!$D:$D,'Annual Cash Flow (3)'!$D35) | K35: =SUMIFS(Proforma!L:L,Proforma!$D:$D,'Annual Cash Flow (3)'!$D35) | L35: =SUMIFS(Proforma!M:M,Proforma!$D:$D,'Annual Cash Flow (3)'!$D35) | M35: =SUMIFS(Proforma!N:N,Proforma!$D:$D,'Annual Cash Flow (3)'!$D35) | N35: =SUMIFS(Proforma!O:O,Proforma!$D:$D,'Annual Cash Flow (3)'!$D35)
D36: Leasing Commissions | E36: =SUMIFS(Proforma!F:F,Proforma!$D:$D,'Annual Cash Flow (3)'!$D36) | F36: =SUMIFS(Proforma!G:G,Proforma!$D:$D,'Annual Cash Flow (3)'!$D36) | G36: =SUMIFS(Proforma!H:H,Proforma!$D:$D,'Annual Cash Flow (3)'!$D36) | H36: =SUMIFS(Proforma!I:I,Proforma!$D:$D,'Annual Cash Flow (3)'!$D36) | I36: =SUMIFS(Proforma!J:J,Proforma!$D:$D,'Annual Cash Flow (3)'!$D36) | J36: =SUMIFS(Proforma!K:K,Proforma!$D:$D,'Annual Cash Flow (3)'!$D36) | K36: =SUMIFS(Proforma!L:L,Proforma!$D:$D,'Annual Cash Flow (3)'!$D36) | L36: =SUMIFS(Proforma!M:M,Proforma!$D:$D,'Annual Cash Flow (3)'!$D36) | M36: =SUMIFS(Proforma!N:N,Proforma!$D:$D,'Annual Cash Flow (3)'!$D36) | N36: =SUMIFS(Proforma!O:O,Proforma!$D:$D,'Annual Cash Flow (3)'!$D36)
D37: Capital Improvements | E37: =SUMIFS(Proforma!F:F,Proforma!$D:$D,'Annual Cash Flow (3)'!$D37) | F37: =SUMIFS(Proforma!G:G,Proforma!$D:$D,'Annual Cash Flow (3)'!$D37) | G37: =SUMIFS(Proforma!H:H,Proforma!$D:$D,'Annual Cash Flow (3)'!$D37) | H37: =SUMIFS(Proforma!I:I,Proforma!$D:$D,'Annual Cash Flow (3)'!$D37) | I37: =SUMIFS(Proforma!J:J,Proforma!$D:$D,'Annual Cash Flow (3)'!$D37) | J37: =SUMIFS(Proforma!K:K,Proforma!$D:$D,'Annual Cash Flow (3)'!$D37) | K37: =SUMIFS(Proforma!L:L,Proforma!$D:$D,'Annual Cash Flow (3)'!$D37) | L37: =SUMIFS(Proforma!M:M,Proforma!$D:$D,'Annual Cash Flow (3)'!$D37) | M37: =SUMIFS(Proforma!N:N,Proforma!$D:$D,'Annual Cash Flow (3)'!$D37) | N37: =SUMIFS(Proforma!O:O,Proforma!$D:$D,'Annual Cash Flow (3)'!$D37)
D38: Structural Reserve / CAPEX | E38: =SUMIFS(Proforma!F:F,Proforma!$D:$D,'Annual Cash Flow (3)'!$D38) | F38: =SUMIFS(Proforma!G:G,Proforma!$D:$D,'Annual Cash Flow (3)'!$D38) | G38: =SUMIFS(Proforma!H:H,Proforma!$D:$D,'Annual Cash Flow (3)'!$D38) | H38: =SUMIFS(Proforma!I:I,Proforma!$D:$D,'Annual Cash Flow (3)'!$D38) | I38: =SUMIFS(Proforma!J:J,Proforma!$D:$D,'Annual Cash Flow (3)'!$D38) | J38: =SUMIFS(Proforma!K:K,Proforma!$D:$D,'Annual Cash Flow (3)'!$D38) | K38: =SUMIFS(Proforma!L:L,Proforma!$D:$D,'Annual Cash Flow (3)'!$D38) | L38: =SUMIFS(Proforma!M:M,Proforma!$D:$D,'Annual Cash Flow (3)'!$D38) | M38: =SUMIFS(Proforma!N:N,Proforma!$D:$D,'Annual Cash Flow (3)'!$D38) | N38: =SUMIFS(Proforma!O:O,Proforma!$D:$D,'Annual Cash Flow (3)'!$D38)
D39: TOTAL LEASING & CAPITAL COSTS | E39: =SUM(E35:E38) | F39: =SUM(F35:F38) | G39: =SUM(G35:G38) | H39: =SUM(H35:H38) | I39: =SUM(I35:I38) | J39: =SUM(J35:J38) | K39: =SUM(K35:K38) | L39: =SUM(L35:L38) | ... N39: =SUM(N35:N38)
D41: UNLEVERAGED CASH FLOW | E41: =E32-E39 | F41: =F32-F39 | G41: =G32-G39 | H41: =H32-H39 | I41: =I32-I39 | J41: =J32-J39 | K41: =K32-K39 | L41: =L32-L39 | ... N41: =N32-N39
E42: 0 | F42: 0 | G42: 0 | H42: 0 | I42: 0 | J42: 0 | K42: 0 | L42: 0 | M42: 0 | N42: 0
D43: DEBT SERVICE
D44: Interest | E44: 0 | F44: =E44-5900 | G44: =F44-5900 | H44: =G44-5900 | I44: =H44-5900 | J44: =I44-5900 | K44: =J44-5900 | L44: =K44-5900 | M44: =L44-5900 | N44: =M44-5900
D45: Principle | E45: 0 | F45: =E45+5900 | G45: =F45+5900 | H45: =G45+5900 | I45: =H45+5900 | J45: =I45+5900 | K45: =J45+5900 | L45: =K45+5900 | M45: =L45+5900 | N45: =M45+5900
D46: TOTAL DEBT SERVICE | E46: =SUM(E44:E45) | F46: =SUM(F44:F45) | G46: =SUM(G44:G45) | H46: =SUM(H44:H45) | I46: =SUM(I44:I45) | J46: =SUM(J44:J45) | K46: =SUM(K44:K45) | L46: =SUM(L44:L45) | ... N46: =SUM(N44:N45)
D48: LEVERAGED CASH FLOW | E48: =E41-E46 | F48: =F41-F46 | G48: =G41-G46 | H48: =H41-H46 | I48: =I41-I46 | J48: =J41-J46 | K48: =K41-K46 | L48: =L41-L46 | ... N48: =N41-N46
E49: 0 | F49: 0 | G49: 0 | H49: 0 | I49: 0 | J49: 0 | K49: 0 | L49: 0 | M49: 0 | N49: 0

Sheet Return Metrics
C3: RETURN METRICS | S3: =Global!$G$7
G5: Investment | H5: 1 | I5: 2 | J5: 3 | K5: 4 | L5: 5 | M5: 6 | N5: 7 | O5: 8 | P5: 9 | Q5: 10 | R5: 11
E7: Net Operating Income | H7: =SUMIFS('Cash flow'!C:C,'Cash flow'!$A:$A,$E$7) | I7: =SUMIFS('Cash flow'!D:D,'Cash flow'!$A:$A,$E$7) | J7: =SUMIFS('Cash flow'!E:E,'Cash flow'!$A:$A,$E$7) | K7: =SUMIFS('Cash flow'!F:F,'Cash flow'!$A:$A,$E$7) | L7: =SUMIFS('Cash flow'!G:G,'Cash flow'!$A:$A,$E$7) | M7: =SUMIFS('Cash flow'!H:H,'Cash flow'!$A:$A,$E$7) | N7: =SUMIFS('Cash flow'!I:I,'Cash flow'!$A:$A,$E$7) | O7: =SUMIFS('Cash flow'!J:J,'Cash flow'!$A:$A,$E$7) | P7: =SUMIFS('Cash flow'!K:K,'Cash flow'!$A:$A,$E$7) | Q7: =SUMIFS('Cash flow'!L:L,'Cash flow'!$A:$A,$E$7) | R7: =SUMIFS('Cash flow'!M:M,'Cash flow'!$A:$A,$E$7)
E8: Total Leasing & Capital Costs | H8: =SUMIFS('Cash flow'!C:C,'Cash flow'!$A:$A,$E$8) | I8: =SUMIFS('Cash flow'!D:D,'Cash flow'!$A:$A,$E$8) | J8: =SUMIFS('Cash flow'!E:E,'Cash flow'!$A:$A,$E$8) | K8: =SUMIFS('Cash flow'!F:F,'Cash flow'!$A:$A,$E$8) | L8: =SUMIFS('Cash flow'!G:G,'Cash flow'!$A:$A,$E$8) | M8: =SUMIFS('Cash flow'!H:H,'Cash flow'!$A:$A,$E$8) | N8: =SUMIFS('Cash flow'!I:I,'Cash flow'!$A:$A,$E$8) | O8: =SUMIFS('Cash flow'!J:J,'Cash flow'!$A:$A,$E$8) | P8: =SUMIFS('Cash flow'!K:K,'Cash flow'!$A:$A,$E$8) | Q8: =SUMIFS('Cash flow'!L:L,'Cash flow'!$A:$A,$E$8)
E9: Unleveraged Cash Flow | H9: =H7-H8 | I9: =I7-I8 | J9: =J7-J8 | K9: =K7-K8 | L9: =L7-L8 | M9: =M7-M8 | N9: =N7-N8 | O9: =O7-O8 | ... Q9: =Q7-Q8
E11: Property Sale | J11: =ROUND(K7/$F$19,-4) | K11: =ROUND(L7/$F$19,-4) | L11: =ROUND(M7/$F$19,-4) | M11: =ROUND(N7/$F$19,-4) | N11: =ROUND(O7/$F$19,-4) | O11: =ROUND(P7/$F$19,-4) | P11: =ROUND(Q7/$F$19,-4) | Q11: =ROUND(R7/$F$19,-4)
E12: PSF | J12: =J11/'Exec Summ'!$J$7 | K12: =K11/'Exec Summ'!$J$7 | L12: =L11/'Exec Summ'!$J$7 | M12: =M11/'Exec Summ'!$J$7 | N12: =N11/'Exec Summ'!$J$7 | O12: =O11/'Exec Summ'!$J$7 | P12: =P11/'Exec Summ'!$J$7 | Q12: =Q11/'Exec Summ'!$J$7
E13: Cost of Sale | J13: =-J11*$F$21 | K13: =-K11*$F$21 | L13: =-L11*$F$21 | M13: =-M11*$F$21 | N13: =-N11*$F$21 | O13: =-O11*$F$21 | P13: =-P11*$F$21 | Q13: =-Q11*$F$21
E14: Net Sale Proceeds | J14: =J11+J13 | K14: =K11+K13 | L14: =L11+L13 | M14: =M11+M13 | N14: =N11+N13 | O14: =O11+O13 | P14: =P11+P13 | Q14: =Q11+Q13
E16: Unleveraged Returns: | G16: PSF
E17: Purchase Price | F17: ='Exec Summ'!H21 | G17: =F17/'Exec Summ'!$J$7
E18: Total Cost | F18: =F17*(1+F20) | G18: =F18/'Exec Summ'!$J$7
E19: Exit Cap Rate | F19: ='Exec Summ'!F7
E20: Closing/Acq Costs | F20: ='Exec Summ'!F8
E21: Cost of Sale | F21: ='Exec Summ'!F9
E23: NOI Return on Cost | H23: =H7/$F$18 | I23: =I7/$F$18 | J23: =J7/$F$18 | K23: =K7/$F$18 | L23: =L7/$F$18 | M23: =M7/$F$18 | N23: =N7/$F$18 | O23: =O7/$F$18 | ... R23: =R7/$F$18
E24: Net Cash Flow Return on Cost | H24: =H9/$F$18 | I24: =I9/$F$18 | J24: =J9/$F$18 | K24: =K9/$F$18 | L24: =L9/$F$18 | M24: =M9/$F$18 | N24: =N9/$F$18 | O24: =O9/$F$18 | ... R24: =R9/$F$18
D26: 3 | E26: 3-Year IRR | F26: =IRR(G26:J26) | G26: =-$F$18 | H26: =H9 | I26: =I9 | J26: =J9+J14
D27: =D26+1 | E27: 4-Year IRR | F27: =IRR(G27:K27) | G27: =-$F$18 | H27: =H26 | I27: =I26 | J27: =J9 | K27: =K9+K14
D28: =D27+1 | E28: 5-Year IRR | F28: =IRR(G28:L28) | G28: =-$F$18 | H28: =H27 | I28: =I27 | J28: =J27 | K28: =K9 | L28: =L9+L14
D29: =D28+1 | E29: 6-Year IRR | F29: =IRR(G29:M29) | G29: =-$F$18 | H29: =H28 | I29: =I28 | J29: =J28 | K29: =K28 | L29: =L9 | M29: =M9+M14
D30: =D29+1 | E30: 7-Year IRR | F30: =IRR(G30:N30) | G30: =-$F$18 | H30: =H29 | I30: =I29 | J30: =J29 | K30: =K29 | L30: =L29 | M30: =M9 | N30: =N9+N14
D31: 10 | E31: 10-Year IRR | F31: =IRR(G31:Q31) | G31: =-$F$18 | H31: =H30 | I31: =I30 | J31: =J30 | K31: =K30 | L31: =L30 | M31: =M30 | N31: =N9 | O31: =O9 | P31: =P9 | Q31: =Q9+Q14
E33: Leveraged Cash Flow:
E34: Loan to Value % | F34: ='Exec Summ'!F13
E35: Loan Amount | F35: ='Exec Summ'!F15
E36: Amortization (Months) | F36: ='Exec Summ'!F16
E37: Interest Rate | F37: ='Exec Summ'!F17
E38: Monthly Loan Payment | F38: =PMT(F37/12,F36,F35)
E39: Loan Funding | G39: ='Exec Summ'!J13 | H39: ='Exec Summ'!J14 | I39: ='Exec Summ'!J15 | J39: ='Exec Summ'!J16 | K39: ='Exec Summ'!J17
E40: Debt Service | H40: =-'Loan Calculation'!$I$27 | I40: =-'Loan Calculation'!$I$39 | J40: =-'Loan Calculation'!$I$51 | K40: =-'Loan Calculation'!$I$63 | L40: =-'Loan Calculation'!$I$75 | M40: =-'Loan Calculation'!$I$87 | N40: =-'Loan Calculation'!$I$99 | O40: =-'Loan Calculation'!$I$111 | P40: =-'Loan Calculation'!$I$123 | Q40: =-'Loan Calculation'!$I$135
E41: Net Cash Flow | G41: =G9+G39+G40-F18 | H41: =H9+H39+H40 | I41: =I9+I39+I40 | J41: =J9+J39+J40 | K41: =K9+K39+K40 | L41: =L9+L39+L40 | M41: =M9+M39+M40 | N41: =N9+N39+N40 | O41: =O9+O39+O40 | ... Q41: =Q9+Q39+Q40
E42: Cash on Cash | H42: =-H41/$G41 | I42: =-I41/$G41 | J42: =-J41/$G41 | K42: =-K41/$G41 | L42: =-L41/$G41 | M42: =-M41/$G41 | N42: =-N41/$G41 | O42: =-O41/$G41 | ... Q42: =-Q41/$G41
E44: Loan Payoff | J44: =-'Loan Calculation'!G51 | K44: =-'Loan Calculation'!G63 | L44: =-'Loan Calculation'!G75 | M44: =-'Loan Calculation'!G87 | N44: =-'Loan Calculation'!G99 | O44: =-'Loan Calculation'!G111 | P44: =-'Loan Calculation'!G123 | Q44: =-'Loan Calculation'!G135
E45: Net Sale Proceeds After Loan Payoff | J45: =J14+J44 | K45: =K14+K44 | L45: =L14+L44 | M45: =M14+M44 | N45: =N14+N44 | O45: =O14+O44 | P45: =P14+P44 | Q45: =Q14+Q44
E47: Leveraged IRR:
D48: 3 | E48: 3-Year IRR | F48: =IRR(G48:J48) | G48: =G41 | H48: =H41 | I48: =I41 | J48: =J41+J45
D49: =D48+1 | E49: 4-Year IRR | F49: =IRR(G49:K49) | G49: =G48 | H49: =H48 | I49: =I48 | J49: =J41 | K49: =K41+K45
D50: =D49+1 | E50: 5-Year IRR | F50: =IRR(G50:L50) | G50: =G49 | H50: =H49 | I50: =I49 | J50: =J49 | K50: =K41 | L50: =L41+L45
D51: =D50+1 | E51: 6-Year IRR | F51: =IRR(G51:M51) | G51: =G50 | H51: =H50 | I51: =I50 | J51: =J50 | K51: =K50 | L51: =L41 | M51: =M41+M45
D52: =D51+1 | E52: 7-Year IRR | F52: =IRR(G52:N52) | G52: =G51 | H52: =H51 | I52: =I51 | J52: =J51 | K52: =K51 | L52: =L51 | M52: =M41 | N52: =N41+N45
D53: 10 | E53: 10-Year IRR | F53: =IRR(G53:Q53) | G53: =G52 | H53: =H52 | I53: =I52 | J53: =J52 | K53: =K52 | L53: =L52 | M53: =M52 | N53: =N41 | O53: =O41 | P53: =P41 | Q53: =Q41+Q45
F59: Check IRR's:
F60: =SUM(F26:F31)-SUM('Exec Summ'!H30:H35)
F61: =SUM(F48:F53)-SUM('Exec Summ'!H38:H43)

Sheet Sensitivity-Low
B2: RETURN METRICS
D5: Investment | E5: 1 | F5: 2 | G5: 3 | H5: 4 | I5: 5 | J5: 6 | K5: 7 | L5: 8 | M5: 9 | N5: 10 | O5: 11
B7: Net Operating Income | E7: ='Return Metrics'!H7 | F7: ='Return Metrics'!I7 | G7: ='Return Metrics'!J7 | H7: ='Return Metrics'!K7 | I7: ='Return Metrics'!L7 | J7: ='Return Metrics'!M7 | K7: ='Return Metrics'!N7 | L7: ='Return Metrics'!O7 | ... O7: ='Return Metrics'!R7
B8: Total Leasing & Capital Costs | E8: ='Return Metrics'!H8 | F8: ='Return Metrics'!I8 | G8: ='Return Metrics'!J8 | H8: ='Return Metrics'!K8 | I8: ='Return Metrics'!L8 | J8: ='Return Metrics'!M8 | K8: ='Return Metrics'!N8 | L8: ='Return Metrics'!O8 | ... N8: ='Return Metrics'!Q8
B9: Unleveraged Cash Flow | E9: =E7-E8 | F9: =F7-F8 | G9: =G7-G8 | H9: =H7-H8 | I9: =I7-I8 | J9: =J7-J8 | K9: =K7-K8 | L9: =L7-L8 | ... N9: =N7-N8
B11: Property Sale | G11: =ROUND(H7/$C$19,-4) | H11: =ROUND(I7/$C$19,-4) | I11: =ROUND(J7/$C$19,-4) | J11: =ROUND(K7/$C$19,-4) | K11: =ROUND(L7/$C$19,-4) | L11: =ROUND(M7/$C$19,-4) | M11: =ROUND(N7/$C$19,-4) | N11: =ROUND(O7/$C$19,-4)
B12: PSF | G12: =G11/'Exec Summ'!$J$7 | H12: =H11/'Exec Summ'!$J$7 | I12: =I11/'Exec Summ'!$J$7 | J12: =J11/'Exec Summ'!$J$7 | K12: =K11/'Exec Summ'!$J$7 | L12: =L11/'Exec Summ'!$J$7 | M12: =M11/'Exec Summ'!$J$7 | N12: =N11/'Exec Summ'!$J$7
B13: Cost of Sale | G13: =-G11*$C$21 | H13: =-H11*$C$21 | I13: =-I11*$C$21 | J13: =-J11*$C$21 | K13: =-K11*$C$21 | L13: =-L11*$C$21 | M13: =-M11*$C$21 | N13: =-N11*$C$21
B14: Net Sale Proceeds | G14: =G11+G13 | H14: =H11+H13 | I14: =I11+I13 | J14: =J11+J13 | K14: =K11+K13 | L14: =L11+L13 | M14: =M11+M13 | N14: =N11+N13
B16: Unleveraged Returns: | D16: PSF
B17: Purchase Price | C17: ='Pres Summ'!F7 | D17: =C17/'Exec Summ'!$J$7
B18: Total Cost | C18: =C17*(1+C20) | D18: =C18/'Exec Summ'!$J$7
B19: Exit Cap Rate | C19: ='Exec Summ'!F7
B20: Closing/Acq Costs | C20: ='Exec Summ'!F8
B21: Cost of Sale | C21: ='Exec Summ'!F9
B23: NOI Return on Cost | E23: =E7/$C$18 | F23: =F7/$C$18 | G23: =G7/$C$18 | H23: =H7/$C$18 | I23: =I7/$C$18 | J23: =J7/$C$18 | K23: =K7/$C$18 | L23: =L7/$C$18 | ... O23: =O7/$C$18
B24: Net Cash Flow Return on Cost | E24: =E9/$C$18 | F24: =F9/$C$18 | G24: =G9/$C$18 | H24: =H9/$C$18 | I24: =I9/$C$18 | J24: =J9/$C$18 | K24: =K9/$C$18 | L24: =L9/$C$18 | ... O24: =O9/$C$18
A26: 3 | B26: 3-Year IRR | C26: =IRR(D26:G26) | D26: =-$C$18 | E26: =E9 | F26: =F9 | G26: =G9+G14
A27: =A26+1 | B27: 4-Year IRR | C27: =IRR(D27:H27) | D27: =-$C$18 | E27: =E26 | F27: =F26 | G27: =G9 | H27: =H9+H14
A28: =A27+1 | B28: 5-Year IRR | C28: =IRR(D28:I28) | D28: =-$C$18 | E28: =E27 | F28: =F27 | G28: =G27 | H28: =H9 | I28: =I9+I14
A29: =A28+1 | B29: 6-Year IRR | C29: =IRR(D29:J29) | D29: =-$C$18 | E29: =E28 | F29: =F28 | G29: =G28 | H29: =H28 | I29: =I9 | J29: =J9+J14
A30: =A29+1 | B30: 7-Year IRR | C30: =IRR(D30:K30) | D30: =-$C$18 | E30: =E29 | F30: =F29 | G30: =G29 | H30: =H29 | I30: =I29 | J30: =J9 | K30: =K9+K14
A31: 10 | B31: 10-Year IRR | C31: =IRR(D31:N31) | D31: =-$C$18 | E31: =E30 | F31: =F30 | G31: =G30 | H31: =H30 | I31: =I30 | J31: =J30 | K31: =K9 | L31: =L9 | M31: =M9 | N31: =N9+N14
B33: Leveraged Cash Flow:
B34: Loan to Value % | C34: ='Exec Summ'!F13
B35: Loan Amount | C35: =C17*C34
B36: Amortization (Months) | C36: ='Exec Summ'!F16
B37: Interest Rate | C37: ='Exec Summ'!F17
B38: Monthly Loan Payment | C38: =PMT(C37/12,C36,C35)
B39: Loan Funding | D39: =C35 | E39: ='Exec Summ'!J14 | F39: ='Exec Summ'!J15 | G39: ='Exec Summ'!J16 | H39: ='Exec Summ'!J17
B40: Debt Service | E40: =-IF(E5<='Exec Summ'!$F$18/12,'Sensitivity-Low'!$C$35*'Sensitivity-Low'!$C$37,PMT($C$37/12,$C$36,-$C$35)*12) | F40: =-IF(F5<='Exec Summ'!$F$18/12,'Sensitivity-Low'!$C$35*'Sensitivity-Low'!$C$37,PMT($C$37/12,$C$36,-$C$35)*12) | G40: =-IF(G5<='Exec Summ'!$F$18/12,'Sensitivity-Low'!$C$35*'Sensitivity-Low'!$C$37,PMT($C$37/12,$C$36,-$C$35)*12) | H40: =-IF(H5<='Exec Summ'!$F$18/12,'Sensitivity-Low'!$C$35*'Sensitivity-Low'!$C$37,PMT($C$37/12,$C$36,-$C$35)*12) | I40: =-IF(I5<='Exec Summ'!$F$18/12,'Sensitivity-Low'!$C$35*'Sensitivity-Low'!$C$37,PMT($C$37/12,$C$36,-$C$35)*12) | J40: =-IF(J5<='Exec Summ'!$F$18/12,'Sensitivity-Low'!$C$35*'Sensitivity-Low'!$C$37,PMT($C$37/12,$C$36,-$C$35)*12) | K40: =-IF(K5<='Exec Summ'!$F$18/12,'Sensitivity-Low'!$C$35*'Sensitivity-Low'!$C$37,PMT($C$37/12,$C$36,-$C$35)*12) | L40: =-IF(L5<='Exec Summ'!$F$18/12,'Sensitivity-Low'!$C$35*'Sensitivity-Low'!$C$37,PMT($C$37/12,$C$36,-$C$35)*12) | ... N40: =-IF(N5<='Exec Summ'!$F$18/12,'Sensitivity-Low'!$C$35*'Sensitivity-Low'!$C$37,PMT($C$37/12,$C$36,-$C$35)*12)
B41: Net Cash Flow | D41: =D9+D39+D40-C18 | E41: =E9+E39+E40 | F41: =F9+F39+F40 | G41: =G9+G39+G40 | H41: =H9+H39+H40 | I41: =I9+I39+I40 | J41: =J9+J39+J40 | K41: =K9+K39+K40 | L41: =L9+L39+L40 | ... N41: =N9+N39+N40
B42: Cash on Cash | E42: =-E41/$D41 | F42: =-F41/$D41 | G42: =-G41/$D41 | H42: =-H41/$D41 | I42: =-I41/$D41 | J42: =-J41/$D41 | K42: =-K41/$D41 | L42: =-L41/$D41 | ... N42: =-N41/$D41
B44: Loan Payoff | G44: =FV($C$37/12,(G$5*12)-('Exec Summ'!$F$18),$C$38,$C$35) | H44: =FV($C$37/12,(H$5*12)-('Exec Summ'!$F$18),$C$38,$C$35) | I44: =FV($C$37/12,(I$5*12)-('Exec Summ'!$F$18),$C$38,$C$35) | J44: =FV($C$37/12,(J$5*12)-('Exec Summ'!$F$18),$C$38,$C$35) | K44: =FV($C$37/12,(K$5*12)-('Exec Summ'!$F$18),$C$38,$C$35) | L44: =FV($C$37/12,(L$5*12)-('Exec Summ'!$F$18),$C$38,$C$35) | M44: =FV($C$37/12,(M$5*12)-('Exec Summ'!$F$18),$C$38,$C$35) | N44: =FV($C$37/12,(N$5*12)-('Exec Summ'!$F$18),$C$38,$C$35)
B45: Net Sale Proceeds After Loan Payoff | G45: =G14+G44 | H45: =H14+H44 | I45: =I14+I44 | J45: =J14+J44 | K45: =K14+K44 | L45: =L14+L44 | M45: =M14+M44 | N45: =N14+N44
B47: Leveraged IRR:
A48: 3 | B48: 3-Year IRR | C48: =IRR(D48:G48) | D48: =D41 | E48: =E41 | F48: =F41 | G48: =G41+G45
A49: =A48+1 | B49: 4-Year IRR | C49: =IRR(D49:H49) | D49: =D48 | E49: =E48 | F49: =F48 | G49: =G41 | H49: =H41+H45
A50: =A49+1 | B50: 5-Year IRR | C50: =IRR(D50:I50) | D50: =D49 | E50: =E49 | F50: =F49 | G50: =G49 | H50: =H41 | I50: =I41+I45
A51: =A50+1 | B51: 6-Year IRR | C51: =IRR(D51:J51) | D51: =D50 | E51: =E50 | F51: =F50 | G51: =G50 | H51: =H50 | I51: =I41 | J51: =J41+J45
A52: =A51+1 | B52: 7-Year IRR | C52: =IRR(D52:K52) | D52: =D51 | E52: =E51 | F52: =F51 | G52: =G51 | H52: =H51 | I52: =I51 | J52: =J41 | K52: =K41+K45
A53: 10 | B53: 10-Year IRR | C53: =IRR(D53:N53) | D53: =D52 | E53: =E52 | F53: =F52 | G53: =G52 | H53: =H52 | I53: =I52 | J53: =J52 | K53: =K41 | L53: =L41 | M53: =M41 | N53: =N41+N45
C59: Check IRR's:
C60: =SUM(C26:C31)-SUM('Exec Summ'!G30:G35)
C61: =SUM(C48:C53)-SUM('Exec Summ'!G38:G43)

Sheet Sensitivity-High
B2: RETURN METRICS
D5: Investment | E5: 1 | F5: 2 | G5: 3 | H5: 4 | I5: 5 | J5: 6 | K5: 7 | L5: 8 | M5: 9 | N5: 10 | O5: 11
B7: Net Operating Income | E7: ='Return Metrics'!H7 | F7: ='Return Metrics'!I7 | G7: ='Return Metrics'!J7 | H7: ='Return Metrics'!K7 | I7: ='Return Metrics'!L7 | J7: ='Return Metrics'!M7 | K7: ='Return Metrics'!N7 | L7: ='Return Metrics'!O7 | ... O7: ='Return Metrics'!R7
B8: Total Leasing & Capital Costs | E8: ='Return Metrics'!H8 | F8: ='Return Metrics'!I8 | G8: ='Return Metrics'!J8 | H8: ='Return Metrics'!K8 | I8: ='Return Metrics'!L8 | J8: ='Return Metrics'!M8 | K8: ='Return Metrics'!N8 | L8: ='Return Metrics'!O8 | ... N8: ='Return Metrics'!Q8
B9: Unleveraged Cash Flow | E9: =E7-E8 | F9: =F7-F8 | G9: =G7-G8 | H9: =H7-H8 | I9: =I7-I8 | J9: =J7-J8 | K9: =K7-K8 | L9: =L7-L8 | ... N9: =N7-N8
B11: Property Sale | G11: =ROUND(H7/$C$19,-4) | H11: =ROUND(I7/$C$19,-4) | I11: =ROUND(J7/$C$19,-4) | J11: =ROUND(K7/$C$19,-4) | K11: =ROUND(L7/$C$19,-4) | L11: =ROUND(M7/$C$19,-4) | M11: =ROUND(N7/$C$19,-4) | N11: =ROUND(O7/$C$19,-4)
B12: PSF | G12: =G11/'Exec Summ'!$J$7 | H12: =H11/'Exec Summ'!$J$7 | I12: =I11/'Exec Summ'!$J$7 | J12: =J11/'Exec Summ'!$J$7 | K12: =K11/'Exec Summ'!$J$7 | L12: =L11/'Exec Summ'!$J$7 | M12: =M11/'Exec Summ'!$J$7 | N12: =N11/'Exec Summ'!$J$7
B13: Cost of Sale | G13: =-G11*$C$21 | H13: =-H11*$C$21 | I13: =-I11*$C$21 | J13: =-J11*$C$21 | K13: =-K11*$C$21 | L13: =-L11*$C$21 | M13: =-M11*$C$21 | N13: =-N11*$C$21
B14: Net Sale Proceeds | G14: =G11+G13 | H14: =H11+H13 | I14: =I11+I13 | J14: =J11+J13 | K14: =K11+K13 | L14: =L11+L13 | M14: =M11+M13 | N14: =N11+N13
B16: Unleveraged Returns: | D16: PSF
B17: Purchase Price | C17: ='Pres Summ'!H7 | D17: =C17/'Exec Summ'!$J$7
B18: Total Cost | C18: =C17*(1+C20) | D18: =C18/'Exec Summ'!$J$7
B19: Exit Cap Rate | C19: ='Exec Summ'!F7
B20: Closing/Acq Costs | C20: ='Exec Summ'!$F$8
B21: Cost of Sale | C21: ='Exec Summ'!F9
B23: NOI Return on Cost | E23: =E7/$C$18 | F23: =F7/$C$18 | G23: =G7/$C$18 | H23: =H7/$C$18 | I23: =I7/$C$18 | J23: =J7/$C$18 | K23: =K7/$C$18 | L23: =L7/$C$18 | ... O23: =O7/$C$18
B24: Net Cash Flow Return on Cost | E24: =E9/$C$18 | F24: =F9/$C$18 | G24: =G9/$C$18 | H24: =H9/$C$18 | I24: =I9/$C$18 | J24: =J9/$C$18 | K24: =K9/$C$18 | L24: =L9/$C$18 | ... O24: =O9/$C$18
A26: 3 | B26: 3-Year IRR | C26: =IRR(D26:G26) | D26: =-$C$18 | E26: =E9 | F26: =F9 | G26: =G9+G14
A27: =A26+1 | B27: 4-Year IRR | C27: =IRR(D27:H27) | D27: =-$C$18 | E27: =E26 | F27: =F26 | G27: =G9 | H27: =H9+H14
A28: =A27+1 | B28: 5-Year IRR | C28: =IRR(D28:I28) | D28: =-$C$18 | E28: =E27 | F28: =F27 | G28: =G27 | H28: =H9 | I28: =I9+I14
A29: =A28+1 | B29: 6-Year IRR | C29: =IRR(D29:J29) | D29: =-$C$18 | E29: =E28 | F29: =F28 | G29: =G28 | H29: =H28 | I29: =I9 | J29: =J9+J14
A30: =A29+1 | B30: 7-Year IRR | C30: =IRR(D30:K30) | D30: =-$C$18 | E30: =E29 | F30: =F29 | G30: =G29 | H30: =H29 | I30: =I29 | J30: =J9 | K30: =K9+K14
A31: 10 | B31: 10-Year IRR | C31: =IRR(D31:N31) | D31: =-$C$18 | E31: =E30 | F31: =F30 | G31: =G30 | H31: =H30 | I31: =I30 | J31: =J30 | K31: =K9 | L31: =L9 | M31: =M9 | N31: =N9+N14
B33: Leveraged Cash Flow:
B34: Loan to Value % | C34: ='Exec Summ'!F13
B35: Loan Amount | C35: =C17*C34
B36: Amortization (Months) | C36: ='Exec Summ'!F16
B37: Interest Rate | C37: ='Exec Summ'!F17
B38: Monthly Loan Payment | C38: =PMT(C37/12,C36,C35)
B39: Loan Funding | D39: =C35 | E39: ='Exec Summ'!J14 | F39: ='Exec Summ'!J15 | G39: ='Exec Summ'!J16 | H39: ='Exec Summ'!J17
B40: Debt Service | E40: =-IF(E$5<='Exec Summ'!$F$18/12,'Sensitivity-High'!$C$35*'Sensitivity-High'!$C$37,PMT($C$37/12,$C$36,-$C$35)*12) | F40: =-IF(F$5<='Exec Summ'!$F$18/12,'Sensitivity-High'!$C$35*'Sensitivity-High'!$C$37,PMT($C$37/12,$C$36,-$C$35)*12) | G40: =-IF(G$5<='Exec Summ'!$F$18/12,'Sensitivity-High'!$C$35*'Sensitivity-High'!$C$37,PMT($C$37/12,$C$36,-$C$35)*12) | H40: =-IF(H$5<='Exec Summ'!$F$18/12,'Sensitivity-High'!$C$35*'Sensitivity-High'!$C$37,PMT($C$37/12,$C$36,-$C$35)*12) | I40: =-IF(I$5<='Exec Summ'!$F$18/12,'Sensitivity-High'!$C$35*'Sensitivity-High'!$C$37,PMT($C$37/12,$C$36,-$C$35)*12) | J40: =-IF(J$5<='Exec Summ'!$F$18/12,'Sensitivity-High'!$C$35*'Sensitivity-High'!$C$37,PMT($C$37/12,$C$36,-$C$35)*12) | K40: =-IF(K$5<='Exec Summ'!$F$18/12,'Sensitivity-High'!$C$35*'Sensitivity-High'!$C$37,PMT($C$37/12,$C$36,-$C$35)*12) | L40: =-IF(L$5<='Exec Summ'!$F$18/12,'Sensitivity-High'!$C$35*'Sensitivity-High'!$C$37,PMT($C$37/12,$C$36,-$C$35)*12) | ... N40: =-IF(N$5<='Exec Summ'!$F$18/12,'Sensitivity-High'!$C$35*'Sensitivity-High'!$C$37,PMT($C$37/12,$C$36,-$C$35)*12)
B41: Net Cash Flow | D41: =D9+D39+D40-C18 | E41: =E9+E39+E40 | F41: =F9+F39+F40 | G41: =G9+G39+G40 | H41: =H9+H39+H40 | I41: =I9+I39+I40 | J41: =J9+J39+J40 | K41: =K9+K39+K40 | L41: =L9+L39+L40 | ... N41: =N9+N39+N40
B42: Cash on Cash | E42: =-E41/$D41 | F42: =-F41/$D41 | G42: =-G41/$D41 | H42: =-H41/$D41 | I42: =-I41/$D41 | J42: =-J41/$D41 | K42: =-K41/$D41 | L42: =-L41/$D41 | ... N42: =-N41/$D41
B44: Loan Payoff | G44: =FV($C$37/12,(G$5*12)-'Exec Summ'!$F$18,$C$38,$C$35) | H44: =FV($C$37/12,(H$5*12)-'Exec Summ'!$F$18,$C$38,$C$35) | I44: =FV($C$37/12,(I$5*12)-'Exec Summ'!$F$18,$C$38,$C$35) | J44: =FV($C$37/12,(J$5*12)-'Exec Summ'!$F$18,$C$38,$C$35) | K44: =FV($C$37/12,(K$5*12)-'Exec Summ'!$F$18,$C$38,$C$35) | L44: =FV($C$37/12,(L$5*12)-'Exec Summ'!$F$18,$C$38,$C$35) | M44: =FV($C$37/12,(M$5*12)-'Exec Summ'!$F$18,$C$38,$C$35) | N44: =FV($C$37/12,(N$5*12)-'Exec Summ'!$F$18,$C$38,$C$35)
B45: Net Sale Proceeds After Loan Payoff | G45: =G14+G44 | H45: =H14+H44 | I45: =I14+I44 | J45: =J14+J44 | K45: =K14+K44 | L45: =L14+L44 | M45: =M14+M44 | N45: =N14+N44
B47: Leveraged IRR:
A48: 3 | B48: 3-Year IRR | C48: =IRR(D48:G48) | D48: =D41 | E48: =E41 | F48: =F41 | G48: =G41+G45
A49: =A48+1 | B49: 4-Year IRR | C49: =IRR(D49:H49) | D49: =D48 | E49: =E48 | F49: =F48 | G49: =G41 | H49: =H41+H45
A50: =A49+1 | B50: 5-Year IRR | C50: =IRR(D50:I50) | D50: =D49 | E50: =E49 | F50: =F49 | G50: =G49 | H50: =H41 | I50: =I41+I45
A51: =A50+1 | B51: 6-Year IRR | C51: =IRR(D51:J51) | D51: =D50 | E51: =E50 | F51: =F50 | G51: =G50 | H51: =H50 | I51: =I41 | J51: =J41+J45
A52: =A51+1 | B52: 7-Year IRR | C52: =IRR(D52:K52) | D52: =D51 | E52: =E51 | F52: =F51 | G52: =G51 | H52: =H51 | I52: =I51 | J52: =J41 | K52: =K41+K45
A53: 10 | B53: 10-Year IRR | C53: =IRR(D53:N53) | D53: =D52 | E53: =E52 | F53: =F52 | G53: =G52 | H53: =H52 | I53: =I52 | J53: =J52 | K53: =K41 | L53: =L41 | M53: =M41 | N53: =N41+N45
C59: Check IRR's:
C60: =SUM(C26:C31)-SUM('Exec Summ'!I30:I35)
C61: =SUM(C48:C53)-SUM('Exec Summ'!I38:I43)

Sheet Loan Calculation
B2: LOAN CALCULATION
B5: Principal | C5: ='Exec Summ'!F15
B6: Initial Funding | C6: =C5-K27-K39-K51-K63
B7: Amortization (Months) | C7: ='Exec Summ'!F16
B8: Interest Rate | C8: ='Exec Summ'!F17
B9: Interest Only (Months) | C9: ='Exec Summ'!F18
B10: Loan Origination Fee | C10: 0
B11: Loan Origination Fee | C11: =C5*C10
B12: Loan Payment (Monthly) | C12: =-PMT(C8/12,C7,C5)
B13: Loan Payment (Annual) | C13: =C12*12
B15: Year | C15: Month | D15: Interest | E15: Principal | F15: Sweep | G15: Balance | I15: Annual Debt Service | J15: Year 1 Principal | K15: Loan Funding | L15: Principal | M15: Interest
B16: =IF(C16/12=INT(C16/12),C16/12,"") | C16: 1 | D16: =C5*C8/12 | E16: =IF(C16<=$C$9,0,$C$12-D16) | G16: =C5-E16
B17: =IF(C17/12=INT(C17/12),C17/12,"") | C17: 2 | D17: =G16*$C$8/12 | E17: =IF(C17<=$C$9,0,$C$12-D17) | G17: =G16-E17
B18: =IF(C18/12=INT(C18/12),C18/12,"") | C18: 3 | D18: =G17*$C$8/12 | E18: =IF(C18<=$C$9,0,$C$12-D18) | G18: =G17-E18
B19: =IF(C19/12=INT(C19/12),C19/12,"") | C19: 4 | D19: =G18*$C$8/12 | E19: =IF(C19<=$C$9,0,$C$12-D19) | G19: =G18-E19
B20: =IF(C20/12=INT(C20/12),C20/12,"") | C20: 5 | D20: =G19*$C$8/12 | E20: =IF(C20<=$C$9,0,$C$12-D20) | G20: =G19-E20
B21: =IF(C21/12=INT(C21/12),C21/12,"") | C21: 6 | D21: =G20*$C$8/12 | E21: =IF(C21<=$C$9,0,$C$12-D21) | G21: =G20-E21
B22: =IF(C22/12=INT(C22/12),C22/12,"") | C22: 7 | D22: =G21*$C$8/12 | E22: =IF(C22<=$C$9,0,$C$12-D22) | G22: =G21-E22
B23: =IF(C23/12=INT(C23/12),C23/12,"") | C23: 8 | D23: =G22*$C$8/12 | E23: =IF(C23<=$C$9,0,$C$12-D23) | G23: =G22-E23
B24: =IF(C24/12=INT(C24/12),C24/12,"") | C24: 9 | D24: =G23*$C$8/12 | E24: =IF(C24<=$C$9,0,$C$12-D24) | G24: =G23-E24
B25: =IF(C25/12=INT(C25/12),C25/12,"") | C25: 10 | D25: =G24*$C$8/12 | E25: =IF(C25<=$C$9,0,$C$12-D25) | G25: =G24-E25
B26: =IF(C26/12=INT(C26/12),C26/12,"") | C26: 11 | D26: =G25*$C$8/12 | E26: =IF(C26<=$C$9,0,$C$12-D26) | G26: =G25-E26
B27: =IF(C27/12=INT(C27/12),C27/12,"") | C27: 12 | D27: =G26*$C$8/12 | E27: =IF(C27<=$C$9,0,$C$12-D27) | G27: =G26-E27 | I27: =SUM(D16:F27) | J27: =SUM(E16:E27) | K27: 0 | L27: =SUM(E16:E27) | M27: =SUM(D16:D27)
B28: =IF(C28/12=INT(C28/12),C28/12,"") | C28: 13 | D28: =G27*$C$8/12 | E28: =IF(C28<=$C$9,0,$C$12-D28) | G28: =G27-E28
B29: =IF(C29/12=INT(C29/12),C29/12,"") | C29: 14 | D29: =G28*$C$8/12 | E29: =IF(C29<=$C$9,0,$C$12-D29) | G29: =G28-E29
B30: =IF(C30/12=INT(C30/12),C30/12,"") | C30: 15 | D30: =G29*$C$8/12 | E30: =IF(C30<=$C$9,0,$C$12-D30) | G30: =G29-E30
B31: =IF(C31/12=INT(C31/12),C31/12,"") | C31: 16 | D31: =G30*$C$8/12 | E31: =IF(C31<=$C$9,0,$C$12-D31) | G31: =G30-E31
B32: =IF(C32/12=INT(C32/12),C32/12,"") | C32: 17 | D32: =G31*$C$8/12 | E32: =IF(C32<=$C$9,0,$C$12-D32) | G32: =G31-E32
B33: =IF(C33/12=INT(C33/12),C33/12,"") | C33: 18 | D33: =G32*$C$8/12 | E33: =IF(C33<=$C$9,0,$C$12-D33) | G33: =G32-E33
B34: =IF(C34/12=INT(C34/12),C34/12,"") | C34: 19 | D34: =G33*$C$8/12 | E34: =IF(C34<=$C$9,0,$C$12-D34) | G34: =G33-E34
B35: =IF(C35/12=INT(C35/12),C35/12,"") | C35: 20 | D35: =G34*$C$8/12 | E35: =IF(C35<=$C$9,0,$C$12-D35) | G35: =G34-E35
B36: =IF(C36/12=INT(C36/12),C36/12,"") | C36: 21 | D36: =G35*$C$8/12 | E36: =IF(C36<=$C$9,0,$C$12-D36) | G36: =G35-E36
B37: =IF(C37/12=INT(C37/12),C37/12,"") | C37: 22 | D37: =G36*$C$8/12 | E37: =IF(C37<=$C$9,0,$C$12-D37) | G37: =G36-E37
B38: =IF(C38/12=INT(C38/12),C38/12,"") | C38: 23 | D38: =G37*$C$8/12 | E38: =IF(C38<=$C$9,0,$C$12-D38) | G38: =G37-E38
B39: =IF(C39/12=INT(C39/12),C39/12,"") | C39: 24 | D39: =G38*$C$8/12 | E39: =IF(C39<=$C$9,0,$C$12-D39) | G39: =G38-E39 | I39: =SUM(D28:F39) | K39: 0 | L39: =SUM(E28:E39) | M39: =SUM(D28:D39)
B40: =IF(C40/12=INT(C40/12),C40/12,"") | C40: 25 | D40: =G39*$C$8/12 | E40: =IF(C40<=$C$9,0,$C$12-D40) | G40: =G39-E40
B41: =IF(C41/12=INT(C41/12),C41/12,"") | C41: 26 | D41: =G40*$C$8/12 | E41: =IF(C41<=$C$9,0,$C$12-D41) | G41: =G40-E41
B42: =IF(C42/12=INT(C42/12),C42/12,"") | C42: 27 | D42: =G41*$C$8/12 | E42: =IF(C42<=$C$9,0,$C$12-D42) | G42: =G41-E42
B43: =IF(C43/12=INT(C43/12),C43/12,"") | C43: 28 | D43: =G42*$C$8/12 | E43: =IF(C43<=$C$9,0,$C$12-D43) | G43: =G42-E43
B44: =IF(C44/12=INT(C44/12),C44/12,"") | C44: 29 | D44: =G43*$C$8/12 | E44: =IF(C44<=$C$9,0,$C$12-D44) | G44: =G43-E44
B45: =IF(C45/12=INT(C45/12),C45/12,"") | C45: 30 | D45: =G44*$C$8/12 | E45: =IF(C45<=$C$9,0,$C$12-D45) | G45: =G44-E45
B46: =IF(C46/12=INT(C46/12),C46/12,"") | C46: 31 | D46: =G45*$C$8/12 | E46: =IF(C46<=$C$9,0,$C$12-D46) | G46: =G45-E46
B47: =IF(C47/12=INT(C47/12),C47/12,"") | C47: 32 | D47: =G46*$C$8/12 | E47: =IF(C47<=$C$9,0,$C$12-D47) | G47: =G46-E47
B48: =IF(C48/12=INT(C48/12),C48/12,"") | C48: 33 | D48: =G47*$C$8/12 | E48: =IF(C48<=$C$9,0,$C$12-D48) | G48: =G47-E48
B49: =IF(C49/12=INT(C49/12),C49/12,"") | C49: 34 | D49: =G48*$C$8/12 | E49: =IF(C49<=$C$9,0,$C$12-D49) | G49: =G48-E49
B50: =IF(C50/12=INT(C50/12),C50/12,"") | C50: 35 | D50: =G49*$C$8/12 | E50: =IF(C50<=$C$9,0,$C$12-D50) | G50: =G49-E50
B51: =IF(C51/12=INT(C51/12),C51/12,"") | C51: 36 | D51: =G50*$C$8/12 | E51: =IF(C51<=$C$9,0,$C$12-D51) | G51: =G50-E51 | I51: =SUM(D40:F51) | K51: 0 | L51: =SUM(E40:E51) | M51: =SUM(D40:D51)
B52: =IF(C52/12=INT(C52/12),C52/12,"") | C52: 37 | D52: =G51*$C$8/12 | E52: =IF(C52<=$C$9,0,$C$12-D52) | G52: =G51-E52
B53: =IF(C53/12=INT(C53/12),C53/12,"") | C53: 38 | D53: =G52*$C$8/12 | E53: =IF(C53<=$C$9,0,$C$12-D53) | G53: =G52-E53
B54: =IF(C54/12=INT(C54/12),C54/12,"") | C54: 39 | D54: =G53*$C$8/12 | E54: =IF(C54<=$C$9,0,$C$12-D54) | G54: =G53-E54
B55: =IF(C55/12=INT(C55/12),C55/12,"") | C55: 40 | D55: =G54*$C$8/12 | E55: =IF(C55<=$C$9,0,$C$12-D55) | G55: =G54-E55
B56: =IF(C56/12=INT(C56/12),C56/12,"") | C56: 41 | D56: =G55*$C$8/12 | E56: =IF(C56<=$C$9,0,$C$12-D56) | G56: =G55-E56
B57: =IF(C57/12=INT(C57/12),C57/12,"") | C57: 42 | D57: =G56*$C$8/12 | E57: =IF(C57<=$C$9,0,$C$12-D57) | G57: =G56-E57
B58: =IF(C58/12=INT(C58/12),C58/12,"") | C58: 43 | D58: =G57*$C$8/12 | E58: =IF(C58<=$C$9,0,$C$12-D58) | G58: =G57-E58
B59: =IF(C59/12=INT(C59/12),C59/12,"") | C59: 44 | D59: =G58*$C$8/12 | E59: =IF(C59<=$C$9,0,$C$12-D59) | G59: =G58-E59
B60: =IF(C60/12=INT(C60/12),C60/12,"") | C60: 45 | D60: =G59*$C$8/12 | E60: =IF(C60<=$C$9,0,$C$12-D60) | G60: =G59-E60
B61: =IF(C61/12=INT(C61/12),C61/12,"") | C61: 46 | D61: =G60*$C$8/12 | E61: =IF(C61<=$C$9,0,$C$12-D61) | G61: =G60-E61
B62: =IF(C62/12=INT(C62/12),C62/12,"") | C62: 47 | D62: =G61*$C$8/12 | E62: =IF(C62<=$C$9,0,$C$12-D62) | G62: =G61-E62
B63: =IF(C63/12=INT(C63/12),C63/12,"") | C63: 48 | D63: =G62*$C$8/12 | E63: =IF(C63<=$C$9,0,$C$12-D63) | G63: =G62-E63 | I63: =SUM(D52:F63) | K63: 0 | L63: =SUM(E52:E63) | M63: =SUM(D52:D63)
B64: =IF(C64/12=INT(C64/12),C64/12,"") | C64: 49 | D64: =G63*$C$8/12 | E64: =IF(C64<=$C$9,0,$C$12-D64) | G64: =G63-E64
B65: =IF(C65/12=INT(C65/12),C65/12,"") | C65: 50 | D65: =G64*$C$8/12 | E65: =IF(C65<=$C$9,0,$C$12-D65) | G65: =G64-E65
B66: =IF(C66/12=INT(C66/12),C66/12,"") | C66: 51 | D66: =G65*$C$8/12 | E66: =IF(C66<=$C$9,0,$C$12-D66) | G66: =G65-E66
B67: =IF(C67/12=INT(C67/12),C67/12,"") | C67: 52 | D67: =G66*$C$8/12 | E67: =IF(C67<=$C$9,0,$C$12-D67) | G67: =G66-E67
B68: =IF(C68/12=INT(C68/12),C68/12,"") | C68: 53 | D68: =G67*$C$8/12 | E68: =IF(C68<=$C$9,0,$C$12-D68) | G68: =G67-E68
B69: =IF(C69/12=INT(C69/12),C69/12,"") | C69: 54 | D69: =G68*$C$8/12 | E69: =IF(C69<=$C$9,0,$C$12-D69) | G69: =G68-E69
B70: =IF(C70/12=INT(C70/12),C70/12,"") | C70: 55 | D70: =G69*$C$8/12 | E70: =IF(C70<=$C$9,0,$C$12-D70) | G70: =G69-E70
B71: =IF(C71/12=INT(C71/12),C71/12,"") | C71: 56 | D71: =G70*$C$8/12 | E71: =IF(C71<=$C$9,0,$C$12-D71) | G71: =G70-E71
B72: =IF(C72/12=INT(C72/12),C72/12,"") | C72: 57 | D72: =G71*$C$8/12 | E72: =IF(C72<=$C$9,0,$C$12-D72) | G72: =G71-E72
B73: =IF(C73/12=INT(C73/12),C73/12,"") | C73: 58 | D73: =G72*$C$8/12 | E73: =IF(C73<=$C$9,0,$C$12-D73) | G73: =G72-E73
B74: =IF(C74/12=INT(C74/12),C74/12,"") | C74: 59 | D74: =G73*$C$8/12 | E74: =IF(C74<=$C$9,0,$C$12-D74) | G74: =G73-E74
B75: =IF(C75/12=INT(C75/12),C75/12,"") | C75: 60 | D75: =G74*$C$8/12 | E75: =IF(C75<=$C$9,0,$C$12-D75) | G75: =G74-E75 | I75: =SUM(D64:F75) | L75: =SUM(E64:E75) | M75: =SUM(D64:D75)
B76: =IF(C76/12=INT(C76/12),C76/12,"") | C76: 61 | D76: =G75*$C$8/12 | E76: =IF(C76<=$C$9,0,$C$12-D76) | G76: =G75-E76
B77: =IF(C77/12=INT(C77/12),C77/12,"") | C77: 62 | D77: =G76*$C$8/12 | E77: =IF(C77<=$C$9,0,$C$12-D77) | G77: =G76-E77
B78: =IF(C78/12=INT(C78/12),C78/12,"") | C78: 63 | D78: =G77*$C$8/12 | E78: =IF(C78<=$C$9,0,$C$12-D78) | G78: =G77-E78
B79: =IF(C79/12=INT(C79/12),C79/12,"") | C79: 64 | D79: =G78*$C$8/12 | E79: =IF(C79<=$C$9,0,$C$12-D79) | G79: =G78-E79
B80: =IF(C80/12=INT(C80/12),C80/12,"") | C80: 65 | D80: =G79*$C$8/12 | E80: =IF(C80<=$C$9,0,$C$12-D80) | G80: =G79-E80
B81: =IF(C81/12=INT(C81/12),C81/12,"") | C81: 66 | D81: =G80*$C$8/12 | E81: =IF(C81<=$C$9,0,$C$12-D81) | G81: =G80-E81
B82: =IF(C82/12=INT(C82/12),C82/12,"") | C82: 67 | D82: =G81*$C$8/12 | E82: =IF(C82<=$C$9,0,$C$12-D82) | G82: =G81-E82
B83: =IF(C83/12=INT(C83/12),C83/12,"") | C83: 68 | D83: =G82*$C$8/12 | E83: =IF(C83<=$C$9,0,$C$12-D83) | G83: =G82-E83
B84: =IF(C84/12=INT(C84/12),C84/12,"") | C84: 69 | D84: =G83*$C$8/12 | E84: =IF(C84<=$C$9,0,$C$12-D84) | G84: =G83-E84
B85: =IF(C85/12=INT(C85/12),C85/12,"") | C85: 70 | D85: =G84*$C$8/12 | E85: =IF(C85<=$C$9,0,$C$12-D85) | G85: =G84-E85
B86: =IF(C86/12=INT(C86/12),C86/12,"") | C86: 71 | D86: =G85*$C$8/12 | E86: =IF(C86<=$C$9,0,$C$12-D86) | G86: =G85-E86
B87: =IF(C87/12=INT(C87/12),C87/12,"") | C87: 72 | D87: =G86*$C$8/12 | E87: =IF(C87<=$C$9,0,$C$12-D87) | G87: =G86-E87 | I87: =SUM(D76:F87) | L87: =SUM(E76:E87) | M87: =SUM(D76:D87)
B88: =IF(C88/12=INT(C88/12),C88/12,"") | C88: 73 | D88: =G87*$C$8/12 | E88: =IF(C88<=$C$9,0,$C$12-D88) | G88: =G87-E88
B89: =IF(C89/12=INT(C89/12),C89/12,"") | C89: 74 | D89: =G88*$C$8/12 | E89: =IF(C89<=$C$9,0,$C$12-D89) | G89: =G88-E89
B90: =IF(C90/12=INT(C90/12),C90/12,"") | C90: 75 | D90: =G89*$C$8/12 | E90: =IF(C90<=$C$9,0,$C$12-D90) | G90: =G89-E90
B91: =IF(C91/12=INT(C91/12),C91/12,"") | C91: 76 | D91: =G90*$C$8/12 | E91: =IF(C91<=$C$9,0,$C$12-D91) | G91: =G90-E91
B92: =IF(C92/12=INT(C92/12),C92/12,"") | C92: 77 | D92: =G91*$C$8/12 | E92: =IF(C92<=$C$9,0,$C$12-D92) | G92: =G91-E92
B93: =IF(C93/12=INT(C93/12),C93/12,"") | C93: 78 | D93: =G92*$C$8/12 | E93: =IF(C93<=$C$9,0,$C$12-D93) | G93: =G92-E93
B94: =IF(C94/12=INT(C94/12),C94/12,"") | C94: 79 | D94: =G93*$C$8/12 | E94: =IF(C94<=$C$9,0,$C$12-D94) | G94: =G93-E94
B95: =IF(C95/12=INT(C95/12),C95/12,"") | C95: 80 | D95: =G94*$C$8/12 | E95: =IF(C95<=$C$9,0,$C$12-D95) | G95: =G94-E95
B96: =IF(C96/12=INT(C96/12),C96/12,"") | C96: 81 | D96: =G95*$C$8/12 | E96: =IF(C96<=$C$9,0,$C$12-D96) | G96: =G95-E96
B97: =IF(C97/12=INT(C97/12),C97/12,"") | C97: 82 | D97: =G96*$C$8/12 | E97: =IF(C97<=$C$9,0,$C$12-D97) | G97: =G96-E97
B98: =IF(C98/12=INT(C98/12),C98/12,"") | C98: 83 | D98: =G97*$C$8/12 | E98: =IF(C98<=$C$9,0,$C$12-D98) | G98: =G97-E98
B99: =IF(C99/12=INT(C99/12),C99/12,"") | C99: 84 | D99: =G98*$C$8/12 | E99: =IF(C99<=$C$9,0,$C$12-D99) | G99: =G98-E99 | I99: =SUM(D88:F99) | L99: =SUM(E88:E99) | M99: =SUM(D88:D99)
B100: =IF(C100/12=INT(C100/12),C100/12,"") | C100: 85 | D100: =G99*$C$8/12 | E100: =IF(C100<=$C$9,0,$C$12-D100) | G100: =G99-E100
B101: =IF(C101/12=INT(C101/12),C101/12,"") | C101: 86 | D101: =G100*$C$8/12 | E101: =IF(C101<=$C$9,0,$C$12-D101) | G101: =G100-E101
B102: =IF(C102/12=INT(C102/12),C102/12,"") | C102: 87 | D102: =G101*$C$8/12 | E102: =IF(C102<=$C$9,0,$C$12-D102) | G102: =G101-E102
B103: =IF(C103/12=INT(C103/12),C103/12,"") | C103: 88 | D103: =G102*$C$8/12 | E103: =IF(C103<=$C$9,0,$C$12-D103) | G103: =G102-E103
B104: =IF(C104/12=INT(C104/12),C104/12,"") | C104: 89 | D104: =G103*$C$8/12 | E104: =IF(C104<=$C$9,0,$C$12-D104) | G104: =G103-E104
...

Sheet Loan Calculation - Low
B2: LOAN CALCULATION
B5: Principal | C5: ='Sensitivity-Low'!C35
B6: Initial Funding | C6: =C5-K27-K39-K51-K63
B7: Amortization (Months) | C7: ='Exec Summ'!F16
B8: Interest Rate | C8: ='Exec Summ'!F17
B9: Interest Only (Months) | C9: ='Exec Summ'!F18
B10: Loan Origination Fee | C10: 0
B11: Loan Origination Fee | C11: =C5*C10
B12: Loan Payment (Monthly) | C12: =-PMT(C8/12,C7,C5)
B13: Loan Payment (Annual) | C13: =C12*12
B15: Year | C15: Month | D15: Interest | E15: Principal | F15: Sweep | G15: Balance | I15: Annual Debt Service | J15: Year 1 Principal | K15: Loan Funding | L15: Principal | M15: Interest
B16: =IF(C16/12=INT(C16/12),C16/12,"") | C16: 1 | D16: =C5*C8/12 | E16: =IF(C16<=$C$9,0,$C$12-D16) | G16: =C5-E16
B17: =IF(C17/12=INT(C17/12),C17/12,"") | C17: 2 | D17: =G16*$C$8/12 | E17: =IF(C17<=$C$9,0,$C$12-D17) | G17: =G16-E17
B18: =IF(C18/12=INT(C18/12),C18/12,"") | C18: 3 | D18: =G17*$C$8/12 | E18: =IF(C18<=$C$9,0,$C$12-D18) | G18: =G17-E18
B19: =IF(C19/12=INT(C19/12),C19/12,"") | C19: 4 | D19: =G18*$C$8/12 | E19: =IF(C19<=$C$9,0,$C$12-D19) | G19: =G18-E19
B20: =IF(C20/12=INT(C20/12),C20/12,"") | C20: 5 | D20: =G19*$C$8/12 | E20: =IF(C20<=$C$9,0,$C$12-D20) | G20: =G19-E20
B21: =IF(C21/12=INT(C21/12),C21/12,"") | C21: 6 | D21: =G20*$C$8/12 | E21: =IF(C21<=$C$9,0,$C$12-D21) | G21: =G20-E21
B22: =IF(C22/12=INT(C22/12),C22/12,"") | C22: 7 | D22: =G21*$C$8/12 | E22: =IF(C22<=$C$9,0,$C$12-D22) | G22: =G21-E22
B23: =IF(C23/12=INT(C23/12),C23/12,"") | C23: 8 | D23: =G22*$C$8/12 | E23: =IF(C23<=$C$9,0,$C$12-D23) | G23: =G22-E23
B24: =IF(C24/12=INT(C24/12),C24/12,"") | C24: 9 | D24: =G23*$C$8/12 | E24: =IF(C24<=$C$9,0,$C$12-D24) | G24: =G23-E24
B25: =IF(C25/12=INT(C25/12),C25/12,"") | C25: 10 | D25: =G24*$C$8/12 | E25: =IF(C25<=$C$9,0,$C$12-D25) | G25: =G24-E25
B26: =IF(C26/12=INT(C26/12),C26/12,"") | C26: 11 | D26: =G25*$C$8/12 | E26: =IF(C26<=$C$9,0,$C$12-D26) | G26: =G25-E26
B27: =IF(C27/12=INT(C27/12),C27/12,"") | C27: 12 | D27: =G26*$C$8/12 | E27: =IF(C27<=$C$9,0,$C$12-D27) | G27: =G26-E27 | I27: =SUM(D16:F27) | J27: =SUM(E16:E27) | K27: 0 | L27: =SUM(E16:E27) | M27: =SUM(D16:D27)
B28: =IF(C28/12=INT(C28/12),C28/12,"") | C28: 13 | D28: =G27*$C$8/12 | E28: =IF(C28<=$C$9,0,$C$12-D28) | G28: =G27-E28
B29: =IF(C29/12=INT(C29/12),C29/12,"") | C29: 14 | D29: =G28*$C$8/12 | E29: =IF(C29<=$C$9,0,$C$12-D29) | G29: =G28-E29
B30: =IF(C30/12=INT(C30/12),C30/12,"") | C30: 15 | D30: =G29*$C$8/12 | E30: =IF(C30<=$C$9,0,$C$12-D30) | G30: =G29-E30
B31: =IF(C31/12=INT(C31/12),C31/12,"") | C31: 16 | D31: =G30*$C$8/12 | E31: =IF(C31<=$C$9,0,$C$12-D31) | G31: =G30-E31
B32: =IF(C32/12=INT(C32/12),C32/12,"") | C32: 17 | D32: =G31*$C$8/12 | E32: =IF(C32<=$C$9,0,$C$12-D32) | G32: =G31-E32
B33: =IF(C33/12=INT(C33/12),C33/12,"") | C33: 18 | D33: =G32*$C$8/12 | E33: =IF(C33<=$C$9,0,$C$12-D33) | G33: =G32-E33
B34: =IF(C34/12=INT(C34/12),C34/12,"") | C34: 19 | D34: =G33*$C$8/12 | E34: =IF(C34<=$C$9,0,$C$12-D34) | G34: =G33-E34
B35: =IF(C35/12=INT(C35/12),C35/12,"") | C35: 20 | D35: =G34*$C$8/12 | E35: =IF(C35<=$C$9,0,$C$12-D35) | G35: =G34-E35
B36: =IF(C36/12=INT(C36/12),C36/12,"") | C36: 21 | D36: =G35*$C$8/12 | E36: =IF(C36<=$C$9,0,$C$12-D36) | G36: =G35-E36
B37: =IF(C37/12=INT(C37/12),C37/12,"") | C37: 22 | D37: =G36*$C$8/12 | E37: =IF(C37<=$C$9,0,$C$12-D37) | G37: =G36-E37
B38: =IF(C38/12=INT(C38/12),C38/12,"") | C38: 23 | D38: =G37*$C$8/12 | E38: =IF(C38<=$C$9,0,$C$12-D38) | G38: =G37-E38
B39: =IF(C39/12=INT(C39/12),C39/12,"") | C39: 24 | D39: =G38*$C$8/12 | E39: =IF(C39<=$C$9,0,$C$12-D39) | G39: =G38-E39 | I39: =SUM(D28:F39) | K39: 0 | L39: =SUM(E28:E39) | M39: =SUM(D28:D39)
B40: =IF(C40/12=INT(C40/12),C40/12,"") | C40: 25 | D40: =G39*$C$8/12 | E40: =IF(C40<=$C$9,0,$C$12-D40) | G40: =G39-E40
B41: =IF(C41/12=INT(C41/12),C41/12,"") | C41: 26 | D41: =G40*$C$8/12 | E41: =IF(C41<=$C$9,0,$C$12-D41) | G41: =G40-E41
B42: =IF(C42/12=INT(C42/12),C42/12,"") | C42: 27 | D42: =G41*$C$8/12 | E42: =IF(C42<=$C$9,0,$C$12-D42) | G42: =G41-E42
B43: =IF(C43/12=INT(C43/12),C43/12,"") | C43: 28 | D43: =G42*$C$8/12 | E43: =IF(C43<=$C$9,0,$C$12-D43) | G43: =G42-E43
B44: =IF(C44/12=INT(C44/12),C44/12,"") | C44: 29 | D44: =G43*$C$8/12 | E44: =IF(C44<=$C$9,0,$C$12-D44) | G44: =G43-E44
B45: =IF(C45/12=INT(C45/12),C45/12,"") | C45: 30 | D45: =G44*$C$8/12 | E45: =IF(C45<=$C$9,0,$C$12-D45) | G45: =G44-E45
B46: =IF(C46/12=INT(C46/12),C46/12,"") | C46: 31 | D46: =G45*$C$8/12 | E46: =IF(C46<=$C$9,0,$C$12-D46) | G46: =G45-E46
B47: =IF(C47/12=INT(C47/12),C47/12,"") | C47: 32 | D47: =G46*$C$8/12 | E47: =IF(C47<=$C$9,0,$C$12-D47) | G47: =G46-E47
B48: =IF(C48/12=INT(C48/12),C48/12,"") | C48: 33 | D48: =G47*$C$8/12 | E48: =IF(C48<=$C$9,0,$C$12-D48) | G48: =G47-E48
B49: =IF(C49/12=INT(C49/12),C49/12,"") | C49: 34 | D49: =G48*$C$8/12 | E49: =IF(C49<=$C$9,0,$C$12-D49) | G49: =G48-E49
B50: =IF(C50/12=INT(C50/12),C50/12,"") | C50: 35 | D50: =G49*$C$8/12 | E50: =IF(C50<=$C$9,0,$C$12-D50) | G50: =G49-E50
B51: =IF(C51/12=INT(C51/12),C51/12,"") | C51: 36 | D51: =G50*$C$8/12 | E51: =IF(C51<=$C$9,0,$C$12-D51) | G51: =G50-E51 | I51: =SUM(D40:F51) | K51: 0 | L51: =SUM(E40:E51) | M51: =SUM(D40:D51)
B52: =IF(C52/12=INT(C52/12),C52/12,"") | C52: 37 | D52: =G51*$C$8/12 | E52: =IF(C52<=$C$9,0,$C$12-D52) | G52: =G51-E52
B53: =IF(C53/12=INT(C53/12),C53/12,"") | C53: 38 | D53: =G52*$C$8/12 | E53: =IF(C53<=$C$9,0,$C$12-D53) | G53: =G52-E53
B54: =IF(C54/12=INT(C54/12),C54/12,"") | C54: 39 | D54: =G53*$C$8/12 | E54: =IF(C54<=$C$9,0,$C$12-D54) | G54: =G53-E54
B55: =IF(C55/12=INT(C55/12),C55/12,"") | C55: 40 | D55: =G54*$C$8/12 | E55: =IF(C55<=$C$9,0,$C$12-D55) | G55: =G54-E55
B56: =IF(C56/12=INT(C56/12),C56/12,"") | C56: 41 | D56: =G55*$C$8/12 | E56: =IF(C56<=$C$9,0,$C$12-D56) | G56: =G55-E56
B57: =IF(C57/12=INT(C57/12),C57/12,"") | C57: 42 | D57: =G56*$C$8/12 | E57: =IF(C57<=$C$9,0,$C$12-D57) | G57: =G56-E57
B58: =IF(C58/12=INT(C58/12),C58/12,"") | C58: 43 | D58: =G57*$C$8/12 | E58: =IF(C58<=$C$9,0,$C$12-D58) | G58: =G57-E58
B59: =IF(C59/12=INT(C59/12),C59/12,"") | C59: 44 | D59: =G58*$C$8/12 | E59: =IF(C59<=$C$9,0,$C$12-D59) | G59: =G58-E59
B60: =IF(C60/12=INT(C60/12),C60/12,"") | C60: 45 | D60: =G59*$C$8/12 | E60: =IF(C60<=$C$9,0,$C$12-D60) | G60: =G59-E60
B61: =IF(C61/12=INT(C61/12),C61/12,"") | C61: 46 | D61: =G60*$C$8/12 | E61: =IF(C61<=$C$9,0,$C$12-D61) | G61: =G60-E61
B62: =IF(C62/12=INT(C62/12),C62/12,"") | C62: 47 | D62: =G61*$C$8/12 | E62: =IF(C62<=$C$9,0,$C$12-D62) | G62: =G61-E62
B63: =IF(C63/12=INT(C63/12),C63/12,"") | C63: 48 | D63: =G62*$C$8/12 | E63: =IF(C63<=$C$9,0,$C$12-D63) | G63: =G62-E63 | I63: =SUM(D52:F63) | K63: 0 | L63: =SUM(E52:E63) | M63: =SUM(D52:D63)
B64: =IF(C64/12=INT(C64/12),C64/12,"") | C64: 49 | D64: =G63*$C$8/12 | E64: =IF(C64<=$C$9,0,$C$12-D64) | G64: =G63-E64
B65: =IF(C65/12=INT(C65/12),C65/12,"") | C65: 50 | D65: =G64*$C$8/12 | E65: =IF(C65<=$C$9,0,$C$12-D65) | G65: =G64-E65
B66: =IF(C66/12=INT(C66/12),C66/12,"") | C66: 51 | D66: =G65*$C$8/12 | E66: =IF(C66<=$C$9,0,$C$12-D66) | G66: =G65-E66
B67: =IF(C67/12=INT(C67/12),C67/12,"") | C67: 52 | D67: =G66*$C$8/12 | E67: =IF(C67<=$C$9,0,$C$12-D67) | G67: =G66-E67
B68: =IF(C68/12=INT(C68/12),C68/12,"") | C68: 53 | D68: =G67*$C$8/12 | E68: =IF(C68<=$C$9,0,$C$12-D68) | G68: =G67-E68
B69: =IF(C69/12=INT(C69/12),C69/12,"") | C69: 54 | D69: =G68*$C$8/12 | E69: =IF(C69<=$C$9,0,$C$12-D69) | G69: =G68-E69
B70: =IF(C70/12=INT(C70/12),C70/12,"") | C70: 55 | D70: =G69*$C$8/12 | E70: =IF(C70<=$C$9,0,$C$12-D70) | G70: =G69-E70
B71: =IF(C71/12=INT(C71/12),C71/12,"") | C71: 56 | D71: =G70*$C$8/12 | E71: =IF(C71<=$C$9,0,$C$12-D71) | G71: =G70-E71
B72: =IF(C72/12=INT(C72/12),C72/12,"") | C72: 57 | D72: =G71*$C$8/12 | E72: =IF(C72<=$C$9,0,$C$12-D72) | G72: =G71-E72
B73: =IF(C73/12=INT(C73/12),C73/12,"") | C73: 58 | D73: =G72*$C$8/12 | E73: =IF(C73<=$C$9,0,$C$12-D73) | G73: =G72-E73
B74: =IF(C74/12=INT(C74/12),C74/12,"") | C74: 59 | D74: =G73*$C$8/12 | E74: =IF(C74<=$C$9,0,$C$12-D74) | G74: =G73-E74
B75: =IF(C75/12=INT(C75/12),C75/12,"") | C75: 60 | D75: =G74*$C$8/12 | E75: =IF(C75<=$C$9,0,$C$12-D75) | G75: =G74-E75 | I75: =SUM(D64:F75) | L75: =SUM(E64:E75) | M75: =SUM(D64:D75)
B76: =IF(C76/12=INT(C76/12),C76/12,"") | C76: 61 | D76: =G75*$C$8/12 | E76: =IF(C76<=$C$9,0,$C$12-D76) | G76: =G75-E76
B77: =IF(C77/12=INT(C77/12),C77/12,"") | C77: 62 | D77: =G76*$C$8/12 | E77: =IF(C77<=$C$9,0,$C$12-D77) | G77: =G76-E77
B78: =IF(C78/12=INT(C78/12),C78/12,"") | C78: 63 | D78: =G77*$C$8/12 | E78: =IF(C78<=$C$9,0,$C$12-D78) | G78: =G77-E78
B79: =IF(C79/12=INT(C79/12),C79/12,"") | C79: 64 | D79: =G78*$C$8/12 | E79: =IF(C79<=$C$9,0,$C$12-D79) | G79: =G78-E79
B80: =IF(C80/12=INT(C80/12),C80/12,"") | C80: 65 | D80: =G79*$C$8/12 | E80: =IF(C80<=$C$9,0,$C$12-D80) | G80: =G79-E80
B81: =IF(C81/12=INT(C81/12),C81/12,"") | C81: 66 | D81: =G80*$C$8/12 | E81: =IF(C81<=$C$9,0,$C$12-D81) | G81: =G80-E81
B82: =IF(C82/12=INT(C82/12),C82/12,"") | C82: 67 | D82: =G81*$C$8/12 | E82: =IF(C82<=$C$9,0,$C$12-D82) | G82: =G81-E82
B83: =IF(C83/12=INT(C83/12),C83/12,"") | C83: 68 | D83: =G82*$C$8/12 | E83: =IF(C83<=$C$9,0,$C$12-D83) | G83: =G82-E83
B84: =IF(C84/12=INT(C84/12),C84/12,"") | C84: 69 | D84: =G83*$C$8/12 | E84: =IF(C84<=$C$9,0,$C$12-D84) | G84: =G83-E84
B85: =IF(C85/12=INT(C85/12),C85/12,"") | C85: 70 | D85: =G84*$C$8/12 | E85: =IF(C85<=$C$9,0,$C$12-D85) | G85: =G84-E85
B86: =IF(C86/12=INT(C86/12),C86/12,"") | C86: 71 | D86: =G85*$C$8/12 | E86: =IF(C86<=$C$9,0,$C$12-D86) | G86: =G85-E86
B87: =IF(C87/12=INT(C87/12),C87/12,"") | C87: 72 | D87: =G86*$C$8/12 | E87: =IF(C87<=$C$9,0,$C$12-D87) | G87: =G86-E87 | I87: =SUM(D76:F87) | L87: =SUM(E76:E87) | M87: =SUM(D76:D87)
B88: =IF(C88/12=INT(C88/12),C88/12,"") | C88: 73 | D88: =G87*$C$8/12 | E88: =IF(C88<=$C$9,0,$C$12-D88) | G88: =G87-E88
B89: =IF(C89/12=INT(C89/12),C89/12,"") | C89: 74 | D89: =G88*$C$8/12 | E89: =IF(C89<=$C$9,0,$C$12-D89) | G89: =G88-E89
B90: =IF(C90/12=INT(C90/12),C90/12,"") | C90: 75 | D90: =G89*$C$8/12 | E90: =IF(C90<=$C$9,0,$C$12-D90) | G90: =G89-E90
B91: =IF(C91/12=INT(C91/12),C91/12,"") | C91: 76 | D91: =G90*$C$8/12 | E91: =IF(C91<=$C$9,0,$C$12-D91) | G91: =G90-E91
B92: =IF(C92/12=INT(C92/12),C92/12,"") | C92: 77 | D92: =G91*$C$8/12 | E92: =IF(C92<=$C$9,0,$C$12-D92) | G92: =G91-E92
B93: =IF(C93/12=INT(C93/12),C93/12,"") | C93: 78 | D93: =G92*$C$8/12 | E93: =IF(C93<=$C$9,0,$C$12-D93) | G93: =G92-E93
B94: =IF(C94/12=INT(C94/12),C94/12,"") | C94: 79 | D94: =G93*$C$8/12 | E94: =IF(C94<=$C$9,0,$C$12-D94) | G94: =G93-E94
B95: =IF(C95/12=INT(C95/12),C95/12,"") | C95: 80 | D95: =G94*$C$8/12 | E95: =IF(C95<=$C$9,0,$C$12-D95) | G95: =G94-E95
B96: =IF(C96/12=INT(C96/12),C96/12,"") | C96: 81 | D96: =G95*$C$8/12 | E96: =IF(C96<=$C$9,0,$C$12-D96) | G96: =G95-E96
B97: =IF(C97/12=INT(C97/12),C97/12,"") | C97: 82 | D97: =G96*$C$8/12 | E97: =IF(C97<=$C$9,0,$C$12-D97) | G97: =G96-E97
B98: =IF(C98/12=INT(C98/12),C98/12,"") | C98: 83 | D98: =G97*$C$8/12 | E98: =IF(C98<=$C$9,0,$C$12-D98) | G98: =G97-E98
B99: =IF(C99/12=INT(C99/12),C99/12,"") | C99: 84 | D99: =G98*$C$8/12 | E99: =IF(C99<=$C$9,0,$C$12-D99) | G99: =G98-E99 | I99: =SUM(D88:F99) | L99: =SUM(E88:E99) | M99: =SUM(D88:D99)
B100: =IF(C100/12=INT(C100/12),C100/12,"") | C100: 85 | D100: =G99*$C$8/12 | E100: =IF(C100<=$C$9,0,$C$12-D100) | G100: =G99-E100
B101: =IF(C101/12=INT(C101/12),C101/12,"") | C101: 86 | D101: =G100*$C$8/12 | E101: =IF(C101<=$C$9,0,$C$12-D101) | G101: =G100-E101
B102: =IF(C102/12=INT(C102/12),C102/12,"") | C102: 87 | D102: =G101*$C$8/12 | E102: =IF(C102<=$C$9,0,$C$12-D102) | G102: =G101-E102
B103: =IF(C103/12=INT(C103/12),C103/12,"") | C103: 88 | D103: =G102*$C$8/12 | E103: =IF(C103<=$C$9,0,$C$12-D103) | G103: =G102-E103
B104: =IF(C104/12=INT(C104/12),C104/12,"") | C104: 89 | D104: =G103*$C$8/12 | E104: =IF(C104<=$C$9,0,$C$12-D104) | G104: =G103-E104
...

Sheet Loan Calculation - High
B2: LOAN CALCULATION
B5: Principal | C5: ='Sensitivity-High'!C35
B6: Initial Funding | C6: =C5-K27-K39-K51-K63
B7: Amortization (Months) | C7: ='Exec Summ'!F16
B8: Interest Rate | C8: ='Exec Summ'!F17
B9: Interest Only (Months) | C9: ='Exec Summ'!F18
B10: Loan Origination Fee | C10: 0
B11: Loan Origination Fee | C11: =C5*C10
B12: Loan Payment (Monthly) | C12: =-PMT(C8/12,C7,C5)
B13: Loan Payment (Annual) | C13: =C12*12
B15: Year | C15: Month | D15: Interest | E15: Principal | F15: Sweep | G15: Balance | I15: Annual Debt Service | J15: Year 1 Principal | K15: Loan Funding | L15: Principal | M15: Interest
B16: =IF(C16/12=INT(C16/12),C16/12,"") | C16: 1 | D16: =C5*C8/12 | E16: =IF(C16<=$C$9,0,$C$12-D16) | G16: =C5-E16
B17: =IF(C17/12=INT(C17/12),C17/12,"") | C17: 2 | D17: =G16*$C$8/12 | E17: =IF(C17<=$C$9,0,$C$12-D17) | G17: =G16-E17
B18: =IF(C18/12=INT(C18/12),C18/12,"") | C18: 3 | D18: =G17*$C$8/12 | E18: =IF(C18<=$C$9,0,$C$12-D18) | G18: =G17-E18
B19: =IF(C19/12=INT(C19/12),C19/12,"") | C19: 4 | D19: =G18*$C$8/12 | E19: =IF(C19<=$C$9,0,$C$12-D19) | G19: =G18-E19
B20: =IF(C20/12=INT(C20/12),C20/12,"") | C20: 5 | D20: =G19*$C$8/12 | E20: =IF(C20<=$C$9,0,$C$12-D20) | G20: =G19-E20
B21: =IF(C21/12=INT(C21/12),C21/12,"") | C21: 6 | D21: =G20*$C$8/12 | E21: =IF(C21<=$C$9,0,$C$12-D21) | G21: =G20-E21
B22: =IF(C22/12=INT(C22/12),C22/12,"") | C22: 7 | D22: =G21*$C$8/12 | E22: =IF(C22<=$C$9,0,$C$12-D22) | G22: =G21-E22
B23: =IF(C23/12=INT(C23/12),C23/12,"") | C23: 8 | D23: =G22*$C$8/12 | E23: =IF(C23<=$C$9,0,$C$12-D23) | G23: =G22-E23
B24: =IF(C24/12=INT(C24/12),C24/12,"") | C24: 9 | D24: =G23*$C$8/12 | E24: =IF(C24<=$C$9,0,$C$12-D24) | G24: =G23-E24
B25: =IF(C25/12=INT(C25/12),C25/12,"") | C25: 10 | D25: =G24*$C$8/12 | E25: =IF(C25<=$C$9,0,$C$12-D25) | G25: =G24-E25
B26: =IF(C26/12=INT(C26/12),C26/12,"") | C26: 11 | D26: =G25*$C$8/12 | E26: =IF(C26<=$C$9,0,$C$12-D26) | G26: =G25-E26
B27: =IF(C27/12=INT(C27/12),C27/12,"") | C27: 12 | D27: =G26*$C$8/12 | E27: =IF(C27<=$C$9,0,$C$12-D27) | G27: =G26-E27 | I27: =SUM(D16:F27) | J27: =SUM(E16:E27) | K27: 0 | L27: =SUM(E16:E27) | M27: =SUM(D16:D27)
B28: =IF(C28/12=INT(C28/12),C28/12,"") | C28: 13 | D28: =G27*$C$8/12 | E28: =IF(C28<=$C$9,0,$C$12-D28) | G28: =G27-E28
B29: =IF(C29/12=INT(C29/12),C29/12,"") | C29: 14 | D29: =G28*$C$8/12 | E29: =IF(C29<=$C$9,0,$C$12-D29) | G29: =G28-E29
B30: =IF(C30/12=INT(C30/12),C30/12,"") | C30: 15 | D30: =G29*$C$8/12 | E30: =IF(C30<=$C$9,0,$C$12-D30) | G30: =G29-E30
B31: =IF(C31/12=INT(C31/12),C31/12,"") | C31: 16 | D31: =G30*$C$8/12 | E31: =IF(C31<=$C$9,0,$C$12-D31) | G31: =G30-E31
B32: =IF(C32/12=INT(C32/12),C32/12,"") | C32: 17 | D32: =G31*$C$8/12 | E32: =IF(C32<=$C$9,0,$C$12-D32) | G32: =G31-E32
B33: =IF(C33/12=INT(C33/12),C33/12,"") | C33: 18 | D33: =G32*$C$8/12 | E33: =IF(C33<=$C$9,0,$C$12-D33) | G33: =G32-E33
B34: =IF(C34/12=INT(C34/12),C34/12,"") | C34: 19 | D34: =G33*$C$8/12 | E34: =IF(C34<=$C$9,0,$C$12-D34) | G34: =G33-E34
B35: =IF(C35/12=INT(C35/12),C35/12,"") | C35: 20 | D35: =G34*$C$8/12 | E35: =IF(C35<=$C$9,0,$C$12-D35) | G35: =G34-E35
B36: =IF(C36/12=INT(C36/12),C36/12,"") | C36: 21 | D36: =G35*$C$8/12 | E36: =IF(C36<=$C$9,0,$C$12-D36) | G36: =G35-E36
B37: =IF(C37/12=INT(C37/12),C37/12,"") | C37: 22 | D37: =G36*$C$8/12 | E37: =IF(C37<=$C$9,0,$C$12-D37) | G37: =G36-E37
B38: =IF(C38/12=INT(C38/12),C38/12,"") | C38: 23 | D38: =G37*$C$8/12 | E38: =IF(C38<=$C$9,0,$C$12-D38) | G38: =G37-E38
B39: =IF(C39/12=INT(C39/12),C39/12,"") | C39: 24 | D39: =G38*$C$8/12 | E39: =IF(C39<=$C$9,0,$C$12-D39) | G39: =G38-E39 | I39: =SUM(D28:F39) | K39: 0 | L39: =SUM(E28:E39) | M39: =SUM(D28:D39)
B40: =IF(C40/12=INT(C40/12),C40/12,"") | C40: 25 | D40: =G39*$C$8/12 | E40: =IF(C40<=$C$9,0,$C$12-D40) | G40: =G39-E40
B41: =IF(C41/12=INT(C41/12),C41/12,"") | C41: 26 | D41: =G40*$C$8/12 | E41: =IF(C41<=$C$9,0,$C$12-D41) | G41: =G40-E41
B42: =IF(C42/12=INT(C42/12),C42/12,"") | C42: 27 | D42: =G41*$C$8/12 | E42: =IF(C42<=$C$9,0,$C$12-D42) | G42: =G41-E42
B43: =IF(C43/12=INT(C43/12),C43/12,"") | C43: 28 | D43: =G42*$C$8/12 | E43: =IF(C43<=$C$9,0,$C$12-D43) | G43: =G42-E43
B44: =IF(C44/12=INT(C44/12),C44/12,"") | C44: 29 | D44: =G43*$C$8/12 | E44: =IF(C44<=$C$9,0,$C$12-D44) | G44: =G43-E44
B45: =IF(C45/12=INT(C45/12),C45/12,"") | C45: 30 | D45: =G44*$C$8/12 | E45: =IF(C45<=$C$9,0,$C$12-D45) | G45: =G44-E45
B46: =IF(C46/12=INT(C46/12),C46/12,"") | C46: 31 | D46: =G45*$C$8/12 | E46: =IF(C46<=$C$9,0,$C$12-D46) | G46: =G45-E46
B47: =IF(C47/12=INT(C47/12),C47/12,"") | C47: 32 | D47: =G46*$C$8/12 | E47: =IF(C47<=$C$9,0,$C$12-D47) | G47: =G46-E47
B48: =IF(C48/12=INT(C48/12),C48/12,"") | C48: 33 | D48: =G47*$C$8/12 | E48: =IF(C48<=$C$9,0,$C$12-D48) | G48: =G47-E48
B49: =IF(C49/12=INT(C49/12),C49/12,"") | C49: 34 | D49: =G48*$C$8/12 | E49: =IF(C49<=$C$9,0,$C$12-D49) | G49: =G48-E49
B50: =IF(C50/12=INT(C50/12),C50/12,"") | C50: 35 | D50: =G49*$C$8/12 | E50: =IF(C50<=$C$9,0,$C$12-D50) | G50: =G49-E50
B51: =IF(C51/12=INT(C51/12),C51/12,"") | C51: 36 | D51: =G50*$C$8/12 | E51: =IF(C51<=$C$9,0,$C$12-D51) | G51: =G50-E51 | I51: =SUM(D40:F51) | K51: 0 | L51: =SUM(E40:E51) | M51: =SUM(D40:D51)
B52: =IF(C52/12=INT(C52/12),C52/12,"") | C52: 37 | D52: =G51*$C$8/12 | E52: =IF(C52<=$C$9,0,$C$12-D52) | G52: =G51-E52
B53: =IF(C53/12=INT(C53/12),C53/12,"") | C53: 38 | D53: =G52*$C$8/12 | E53: =IF(C53<=$C$9,0,$C$12-D53) | G53: =G52-E53
B54: =IF(C54/12=INT(C54/12),C54/12,"") | C54: 39 | D54: =G53*$C$8/12 | E54: =IF(C54<=$C$9,0,$C$12-D54) | G54: =G53-E54
B55: =IF(C55/12=INT(C55/12),C55/12,"") | C55: 40 | D55: =G54*$C$8/12 | E55: =IF(C55<=$C$9,0,$C$12-D55) | G55: =G54-E55
B56: =IF(C56/12=INT(C56/12),C56/12,"") | C56: 41 | D56: =G55*$C$8/12 | E56: =IF(C56<=$C$9,0,$C$12-D56) | G56: =G55-E56
B57: =IF(C57/12=INT(C57/12),C57/12,"") | C57: 42 | D57: =G56*$C$8/12 | E57: =IF(C57<=$C$9,0,$C$12-D57) | G57: =G56-E57
B58: =IF(C58/12=INT(C58/12),C58/12,"") | C58: 43 | D58: =G57*$C$8/12 | E58: =IF(C58<=$C$9,0,$C$12-D58) | G58: =G57-E58
B59: =IF(C59/12=INT(C59/12),C59/12,"") | C59: 44 | D59: =G58*$C$8/12 | E59: =IF(C59<=$C$9,0,$C$12-D59) | G59: =G58-E59
B60: =IF(C60/12=INT(C60/12),C60/12,"") | C60: 45 | D60: =G59*$C$8/12 | E60: =IF(C60<=$C$9,0,$C$12-D60) | G60: =G59-E60
B61: =IF(C61/12=INT(C61/12),C61/12,"") | C61: 46 | D61: =G60*$C$8/12 | E61: =IF(C61<=$C$9,0,$C$12-D61) | G61: =G60-E61
B62: =IF(C62/12=INT(C62/12),C62/12,"") | C62: 47 | D62: =G61*$C$8/12 | E62: =IF(C62<=$C$9,0,$C$12-D62) | G62: =G61-E62
B63: =IF(C63/12=INT(C63/12),C63/12,"") | C63: 48 | D63: =G62*$C$8/12 | E63: =IF(C63<=$C$9,0,$C$12-D63) | G63: =G62-E63 | I63: =SUM(D52:F63) | K63: 0 | L63: =SUM(E52:E63) | M63: =SUM(D52:D63)
B64: =IF(C64/12=INT(C64/12),C64/12,"") | C64: 49 | D64: =G63*$C$8/12 | E64: =IF(C64<=$C$9,0,$C$12-D64) | G64: =G63-E64
B65: =IF(C65/12=INT(C65/12),C65/12,"") | C65: 50 | D65: =G64*$C$8/12 | E65: =IF(C65<=$C$9,0,$C$12-D65) | G65: =G64-E65
B66: =IF(C66/12=INT(C66/12),C66/12,"") | C66: 51 | D66: =G65*$C$8/12 | E66: =IF(C66<=$C$9,0,$C$12-D66) | G66: =G65-E66
B67: =IF(C67/12=INT(C67/12),C67/12,"") | C67: 52 | D67: =G66*$C$8/12 | E67: =IF(C67<=$C$9,0,$C$12-D67) | G67: =G66-E67
B68: =IF(C68/12=INT(C68/12),C68/12,"") | C68: 53 | D68: =G67*$C$8/12 | E68: =IF(C68<=$C$9,0,$C$12-D68) | G68: =G67-E68
B69: =IF(C69/12=INT(C69/12),C69/12,"") | C69: 54 | D69: =G68*$C$8/12 | E69: =IF(C69<=$C$9,0,$C$12-D69) | G69: =G68-E69
B70: =IF(C70/12=INT(C70/12),C70/12,"") | C70: 55 | D70: =G69*$C$8/12 | E70: =IF(C70<=$C$9,0,$C$12-D70) | G70: =G69-E70
B71: =IF(C71/12=INT(C71/12),C71/12,"") | C71: 56 | D71: =G70*$C$8/12 | E71: =IF(C71<=$C$9,0,$C$12-D71) | G71: =G70-E71
B72: =IF(C72/12=INT(C72/12),C72/12,"") | C72: 57 | D72: =G71*$C$8/12 | E72: =IF(C72<=$C$9,0,$C$12-D72) | G72: =G71-E72
B73: =IF(C73/12=INT(C73/12),C73/12,"") | C73: 58 | D73: =G72*$C$8/12 | E73: =IF(C73<=$C$9,0,$C$12-D73) | G73: =G72-E73
B74: =IF(C74/12=INT(C74/12),C74/12,"") | C74: 59 | D74: =G73*$C$8/12 | E74: =IF(C74<=$C$9,0,$C$12-D74) | G74: =G73-E74
B75: =IF(C75/12=INT(C75/12),C75/12,"") | C75: 60 | D75: =G74*$C$8/12 | E75: =IF(C75<=$C$9,0,$C$12-D75) | G75: =G74-E75 | I75: =SUM(D64:F75) | L75: =SUM(E64:E75) | M75: =SUM(D64:D75)
B76: =IF(C76/12=INT(C76/12),C76/12,"") | C76: 61 | D76: =G75*$C$8/12 | E76: =IF(C76<=$C$9,0,$C$12-D76) | G76: =G75-E76
B77: =IF(C77/12=INT(C77/12),C77/12,"") | C77: 62 | D77: =G76*$C$8/12 | E77: =IF(C77<=$C$9,0,$C$12-D77) | G77: =G76-E77
B78: =IF(C78/12=INT(C78/12),C78/12,"") | C78: 63 | D78: =G77*$C$8/12 | E78: =IF(C78<=$C$9,0,$C$12-D78) | G78: =G77-E78
B79: =IF(C79/12=INT(C79/12),C79/12,"") | C79: 64 | D79: =G78*$C$8/12 | E79: =IF(C79<=$C$9,0,$C$12-D79) | G79: =G78-E79
B80: =IF(C80/12=INT(C80/12),C80/12,"") | C80: 65 | D80: =G79*$C$8/12 | E80: =IF(C80<=$C$9,0,$C$12-D80) | G80: =G79-E80
B81: =IF(C81/12=INT(C81/12),C81/12,"") | C81: 66 | D81: =G80*$C$8/12 | E81: =IF(C81<=$C$9,0,$C$12-D81) | G81: =G80-E81
B82: =IF(C82/12=INT(C82/12),C82/12,"") | C82: 67 | D82: =G81*$C$8/12 | E82: =IF(C82<=$C$9,0,$C$12-D82) | G82: =G81-E82
B83: =IF(C83/12=INT(C83/12),C83/12,"") | C83: 68 | D83: =G82*$C$8/12 | E83: =IF(C83<=$C$9,0,$C$12-D83) | G83: =G82-E83
B84: =IF(C84/12=INT(C84/12),C84/12,"") | C84: 69 | D84: =G83*$C$8/12 | E84: =IF(C84<=$C$9,0,$C$12-D84) | G84: =G83-E84
B85: =IF(C85/12=INT(C85/12),C85/12,"") | C85: 70 | D85: =G84*$C$8/12 | E85: =IF(C85<=$C$9,0,$C$12-D85) | G85: =G84-E85
B86: =IF(C86/12=INT(C86/12),C86/12,"") | C86: 71 | D86: =G85*$C$8/12 | E86: =IF(C86<=$C$9,0,$C$12-D86) | G86: =G85-E86
B87: =IF(C87/12=INT(C87/12),C87/12,"") | C87: 72 | D87: =G86*$C$8/12 | E87: =IF(C87<=$C$9,0,$C$12-D87) | G87: =G86-E87 | I87: =SUM(D76:F87) | L87: =SUM(E76:E87) | M87: =SUM(D76:D87)
B88: =IF(C88/12=INT(C88/12),C88/12,"") | C88: 73 | D88: =G87*$C$8/12 | E88: =IF(C88<=$C$9,0,$C$12-D88) | G88: =G87-E88
B89: =IF(C89/12=INT(C89/12),C89/12,"") | C89: 74 | D89: =G88*$C$8/12 | E89: =IF(C89<=$C$9,0,$C$12-D89) | G89: =G88-E89
B90: =IF(C90/12=INT(C90/12),C90/12,"") | C90: 75 | D90: =G89*$C$8/12 | E90: =IF(C90<=$C$9,0,$C$12-D90) | G90: =G89-E90
B91: =IF(C91/12=INT(C91/12),C91/12,"") | C91: 76 | D91: =G90*$C$8/12 | E91: =IF(C91<=$C$9,0,$C$12-D91) | G91: =G90-E91
B92: =IF(C92/12=INT(C92/12),C92/12,"") | C92: 77 | D92: =G91*$C$8/12 | E92: =IF(C92<=$C$9,0,$C$12-D92) | G92: =G91-E92
B93: =IF(C93/12=INT(C93/12),C93/12,"") | C93: 78 | D93: =G92*$C$8/12 | E93: =IF(C93<=$C$9,0,$C$12-D93) | G93: =G92-E93
B94: =IF(C94/12=INT(C94/12),C94/12,"") | C94: 79 | D94: =G93*$C$8/12 | E94: =IF(C94<=$C$9,0,$C$12-D94) | G94: =G93-E94
B95: =IF(C95/12=INT(C95/12),C95/12,"") | C95: 80 | D95: =G94*$C$8/12 | E95: =IF(C95<=$C$9,0,$C$12-D95) | G95: =G94-E95
B96: =IF(C96/12=INT(C96/12),C96/12,"") | C96: 81 | D96: =G95*$C$8/12 | E96: =IF(C96<=$C$9,0,$C$12-D96) | G96: =G95-E96
B97: =IF(C97/12=INT(C97/12),C97/12,"") | C97: 82 | D97: =G96*$C$8/12 | E97: =IF(C97<=$C$9,0,$C$12-D97) | G97: =G96-E97
B98: =IF(C98/12=INT(C98/12),C98/12,"") | C98: 83 | D98: =G97*$C$8/12 | E98: =IF(C98<=$C$9,0,$C$12-D98) | G98: =G97-E98
B99: =IF(C99/12=INT(C99/12),C99/12,"") | C99: 84 | D99: =G98*$C$8/12 | E99: =IF(C99<=$C$9,0,$C$12-D99) | G99: =G98-E99 | I99: =SUM(D88:F99) | L99: =SUM(E88:E99) | M99: =SUM(D88:D99)
B100: =IF(C100/12=INT(C100/12),C100/12,"") | C100: 85 | D100: =G99*$C$8/12 | E100: =IF(C100<=$C$9,0,$C$12-D100) | G100: =G99-E100
B101: =IF(C101/12=INT(C101/12),C101/12,"") | C101: 86 | D101: =G100*$C$8/12 | E101: =IF(C101<=$C$9,0,$C$12-D101) | G101: =G100-E101
B102: =IF(C102/12=INT(C102/12),C102/12,"") | C102: 87 | D102: =G101*$C$8/12 | E102: =IF(C102<=$C$9,0,$C$12-D102) | G102: =G101-E102
B103: =IF(C103/12=INT(C103/12),C103/12,"") | C103: 88 | D103: =G102*$C$8/12 | E103: =IF(C103<=$C$9,0,$C$12-D103) | G103: =G102-E103
B104: =IF(C104/12=INT(C104/12),C104/12,"") | C104: 89 | D104: =G103*$C$8/12 | E104: =IF(C104<=$C$9,0,$C$12-D104) | G104: =G103-E104
...

Sheet Exhibits-->

Sheet OM Exhibits
B2: EXECUTIVE SUMMARY | E2: FOR SITE PLAN | I2: FOR SITE PLAN | N2: PROPERTY OVERVIEW
B3: THE OFFERING | E3: SUITE # | F3: TENANT | G3: SF | J3: 1 | N3: Property Details
B4: PURCHASE PRICE | C4: ='Exec Summ'!H21 | E4: {=_xlfn._xlws.FILTER('One-line RR'!D7:D12,'One-line RR'!D7:D12<>"")} | F4: =INDEX('One-line RR'!F$7:F$12,MATCH($E4,'One-line RR'!$D$7:$D$12,0)) | G4: =INDEX('One-line RR'!H$7:H$12,MATCH($E4,'One-line RR'!$D$7:$D$12,0)) | I4: 1 | J4: {=_xlfn._xlws.SORT(_xlfn._xlws.FILTER('One-line RR'!$D$8:$H$12,'One-line RR'!$AE$8:$AE$12='OM Exhibits'!$J$3),1,1,)} | N4: Address | O4: =Global!G8&"., "&Global!G9
B5: IN-PLACE CAP RATE | C5: ='Exec Summ'!H25 | E5: 2 | F5: =INDEX('One-line RR'!F$7:F$12,MATCH($E5,'One-line RR'!$D$7:$D$12,0)) | G5: =INDEX('One-line RR'!H$7:H$12,MATCH($E5,'One-line RR'!$D$7:$D$12,0)) | I5: =I4+1 | N5: GLA | O5: =Global!G18
B6: IN-PLACE NOI | C6: =C4*C5 | D6: =IF(C6='Exec Summ'!J10,"ok","!") | E6: 3 | F6: =INDEX('One-line RR'!F$7:F$12,MATCH($E6,'One-line RR'!$D$7:$D$12,0)) | G6: =INDEX('One-line RR'!H$7:H$12,MATCH($E6,'One-line RR'!$D$7:$D$12,0)) | I6: =I5+1 | N6: Number of Buildings | O6: 11
B7: PRO FORMA CAP RATE (YR 2) | C7: ='Exec Summ'!H26 | E7: 4 | F7: =INDEX('One-line RR'!F$7:F$12,MATCH($E7,'One-line RR'!$D$7:$D$12,0)) | G7: =INDEX('One-line RR'!H$7:H$12,MATCH($E7,'One-line RR'!$D$7:$D$12,0)) | I7: =I6+1 | N7: Year Built/Renovated | O7: =C12
B8: PRO FORMA NOI (YR 2) | C8: =Proforma!F44 | E8: 112 | F8: =INDEX('One-line RR'!F$7:F$12,MATCH($E8,'One-line RR'!$D$7:$D$12,0)) | G8: =INDEX('One-line RR'!H$7:H$12,MATCH($E8,'One-line RR'!$D$7:$D$12,0)) | I8: =I7+1 | N8: Parking Ratio | O8: 4.13/1,000 SF
B9: GLA | C9: ='Exec Summ'!J7 | E9: 6 | F9: =INDEX('One-line RR'!F$7:F$12,MATCH($E9,'One-line RR'!$D$7:$D$12,0)) | G9: =INDEX('One-line RR'!H$7:H$12,MATCH($E9,'One-line RR'!$D$7:$D$12,0)) | I9: =I8+1 | N9: Land Acres | O9: ='Tax-Assessor Info'!I24
B10: UNIT OCCUPANCY | C10: ='Exec Summ'!J8 | F10: =INDEX('One-line RR'!F$7:F$12,MATCH($E10,'One-line RR'!$D$7:$D$12,0)) | G10: =INDEX('One-line RR'!H$7:H$12,MATCH($E10,'One-line RR'!$D$7:$D$12,0)) | N10: County | O10: Solano
B11: LAND AREA | C11: 19.12 | F11: =INDEX('One-line RR'!F$7:F$12,MATCH($E11,'One-line RR'!$D$7:$D$12,0)) | G11: =INDEX('One-line RR'!H$7:H$12,MATCH($E11,'One-line RR'!$D$7:$D$12,0)) | J11: =J3+1 | N11: APN | O11: ='Tax-Assessor Info'!G6
B12: YEAR BUILT/RENOVATED | C12: 1961/1986 | F12: =INDEX('One-line RR'!F$7:F$12,MATCH($E12,'One-line RR'!$D$7:$D$12,0)) | G12: =INDEX('One-line RR'!H$7:H$12,MATCH($E12,'One-line RR'!$D$7:$D$12,0)) | I12: =I9+1 | J12: {=_xlfn._xlws.SORT(_xlfn._xlws.FILTER('One-line RR'!$D$8:$H$12,'One-line RR'!$AE$8:$AE$12='OM Exhibits'!$J$11),1,1,)} | N12: Frontage | O12: 359' on Sonoma Blvd
B13: ZONING | C13: CP (Central Corridor Commercial) | F13: =INDEX('One-line RR'!F$7:F$12,MATCH($E13,'One-line RR'!$D$7:$D$12,0)) | G13: =INDEX('One-line RR'!H$7:H$12,MATCH($E13,'One-line RR'!$D$7:$D$12,0)) | I13: =I12+1 | N13: Highway Access | O13: Direct Access to CA-29/CA-37 via Redwood St/Valle Vista Ave
B14: APN | C14: ='Tax-Assessor Info'!G6 | F14: =INDEX('One-line RR'!F$7:F$12,MATCH($E14,'One-line RR'!$D$7:$D$12,0)) | G14: =INDEX('One-line RR'!H$7:H$12,MATCH($E14,'One-line RR'!$D$7:$D$12,0)) | I14: =I13+1
F15: =INDEX('One-line RR'!F$7:F$12,MATCH($E15,'One-line RR'!$D$7:$D$12,0)) | G15: =INDEX('One-line RR'!H$7:H$12,MATCH($E15,'One-line RR'!$D$7:$D$12,0)) | I15: =I14+1
F16: =INDEX('One-line RR'!F$7:F$12,MATCH($E16,'One-line RR'!$D$7:$D$12,0)) | G16: =INDEX('One-line RR'!H$7:H$12,MATCH($E16,'One-line RR'!$D$7:$D$12,0)) | I16: =I15+1
F17: =INDEX('One-line RR'!F$7:F$12,MATCH($E17,'One-line RR'!$D$7:$D$12,0)) | G17: =INDEX('One-line RR'!H$7:H$12,MATCH($E17,'One-line RR'!$D$7:$D$12,0))
F18: =INDEX('One-line RR'!F$7:F$12,MATCH($E18,'One-line RR'!$D$7:$D$12,0)) | G18: =INDEX('One-line RR'!H$7:H$12,MATCH($E18,'One-line RR'!$D$7:$D$12,0)) | J18: =J11+1
F19: =INDEX('One-line RR'!F$7:F$12,MATCH($E19,'One-line RR'!$D$7:$D$12,0)) | G19: =INDEX('One-line RR'!H$7:H$12,MATCH($E19,'One-line RR'!$D$7:$D$12,0)) | I19: =I16+1 | J19: {=_xlfn._xlws.SORT(_xlfn._xlws.FILTER('One-line RR'!$D$8:$H$12,'One-line RR'!$AE$8:$AE$12='OM Exhibits'!$J$18),1,1,)}
F20: =INDEX('One-line RR'!F$7:F$12,MATCH($E20,'One-line RR'!$D$7:$D$12,0)) | G20: =INDEX('One-line RR'!H$7:H$12,MATCH($E20,'One-line RR'!$D$7:$D$12,0)) | I20: =I19+1
F21: =INDEX('One-line RR'!F$7:F$12,MATCH($E21,'One-line RR'!$D$7:$D$12,0)) | G21: =INDEX('One-line RR'!H$7:H$12,MATCH($E21,'One-line RR'!$D$7:$D$12,0)) | I21: =I20+1
F22: =INDEX('One-line RR'!F$7:F$12,MATCH($E22,'One-line RR'!$D$7:$D$12,0)) | G22: =INDEX('One-line RR'!H$7:H$12,MATCH($E22,'One-line RR'!$D$7:$D$12,0)) | I22: =I21+1
F23: =INDEX('One-line RR'!F$7:F$12,MATCH($E23,'One-line RR'!$D$7:$D$12,0)) | G23: =INDEX('One-line RR'!H$7:H$12,MATCH($E23,'One-line RR'!$D$7:$D$12,0)) | I23: =I22+1
F24: =INDEX('One-line RR'!F$7:F$12,MATCH($E24,'One-line RR'!$D$7:$D$12,0)) | G24: =INDEX('One-line RR'!H$7:H$12,MATCH($E24,'One-line RR'!$D$7:$D$12,0)) | I24: 17/18
F25: =INDEX('One-line RR'!F$7:F$12,MATCH($E25,'One-line RR'!$D$7:$D$12,0)) | G25: =INDEX('One-line RR'!H$7:H$12,MATCH($E25,'One-line RR'!$D$7:$D$12,0))
F26: =INDEX('One-line RR'!F$7:F$12,MATCH($E26,'One-line RR'!$D$7:$D$12,0)) | G26: =INDEX('One-line RR'!H$7:H$12,MATCH($E26,'One-line RR'!$D$7:$D$12,0)) | J26: =J18+1
F27: =INDEX('One-line RR'!F$7:F$12,MATCH($E27,'One-line RR'!$D$7:$D$12,0)) | G27: =INDEX('One-line RR'!H$7:H$12,MATCH($E27,'One-line RR'!$D$7:$D$12,0)) | I27: 19 | J27: {=_xlfn._xlws.SORT(_xlfn._xlws.FILTER('One-line RR'!$D$8:$H$12,'One-line RR'!$AE$8:$AE$12='OM Exhibits'!$J$26),1,1,)}
F28: =INDEX('One-line RR'!F$7:F$12,MATCH($E28,'One-line RR'!$D$7:$D$12,0)) | G28: =INDEX('One-line RR'!H$7:H$12,MATCH($E28,'One-line RR'!$D$7:$D$12,0)) | I28: =I27+1
F29: =INDEX('One-line RR'!F$7:F$12,MATCH($E29,'One-line RR'!$D$7:$D$12,0)) | G29: =INDEX('One-line RR'!H$7:H$12,MATCH($E29,'One-line RR'!$D$7:$D$12,0)) | I29: =I28+1
F30: =INDEX('One-line RR'!F$7:F$12,MATCH($E30,'One-line RR'!$D$7:$D$12,0)) | G30: =INDEX('One-line RR'!H$7:H$12,MATCH($E30,'One-line RR'!$D$7:$D$12,0)) | I30: =I29+1
F31: =INDEX('One-line RR'!F$7:F$12,MATCH($E31,'One-line RR'!$D$7:$D$12,0)) | G31: =INDEX('One-line RR'!H$7:H$12,MATCH($E31,'One-line RR'!$D$7:$D$12,0)) | I31: =I30+1
F32: =INDEX('One-line RR'!F$7:F$12,MATCH($E32,'One-line RR'!$D$7:$D$12,0)) | G32: =INDEX('One-line RR'!H$7:H$12,MATCH($E32,'One-line RR'!$D$7:$D$12,0)) | I32: =I31+1
F33: =INDEX('One-line RR'!F$7:F$12,MATCH($E33,'One-line RR'!$D$7:$D$12,0)) | G33: =INDEX('One-line RR'!H$7:H$12,MATCH($E33,'One-line RR'!$D$7:$D$12,0))
F34: =INDEX('One-line RR'!F$7:F$12,MATCH($E34,'One-line RR'!$D$7:$D$12,0)) | G34: =INDEX('One-line RR'!H$7:H$12,MATCH($E34,'One-line RR'!$D$7:$D$12,0)) | J34: =J26+1
F35: =INDEX('One-line RR'!F$7:F$12,MATCH($E35,'One-line RR'!$D$7:$D$12,0)) | G35: =INDEX('One-line RR'!H$7:H$12,MATCH($E35,'One-line RR'!$D$7:$D$12,0)) | I35: =I32+1 | J35: {=_xlfn._xlws.SORT(_xlfn._xlws.FILTER('One-line RR'!$D$8:$H$12,'One-line RR'!$AE$8:$AE$12='OM Exhibits'!$J$34),1,1,)}
F36: =INDEX('One-line RR'!F$7:F$12,MATCH($E36,'One-line RR'!$D$7:$D$12,0)) | G36: =INDEX('One-line RR'!H$7:H$12,MATCH($E36,'One-line RR'!$D$7:$D$12,0)) | I36: =I35+1
F37: =INDEX('One-line RR'!F$7:F$12,MATCH($E37,'One-line RR'!$D$7:$D$12,0)) | G37: =INDEX('One-line RR'!H$7:H$12,MATCH($E37,'One-line RR'!$D$7:$D$12,0)) | I37: =I36+1
F38: =INDEX('One-line RR'!F$7:F$12,MATCH($E38,'One-line RR'!$D$7:$D$12,0)) | G38: =INDEX('One-line RR'!H$7:H$12,MATCH($E38,'One-line RR'!$D$7:$D$12,0)) | I38: =I37+1
F39: =INDEX('One-line RR'!F$7:F$12,MATCH($E39,'One-line RR'!$D$7:$D$12,0)) | G39: =INDEX('One-line RR'!H$7:H$12,MATCH($E39,'One-line RR'!$D$7:$D$12,0)) | I39: =I38+1
F40: =INDEX('One-line RR'!F$7:F$12,MATCH($E40,'One-line RR'!$D$7:$D$12,0)) | G40: =INDEX('One-line RR'!H$7:H$12,MATCH($E40,'One-line RR'!$D$7:$D$12,0))
F41: =INDEX('One-line RR'!F$7:F$12,MATCH($E41,'One-line RR'!$D$7:$D$12,0)) | G41: =INDEX('One-line RR'!H$7:H$12,MATCH($E41,'One-line RR'!$D$7:$D$12,0)) | J41: =J34+1
F42: =INDEX('One-line RR'!F$7:F$12,MATCH($E42,'One-line RR'!$D$7:$D$12,0)) | G42: =INDEX('One-line RR'!H$7:H$12,MATCH($E42,'One-line RR'!$D$7:$D$12,0)) | I42: =I39+1 | J42: {=_xlfn._xlws.SORT(_xlfn._xlws.FILTER('One-line RR'!$D$8:$H$12,'One-line RR'!$AE$8:$AE$12='OM Exhibits'!$J$41),1,1,)}
F43: =INDEX('One-line RR'!F$7:F$12,MATCH($E43,'One-line RR'!$D$7:$D$12,0)) | G43: =INDEX('One-line RR'!H$7:H$12,MATCH($E43,'One-line RR'!$D$7:$D$12,0)) | I43: =I42+1
F44: =INDEX('One-line RR'!F$7:F$12,MATCH($E44,'One-line RR'!$D$7:$D$12,0)) | G44: =INDEX('One-line RR'!H$7:H$12,MATCH($E44,'One-line RR'!$D$7:$D$12,0)) | I44: =I43+1
F45: =INDEX('One-line RR'!F$7:F$12,MATCH($E45,'One-line RR'!$D$7:$D$12,0)) | G45: =INDEX('One-line RR'!H$7:H$12,MATCH($E45,'One-line RR'!$D$7:$D$12,0)) | I45: =I44+1
F46: =INDEX('One-line RR'!F$7:F$12,MATCH($E46,'One-line RR'!$D$7:$D$12,0)) | G46: =INDEX('One-line RR'!H$7:H$12,MATCH($E46,'One-line RR'!$D$7:$D$12,0)) | I46: =I45+1
F47: =INDEX('One-line RR'!F$7:F$12,MATCH($E47,'One-line RR'!$D$7:$D$12,0)) | G47: =INDEX('One-line RR'!H$7:H$12,MATCH($E47,'One-line RR'!$D$7:$D$12,0)) | I47: =I46+1
F48: =INDEX('One-line RR'!F$7:F$12,MATCH($E48,'One-line RR'!$D$7:$D$12,0)) | G48: =INDEX('One-line RR'!H$7:H$12,MATCH($E48,'One-line RR'!$D$7:$D$12,0))
F49: =INDEX('One-line RR'!F$7:F$12,MATCH($E49,'One-line RR'!$D$7:$D$12,0)) | G49: =INDEX('One-line RR'!H$7:H$12,MATCH($E49,'One-line RR'!$D$7:$D$12,0)) | J49: =J41+1
F50: =INDEX('One-line RR'!F$7:F$12,MATCH($E50,'One-line RR'!$D$7:$D$12,0)) | G50: =INDEX('One-line RR'!H$7:H$12,MATCH($E50,'One-line RR'!$D$7:$D$12,0)) | I50: =I47+1 | J50: {=_xlfn._xlws.SORT(_xlfn._xlws.FILTER('One-line RR'!$D$8:$H$12,'One-line RR'!$AE$8:$AE$12='OM Exhibits'!$J$49),1,1,)}
F51: =INDEX('One-line RR'!F$7:F$12,MATCH($E51,'One-line RR'!$D$7:$D$12,0)) | G51: =INDEX('One-line RR'!H$7:H$12,MATCH($E51,'One-line RR'!$D$7:$D$12,0)) | I51: =I50+1
F52: =INDEX('One-line RR'!F$7:F$12,MATCH($E52,'One-line RR'!$D$7:$D$12,0)) | G52: =INDEX('One-line RR'!H$7:H$12,MATCH($E52,'One-line RR'!$D$7:$D$12,0)) | I52: =I51+1
J54: =J49+1
I55: =I52+1 | J55: {=_xlfn._xlws.SORT(_xlfn._xlws.FILTER('One-line RR'!$D$8:$H$12,'One-line RR'!$AE$8:$AE$12='OM Exhibits'!$J$54),1,1,)}
I56: =I55+1
I57: =I56+1
I58: =I57+1
I59: =I58+1
J61: =J54+1
I62: =I59+1 | J62: {=_xlfn._xlws.SORT(_xlfn._xlws.FILTER('One-line RR'!$D$8:$H$12,'One-line RR'!$AE$8:$AE$12='OM Exhibits'!$J$61),1,1,)}
I63: =I62+1
J65: =J61+1
I66: =I63+1 | J66: {=_xlfn._xlws.SORT(_xlfn._xlws.FILTER('One-line RR'!$D$8:$H$12,'One-line RR'!$AE$8:$AE$12='OM Exhibits'!$J$65),1,1,)}
I67: =I66+1
J70: =J65+1
I71: =I67+1 | J71: {=_xlfn._xlws.SORT(_xlfn._xlws.FILTER('One-line RR'!$D$8:$H$12,'One-line RR'!$AE$8:$AE$12='OM Exhibits'!$J$70),1,1,)}

Sheet Notes
C3: - Detailed RR - Change current to >= analysis start date
C4: - One Line RR, Add columns with Annual total rent and recoveries; add Vacant SF
C5: - Group MLAs by SF - <10k SF = $14.50; >10k & <=20k = $13.50; >20k = $12.50 PSF | K5: -> Francis said the MLA's are assumed based on Rental Rates.
C6: - Detailed rent roll should only show rents from 10/1/2025 +
C11: Notes:
C12: - Used P&Ls with 'Draft' label because 2024 heading labeled 'Actual', whereas the 2024 heading on file without 'Draft' watermark is labeled with 'Forecast'.
C13: - Updated PARKING amount total PARKING interior/exterior $1,840/mo + Other paking charges $444/mo. Total annual parking ($27k)
C14: - Rent Adjustment
C23: Questions?
C24: - Need to project parking reveue but unsure how many spaces there are; how many interior/exterior parking spaces?
C25: - Need to adjust General Vacancy %
C26: - Should we assume Static Vacancy for some tenants?
C27: -
C28: -
C29: -
... C54: MARKET LEASING ASSUMPTIONS: Added a new '$19.00 PSF' bucket to the 'MLAs' tab (NNN, 60-month term, 75% renewal probability, 3-month downtime, 1 month free rent new/0 months renewal, 3% annual escalation) as a placeholder market-rate assumption for this small 4-suite retail/medical strip, roughly in line with the property's ~$18.36/SF blended in-place rent. This should be refined against actual comps before finalizing valuation.

Sheet Global
C3: GLOBAL ASSUMPTIONS | N3: =$G$7 | Q3: ='Rent Roll-Detailed'!$H$65
D5: Property Details | I5: Main Takeaways
D7: Property Name | G7: 1603 Ridgeside Drive
D8: Street Address | G8: 1603 Ridgeside Drive
D9: City, State, Zip | G9: Mount Airy, MD 21771 (Carroll County)
D11: General | I11: Base Case Underwriting
D13: Valuation Start Date | G13: 46204 | I13: Valuation Start Date | N13: =G13
S14: Notes:
D15: Building Size by Property Type | I15: Building Size by Property Type
D16: Occupied | G16: =N16 | I16: Occupied | N16: ='One-line RR'!H17
D17: Vacant | G17: =N17 | I17: Vacant | N17: ='Rent Roll-Detailed'!H64
D18: Total | G18: =SUM(G16:G17) | I18: Total | N18: =SUM(N16:N17)
D19: In-place Occupancy | G19: =G16/G18 | I19: In-place Occupancy | N19: =N16/N18
D21: General Vacancy* | I21: General Vacancy & Credit Loss Factor
D22: Gross up Revenue by Absorption & Turnover | G22: Y1=0%, Y2=9.167%, 10% Thereafter | N22: Y1=0%, Y2=9.167%, 10% Thereafter
D25: Collection Loss | G25: 0 | I25: Inflation Rates (beginning 4/1/2026)
I26: General | N26: Y1=0%, 3% Thereafter
D27: Inflation Rates (beginning 10/1/2026) | I27: Capital/Expenses | N27: Y1=0%, 3% Thereafter
D28: General | G28: Y1=0%, 3% Thereafter | I28: Property Taxes | N28: Y1=0%, 3% Thereafter
D29: Expenses/Misc. Rev./Reimbursables | G29: Y1=0%, 3% Thereafter | I29: Mkt. Rent
D30: Property Taxes | G30: Y1=0%, 3% Thereafter | K30: ARGUS Rental | L30: Subject | M30: Est. New Const. | N30: Discount to
D31: Market Rent | F31: =G13 | G31: 0 | K31: Inflation Rate | L31: NNN | M31: NNN | N31: New Const.
F32: =EDATE(F31,12) | G32: 0.03 | J32: =N13 | K32: 0 | L32: ='One-line RR'!S13 | M32: N/A | N32: =IFERROR((M32-L32)/M32,"")
F33: =EDATE(F32,12) | G33: 0.03 | J33: =EDATE(J32,12) | K33: 0.03 | L33: =L32*(1+K33)
F34: =EDATE(F33,12) | G34: 0.03 | J34: Thereafter | K34: 0.03 | L34: =L33*(1+K34)
F35: =EDATE(F34,12) | G35: 0.03
F36: =EDATE(F35,12) | G36: 0.03 | I36: Operating Expense Assumptions
F37: Thereafter | G37: Thereafter | I37: Operating Expenses | N37: 2026 Budget + 0.25%
I38: Management Fee (% of EGR) | N38: 0
D39: Operating Expense Assumptions | I39: Property Taxes | N39: 2026 Budget + 0.25%
D40: Operating Expenses | G40: 2026 Budget + 0.25%
D41: Management Fee (% of EGR) | G41: 0
D42: Property Taxes | G42: 2026 Budget + 0.25% | I42: Upfront Building Capital Expenses | N42: 0
D45: Capital Reserve | G45: 0 | I45: Capital Reserve | N45: 0
D47: Building Capital Expenses | G47: N/A | I47: Building Capital Expenses | N47: N/A

Sheet Proforma
C3: PROFORMA | O3: =Global!$G$7 | R3: ='Rent Roll-Detailed'!$H$65
F5: 1 | G5: =F5+1 | H5: =G5+1 | I5: =H5+1 | J5: =I5+1 | K5: =J5+1 | L5: =K5+1 | M5: =L5+1 | N5: =M5+1 | O5: =N5+1
F6: =EOMONTH(Global!$G$13,11) | G6: =EOMONTH(F6,12) | H6: =EOMONTH(G6,12) | I6: =EOMONTH(H6,12) | J6: =EOMONTH(I6,12) | K6: =EOMONTH(J6,12) | L6: =EOMONTH(K6,12) | M6: =EOMONTH(L6,12) | N6: =EOMONTH(M6,12) | O6: =EOMONTH(N6,12)
D8: Occupied SF | F8: =_xlfn.XLOOKUP(" Total Area",'Lease Audit '!$A:$A,'Lease Audit '!C:C) | G8: =_xlfn.XLOOKUP(" Total Area",'Lease Audit '!$A:$A,'Lease Audit '!D:D) | H8: =_xlfn.XLOOKUP(" Total Area",'Lease Audit '!$A:$A,'Lease Audit '!E:E) | I8: =_xlfn.XLOOKUP(" Total Area",'Lease Audit '!$A:$A,'Lease Audit '!F:F) | J8: =_xlfn.XLOOKUP(" Total Area",'Lease Audit '!$A:$A,'Lease Audit '!G:G) | K8: =_xlfn.XLOOKUP(" Total Area",'Lease Audit '!$A:$A,'Lease Audit '!H:H) | L8: =_xlfn.XLOOKUP(" Total Area",'Lease Audit '!$A:$A,'Lease Audit '!I:I) | M8: =_xlfn.XLOOKUP(" Total Area",'Lease Audit '!$A:$A,'Lease Audit '!J:J) | N8: =_xlfn.XLOOKUP(" Total Area",'Lease Audit '!$A:$A,'Lease Audit '!K:K) | O8: =_xlfn.XLOOKUP(" Total Area",'Lease Audit '!$A:$A,'Lease Audit '!L:L)
D9: Physical Occupancy | F9: =F8/'Rent Roll-Detailed'!$H$65 | G9: =G8/'Rent Roll-Detailed'!$H$65 | H9: =H8/'Rent Roll-Detailed'!$H$65 | I9: =I8/'Rent Roll-Detailed'!$H$65 | J9: =J8/'Rent Roll-Detailed'!$H$65 | K9: =K8/'Rent Roll-Detailed'!$H$65 | L9: =L8/'Rent Roll-Detailed'!$H$65 | M9: =M8/'Rent Roll-Detailed'!$H$65 | ... O9: =O8/'Rent Roll-Detailed'!$H$65
D10: Overall Economic Occupancy | F10: =(SUM(F17:F18,F20,F32)/F17) | G10: =(SUM(G17:G18,G20,G32)/G17) | H10: =(SUM(H17:H18,H20,H32)/H17) | I10: =(SUM(I17:I18,I20,I32)/I17) | J10: =(SUM(J17:J18,J20,J32)/J17) | K10: =(SUM(K17:K18,K20,K32)/K17) | L10: =(SUM(L17:L18,L20,L32)/L17) | M10: =(SUM(M17:M18,M20,M32)/M17) | ... O10: =(SUM(O17:O18,O20,O32)/O17)
D11: Wtd Avg. Market Rent
D12: Wtd. Avg. In Place Rent | Z12: This figure does not include any amount related to expense reimbursements. Only Scheduled Base Rent and Fixed/CPI Increases are included in this calculation, which is based on the weighted-average physical occupancy during each
D13: Lease SF Expiring (CY; Initial Term Only) | F13: ='Lease SF Exp Schedule'!I16 | G13: ='Lease SF Exp Schedule'!J16 | H13: ='Lease SF Exp Schedule'!K16 | I13: ='Lease SF Exp Schedule'!L16 | J13: ='Lease SF Exp Schedule'!M16 | K13: ='Lease SF Exp Schedule'!N16 | L13: ='Lease SF Exp Schedule'!O16 | M13: ='Lease SF Exp Schedule'!P16 | N13: ='Lease SF Exp Schedule'!Q16 | O13: ='Lease SF Exp Schedule'!Y16
D14: Lease SF Expiring (CY; Cumulative %) | F14: ='Lease SF Exp Schedule'!I19 | G14: ='Lease SF Exp Schedule'!J19 | H14: ='Lease SF Exp Schedule'!K19 | I14: ='Lease SF Exp Schedule'!L19 | J14: ='Lease SF Exp Schedule'!M19 | K14: ='Lease SF Exp Schedule'!N19 | L14: ='Lease SF Exp Schedule'!O19 | M14: ='Lease SF Exp Schedule'!P19 | N14: ='Lease SF Exp Schedule'!Q19 | O14: ='Lease SF Exp Schedule'!Y19
D16: Potential Gross Revenue
D17: Base Rental Revenue | F17: =SUMIFS('Cash flow'!C:C,'Cash flow'!$A:$A,Proforma!$D17) | G17: =SUMIFS('Cash flow'!D:D,'Cash flow'!$A:$A,Proforma!$D17) | H17: =SUMIFS('Cash flow'!E:E,'Cash flow'!$A:$A,Proforma!$D17) | I17: =SUMIFS('Cash flow'!F:F,'Cash flow'!$A:$A,Proforma!$D17) | J17: =SUMIFS('Cash flow'!G:G,'Cash flow'!$A:$A,Proforma!$D17) | K17: =SUMIFS('Cash flow'!H:H,'Cash flow'!$A:$A,Proforma!$D17) | L17: =SUMIFS('Cash flow'!I:I,'Cash flow'!$A:$A,Proforma!$D17) | M17: =SUMIFS('Cash flow'!J:J,'Cash flow'!$A:$A,Proforma!$D17) | N17: =SUMIFS('Cash flow'!K:K,'Cash flow'!$A:$A,Proforma!$D17) | O17: =SUMIFS('Cash flow'!L:L,'Cash flow'!$A:$A,Proforma!$D17)
D18: Base Rent Abatements | F18: =SUMIFS('Cash flow'!C:C,'Cash flow'!$A:$A,Proforma!$D18) | G18: =SUMIFS('Cash flow'!D:D,'Cash flow'!$A:$A,Proforma!$D18) | H18: =SUMIFS('Cash flow'!E:E,'Cash flow'!$A:$A,Proforma!$D18) | I18: =SUMIFS('Cash flow'!F:F,'Cash flow'!$A:$A,Proforma!$D18) | J18: =SUMIFS('Cash flow'!G:G,'Cash flow'!$A:$A,Proforma!$D18) | K18: =SUMIFS('Cash flow'!H:H,'Cash flow'!$A:$A,Proforma!$D18) | L18: =SUMIFS('Cash flow'!I:I,'Cash flow'!$A:$A,Proforma!$D18) | M18: =SUMIFS('Cash flow'!J:J,'Cash flow'!$A:$A,Proforma!$D18) | N18: =SUMIFS('Cash flow'!K:K,'Cash flow'!$A:$A,Proforma!$D18) | O18: =SUMIFS('Cash flow'!L:L,'Cash flow'!$A:$A,Proforma!$D18)
D19: Free Rent | F19: =SUMIFS('Cash flow'!C:C,'Cash flow'!$A:$A,Proforma!$D19) | G19: =SUMIFS('Cash flow'!D:D,'Cash flow'!$A:$A,Proforma!$D19) | H19: =SUMIFS('Cash flow'!E:E,'Cash flow'!$A:$A,Proforma!$D19) | I19: =SUMIFS('Cash flow'!F:F,'Cash flow'!$A:$A,Proforma!$D19) | J19: =SUMIFS('Cash flow'!G:G,'Cash flow'!$A:$A,Proforma!$D19) | K19: =SUMIFS('Cash flow'!H:H,'Cash flow'!$A:$A,Proforma!$D19) | L19: =SUMIFS('Cash flow'!I:I,'Cash flow'!$A:$A,Proforma!$D19) | M19: =SUMIFS('Cash flow'!J:J,'Cash flow'!$A:$A,Proforma!$D19) | N19: =SUMIFS('Cash flow'!K:K,'Cash flow'!$A:$A,Proforma!$D19) | O19: =SUMIFS('Cash flow'!L:L,'Cash flow'!$A:$A,Proforma!$D19)
D20: Absorption and Turnover Vacancy | F20: =SUMIFS('Cash flow'!C:C,'Cash flow'!$A:$A,Proforma!$D20) | G20: =SUMIFS('Cash flow'!D:D,'Cash flow'!$A:$A,Proforma!$D20) | H20: =SUMIFS('Cash flow'!E:E,'Cash flow'!$A:$A,Proforma!$D20) | I20: =SUMIFS('Cash flow'!F:F,'Cash flow'!$A:$A,Proforma!$D20) | J20: =SUMIFS('Cash flow'!G:G,'Cash flow'!$A:$A,Proforma!$D20) | K20: =SUMIFS('Cash flow'!H:H,'Cash flow'!$A:$A,Proforma!$D20) | L20: =SUMIFS('Cash flow'!I:I,'Cash flow'!$A:$A,Proforma!$D20) | M20: =SUMIFS('Cash flow'!J:J,'Cash flow'!$A:$A,Proforma!$D20) | N20: =SUMIFS('Cash flow'!K:K,'Cash flow'!$A:$A,Proforma!$D20) | O20: =SUMIFS('Cash flow'!L:L,'Cash flow'!$A:$A,Proforma!$D20)
D21: Total Scheduled Base Rent | F21: =SUM(F17:F20) | G21: =SUM(G17:G20) | H21: =SUM(H17:H20) | I21: =SUM(I17:I20) | J21: =SUM(J17:J20) | K21: =SUM(K17:K20) | L21: =SUM(L17:L20) | M21: =SUM(M17:M20) | ... O21: =SUM(O17:O20)
D22: CAM Recovery | F22: =SUMIFS('Cash flow'!C:C,'Cash flow'!$A:$A,Proforma!$D22) | G22: =SUMIFS('Cash flow'!D:D,'Cash flow'!$A:$A,Proforma!$D22) | H22: =SUMIFS('Cash flow'!E:E,'Cash flow'!$A:$A,Proforma!$D22) | I22: =SUMIFS('Cash flow'!F:F,'Cash flow'!$A:$A,Proforma!$D22) | J22: =SUMIFS('Cash flow'!G:G,'Cash flow'!$A:$A,Proforma!$D22) | K22: =SUMIFS('Cash flow'!H:H,'Cash flow'!$A:$A,Proforma!$D22) | L22: =SUMIFS('Cash flow'!I:I,'Cash flow'!$A:$A,Proforma!$D22) | M22: =SUMIFS('Cash flow'!J:J,'Cash flow'!$A:$A,Proforma!$D22) | N22: =SUMIFS('Cash flow'!K:K,'Cash flow'!$A:$A,Proforma!$D22) | O22: =SUMIFS('Cash flow'!L:L,'Cash flow'!$A:$A,Proforma!$D22)
D23: Realty Tax Recovery | F23: =SUMIFS('Cash flow'!C:C,'Cash flow'!$A:$A,Proforma!$D23) | G23: =SUMIFS('Cash flow'!D:D,'Cash flow'!$A:$A,Proforma!$D23) | H23: =SUMIFS('Cash flow'!E:E,'Cash flow'!$A:$A,Proforma!$D23) | I23: =SUMIFS('Cash flow'!F:F,'Cash flow'!$A:$A,Proforma!$D23) | J23: =SUMIFS('Cash flow'!G:G,'Cash flow'!$A:$A,Proforma!$D23) | K23: =SUMIFS('Cash flow'!H:H,'Cash flow'!$A:$A,Proforma!$D23) | L23: =SUMIFS('Cash flow'!I:I,'Cash flow'!$A:$A,Proforma!$D23) | M23: =SUMIFS('Cash flow'!J:J,'Cash flow'!$A:$A,Proforma!$D23) | N23: =SUMIFS('Cash flow'!K:K,'Cash flow'!$A:$A,Proforma!$D23) | O23: =SUMIFS('Cash flow'!L:L,'Cash flow'!$A:$A,Proforma!$D23)
D24: Insurance Recovery | F24: =SUMIFS('Cash flow'!C:C,'Cash flow'!$A:$A,Proforma!$D24) | G24: =SUMIFS('Cash flow'!D:D,'Cash flow'!$A:$A,Proforma!$D24) | H24: =SUMIFS('Cash flow'!E:E,'Cash flow'!$A:$A,Proforma!$D24) | I24: =SUMIFS('Cash flow'!F:F,'Cash flow'!$A:$A,Proforma!$D24) | J24: =SUMIFS('Cash flow'!G:G,'Cash flow'!$A:$A,Proforma!$D24) | K24: =SUMIFS('Cash flow'!H:H,'Cash flow'!$A:$A,Proforma!$D24) | L24: =SUMIFS('Cash flow'!I:I,'Cash flow'!$A:$A,Proforma!$D24) | M24: =SUMIFS('Cash flow'!J:J,'Cash flow'!$A:$A,Proforma!$D24) | N24: =SUMIFS('Cash flow'!K:K,'Cash flow'!$A:$A,Proforma!$D24) | O24: =SUMIFS('Cash flow'!L:L,'Cash flow'!$A:$A,Proforma!$D24)
D25: Total Expense Recoveries | F25: =SUMIFS('Cash flow'!C:C,'Cash flow'!$A:$A,Proforma!$D25) | G25: =SUMIFS('Cash flow'!D:D,'Cash flow'!$A:$A,Proforma!$D25) | H25: =SUMIFS('Cash flow'!E:E,'Cash flow'!$A:$A,Proforma!$D25) | I25: =SUMIFS('Cash flow'!F:F,'Cash flow'!$A:$A,Proforma!$D25) | J25: =SUMIFS('Cash flow'!G:G,'Cash flow'!$A:$A,Proforma!$D25) | K25: =SUMIFS('Cash flow'!H:H,'Cash flow'!$A:$A,Proforma!$D25) | L25: =SUMIFS('Cash flow'!I:I,'Cash flow'!$A:$A,Proforma!$D25) | M25: =SUMIFS('Cash flow'!J:J,'Cash flow'!$A:$A,Proforma!$D25) | N25: =SUMIFS('Cash flow'!K:K,'Cash flow'!$A:$A,Proforma!$D25) | O25: =SUMIFS('Cash flow'!L:L,'Cash flow'!$A:$A,Proforma!$D25)
D26: Total Expense Reimbursements | F26: =SUM(F22:F25) | G26: =SUM(G22:G25) | H26: =SUM(H22:H25) | I26: =SUM(I22:I25) | J26: =SUM(J22:J25) | K26: =SUM(K22:K25) | L26: =SUM(L22:L25) | M26: =SUM(M22:M25) | ... O26: =SUM(O22:O25)
D27: Percentage Rent | F27: =SUMIFS('Cash flow'!C:C,'Cash flow'!$A:$A,Proforma!$D27) | G27: =SUMIFS('Cash flow'!D:D,'Cash flow'!$A:$A,Proforma!$D27) | H27: =SUMIFS('Cash flow'!E:E,'Cash flow'!$A:$A,Proforma!$D27) | I27: =SUMIFS('Cash flow'!F:F,'Cash flow'!$A:$A,Proforma!$D27) | J27: =SUMIFS('Cash flow'!G:G,'Cash flow'!$A:$A,Proforma!$D27) | K27: =SUMIFS('Cash flow'!H:H,'Cash flow'!$A:$A,Proforma!$D27) | L27: =SUMIFS('Cash flow'!I:I,'Cash flow'!$A:$A,Proforma!$D27) | M27: =SUMIFS('Cash flow'!J:J,'Cash flow'!$A:$A,Proforma!$D27) | N27: =SUMIFS('Cash flow'!K:K,'Cash flow'!$A:$A,Proforma!$D27) | O27: =SUMIFS('Cash flow'!L:L,'Cash flow'!$A:$A,Proforma!$D27)
D28: Parking Revenue | F28: =SUMIFS('Cash flow'!C:C,'Cash flow'!$A:$A,Proforma!$D28) | G28: =SUMIFS('Cash flow'!D:D,'Cash flow'!$A:$A,Proforma!$D28) | H28: =SUMIFS('Cash flow'!E:E,'Cash flow'!$A:$A,Proforma!$D28) | I28: =SUMIFS('Cash flow'!F:F,'Cash flow'!$A:$A,Proforma!$D28) | J28: =SUMIFS('Cash flow'!G:G,'Cash flow'!$A:$A,Proforma!$D28) | K28: =SUMIFS('Cash flow'!H:H,'Cash flow'!$A:$A,Proforma!$D28) | L28: =SUMIFS('Cash flow'!I:I,'Cash flow'!$A:$A,Proforma!$D28) | M28: =SUMIFS('Cash flow'!J:J,'Cash flow'!$A:$A,Proforma!$D28) | N28: =SUMIFS('Cash flow'!K:K,'Cash flow'!$A:$A,Proforma!$D28) | O28: =SUMIFS('Cash flow'!L:L,'Cash flow'!$A:$A,Proforma!$D28)
D29: Storage | F29: =SUMIFS('Cash flow'!C:C,'Cash flow'!$A:$A,Proforma!$D29) | G29: =SUMIFS('Cash flow'!D:D,'Cash flow'!$A:$A,Proforma!$D29) | H29: =SUMIFS('Cash flow'!E:E,'Cash flow'!$A:$A,Proforma!$D29) | I29: =SUMIFS('Cash flow'!F:F,'Cash flow'!$A:$A,Proforma!$D29) | J29: =SUMIFS('Cash flow'!G:G,'Cash flow'!$A:$A,Proforma!$D29) | K29: =SUMIFS('Cash flow'!H:H,'Cash flow'!$A:$A,Proforma!$D29) | L29: =SUMIFS('Cash flow'!I:I,'Cash flow'!$A:$A,Proforma!$D29) | M29: =SUMIFS('Cash flow'!J:J,'Cash flow'!$A:$A,Proforma!$D29) | N29: =SUMIFS('Cash flow'!K:K,'Cash flow'!$A:$A,Proforma!$D29) | O29: =SUMIFS('Cash flow'!L:L,'Cash flow'!$A:$A,Proforma!$D29)
D30: Signage and Other Revenues | F30: =SUMIFS('Cash flow'!C:C,'Cash flow'!$A:$A,Proforma!$D30) | G30: =SUMIFS('Cash flow'!D:D,'Cash flow'!$A:$A,Proforma!$D30) | H30: =SUMIFS('Cash flow'!E:E,'Cash flow'!$A:$A,Proforma!$D30) | I30: =SUMIFS('Cash flow'!F:F,'Cash flow'!$A:$A,Proforma!$D30) | J30: =SUMIFS('Cash flow'!G:G,'Cash flow'!$A:$A,Proforma!$D30) | K30: =SUMIFS('Cash flow'!H:H,'Cash flow'!$A:$A,Proforma!$D30) | L30: =SUMIFS('Cash flow'!I:I,'Cash flow'!$A:$A,Proforma!$D30) | M30: =SUMIFS('Cash flow'!J:J,'Cash flow'!$A:$A,Proforma!$D30) | N30: =SUMIFS('Cash flow'!K:K,'Cash flow'!$A:$A,Proforma!$D30) | O30: =SUMIFS('Cash flow'!L:L,'Cash flow'!$A:$A,Proforma!$D30)
D31: Total Gross Revenue | F31: =F21+SUM(F26:F30) | G31: =G21+SUM(G26:G30) | H31: =H21+SUM(H26:H30) | I31: =I21+SUM(I26:I30) | J31: =J21+SUM(J26:J30) | K31: =K21+SUM(K26:K30) | L31: =L21+SUM(L26:L30) | M31: =M21+SUM(M26:M30) | ... O31: =O21+SUM(O26:O30)
D32: General Vacancy Loss | F32: =SUMIFS('Cash flow'!C:C,'Cash flow'!$A:$A,Proforma!$D32) | G32: =SUMIFS('Cash flow'!D:D,'Cash flow'!$A:$A,Proforma!$D32) | H32: =SUMIFS('Cash flow'!E:E,'Cash flow'!$A:$A,Proforma!$D32) | I32: =SUMIFS('Cash flow'!F:F,'Cash flow'!$A:$A,Proforma!$D32) | J32: =SUMIFS('Cash flow'!G:G,'Cash flow'!$A:$A,Proforma!$D32) | K32: =SUMIFS('Cash flow'!H:H,'Cash flow'!$A:$A,Proforma!$D32) | L32: =SUMIFS('Cash flow'!I:I,'Cash flow'!$A:$A,Proforma!$D32) | M32: =SUMIFS('Cash flow'!J:J,'Cash flow'!$A:$A,Proforma!$D32) | N32: =SUMIFS('Cash flow'!K:K,'Cash flow'!$A:$A,Proforma!$D32) | O32: =SUMIFS('Cash flow'!L:L,'Cash flow'!$A:$A,Proforma!$D32)
D33: Effective Gross Revenue | F33: =SUM(F31:F32) | G33: =SUM(G31:G32) | H33: =SUM(H31:H32) | I33: =SUM(I31:I32) | J33: =SUM(J31:J32) | K33: =SUM(K31:K32) | L33: =SUM(L31:L32) | M33: =SUM(M31:M32) | ... O33: =SUM(O31:O32)
D36: Expenses
D37: RE Taxes | F37: =SUMIFS('Cash flow'!C:C,'Cash flow'!$A:$A,Proforma!$D37) | G37: =SUMIFS('Cash flow'!D:D,'Cash flow'!$A:$A,Proforma!$D37) | H37: =SUMIFS('Cash flow'!E:E,'Cash flow'!$A:$A,Proforma!$D37) | I37: =SUMIFS('Cash flow'!F:F,'Cash flow'!$A:$A,Proforma!$D37) | J37: =SUMIFS('Cash flow'!G:G,'Cash flow'!$A:$A,Proforma!$D37) | K37: =SUMIFS('Cash flow'!H:H,'Cash flow'!$A:$A,Proforma!$D37) | L37: =SUMIFS('Cash flow'!I:I,'Cash flow'!$A:$A,Proforma!$D37) | M37: =SUMIFS('Cash flow'!J:J,'Cash flow'!$A:$A,Proforma!$D37) | N37: =SUMIFS('Cash flow'!K:K,'Cash flow'!$A:$A,Proforma!$D37) | O37: =SUMIFS('Cash flow'!L:L,'Cash flow'!$A:$A,Proforma!$D37)
D38: Insurance | F38: =SUMIFS('Cash flow'!C:C,'Cash flow'!$A:$A,Proforma!$D38) | G38: =SUMIFS('Cash flow'!D:D,'Cash flow'!$A:$A,Proforma!$D38) | H38: =SUMIFS('Cash flow'!E:E,'Cash flow'!$A:$A,Proforma!$D38) | I38: =SUMIFS('Cash flow'!F:F,'Cash flow'!$A:$A,Proforma!$D38) | J38: =SUMIFS('Cash flow'!G:G,'Cash flow'!$A:$A,Proforma!$D38) | K38: =SUMIFS('Cash flow'!H:H,'Cash flow'!$A:$A,Proforma!$D38) | L38: =SUMIFS('Cash flow'!I:I,'Cash flow'!$A:$A,Proforma!$D38) | M38: =SUMIFS('Cash flow'!J:J,'Cash flow'!$A:$A,Proforma!$D38) | N38: =SUMIFS('Cash flow'!K:K,'Cash flow'!$A:$A,Proforma!$D38) | O38: =SUMIFS('Cash flow'!L:L,'Cash flow'!$A:$A,Proforma!$D38)
D39: Other CAM | F39: =SUMIFS('Cash flow'!C:C,'Cash flow'!$A:$A,Proforma!$D39) | G39: =SUMIFS('Cash flow'!D:D,'Cash flow'!$A:$A,Proforma!$D39) | H39: =SUMIFS('Cash flow'!E:E,'Cash flow'!$A:$A,Proforma!$D39) | I39: =SUMIFS('Cash flow'!F:F,'Cash flow'!$A:$A,Proforma!$D39) | J39: =SUMIFS('Cash flow'!G:G,'Cash flow'!$A:$A,Proforma!$D39) | K39: =SUMIFS('Cash flow'!H:H,'Cash flow'!$A:$A,Proforma!$D39) | L39: =SUMIFS('Cash flow'!I:I,'Cash flow'!$A:$A,Proforma!$D39) | M39: =SUMIFS('Cash flow'!J:J,'Cash flow'!$A:$A,Proforma!$D39) | N39: =SUMIFS('Cash flow'!K:K,'Cash flow'!$A:$A,Proforma!$D39) | O39: =SUMIFS('Cash flow'!L:L,'Cash flow'!$A:$A,Proforma!$D39)
D40: Non-Recoverable Expenses | F40: =SUMIFS('Cash flow'!C:C,'Cash flow'!$A:$A,Proforma!$D40) | G40: =SUMIFS('Cash flow'!D:D,'Cash flow'!$A:$A,Proforma!$D40) | H40: =SUMIFS('Cash flow'!E:E,'Cash flow'!$A:$A,Proforma!$D40) | I40: =SUMIFS('Cash flow'!F:F,'Cash flow'!$A:$A,Proforma!$D40) | J40: =SUMIFS('Cash flow'!G:G,'Cash flow'!$A:$A,Proforma!$D40) | K40: =SUMIFS('Cash flow'!H:H,'Cash flow'!$A:$A,Proforma!$D40) | L40: =SUMIFS('Cash flow'!I:I,'Cash flow'!$A:$A,Proforma!$D40) | M40: =SUMIFS('Cash flow'!J:J,'Cash flow'!$A:$A,Proforma!$D40) | N40: =SUMIFS('Cash flow'!K:K,'Cash flow'!$A:$A,Proforma!$D40) | O40: =SUMIFS('Cash flow'!L:L,'Cash flow'!$A:$A,Proforma!$D40)
D41: Total Operating Expenses | F41: =SUM(F37:F40) | G41: =SUM(G37:G40) | H41: =SUM(H37:H40) | I41: =SUM(I37:I40) | J41: =SUM(J37:J40) | K41: =SUM(K37:K40) | L41: =SUM(L37:L40) | M41: =SUM(M37:M40) | ... O41: =SUM(O37:O40)
D42: % Increase/(Decrease) | G42: =G41/F41-1 | H42: =H41/G41-1 | I42: =I41/H41-1 | J42: =J41/I41-1 | K42: =K41/J41-1 | L42: =L41/K41-1 | M42: =M41/L41-1 | N42: =N41/M41-1 | O42: =O41/N41-1
D44: Net Operating Income | F44: =F33-F41 | G44: =G33-G41 | H44: =H33-H41 | I44: =I33-I41 | J44: =J33-J41 | K44: =K33-K41 | L44: =L33-L41 | M44: =M33-M41 | ... O44: =O33-O41
D47: Leasing Costs:
D48: Tenant Improvements | F48: =SUMIFS('Cash flow'!C:C,'Cash flow'!$A:$A,Proforma!$D48) | G48: =SUMIFS('Cash flow'!D:D,'Cash flow'!$A:$A,Proforma!$D48) | H48: =SUMIFS('Cash flow'!E:E,'Cash flow'!$A:$A,Proforma!$D48) | I48: =SUMIFS('Cash flow'!F:F,'Cash flow'!$A:$A,Proforma!$D48) | J48: =SUMIFS('Cash flow'!G:G,'Cash flow'!$A:$A,Proforma!$D48) | K48: =SUMIFS('Cash flow'!H:H,'Cash flow'!$A:$A,Proforma!$D48) | L48: =SUMIFS('Cash flow'!I:I,'Cash flow'!$A:$A,Proforma!$D48) | M48: =SUMIFS('Cash flow'!J:J,'Cash flow'!$A:$A,Proforma!$D48) | N48: =SUMIFS('Cash flow'!K:K,'Cash flow'!$A:$A,Proforma!$D48) | O48: =SUMIFS('Cash flow'!L:L,'Cash flow'!$A:$A,Proforma!$D48)
D49: Leasing Commissions | F49: =SUMIFS('Cash flow'!C:C,'Cash flow'!$A:$A,Proforma!$D49) | G49: =SUMIFS('Cash flow'!D:D,'Cash flow'!$A:$A,Proforma!$D49) | H49: =SUMIFS('Cash flow'!E:E,'Cash flow'!$A:$A,Proforma!$D49) | I49: =SUMIFS('Cash flow'!F:F,'Cash flow'!$A:$A,Proforma!$D49) | J49: =SUMIFS('Cash flow'!G:G,'Cash flow'!$A:$A,Proforma!$D49) | K49: =SUMIFS('Cash flow'!H:H,'Cash flow'!$A:$A,Proforma!$D49) | L49: =SUMIFS('Cash flow'!I:I,'Cash flow'!$A:$A,Proforma!$D49) | M49: =SUMIFS('Cash flow'!J:J,'Cash flow'!$A:$A,Proforma!$D49) | N49: =SUMIFS('Cash flow'!K:K,'Cash flow'!$A:$A,Proforma!$D49) | O49: =SUMIFS('Cash flow'!L:L,'Cash flow'!$A:$A,Proforma!$D49)
D50: Total Leasing Cost | F50: =SUM(F48:F49) | G50: =SUM(G48:G49) | H50: =SUM(H48:H49) | I50: =SUM(I48:I49) | J50: =SUM(J48:J49) | K50: =SUM(K48:K49) | L50: =SUM(L48:L49) | M50: =SUM(M48:M49) | ... O50: =SUM(O48:O49)
D52: Capital Expenditures:
D53: Capex Reserve | F53: =SUMIFS('Cash flow'!C:C,'Cash flow'!$A:$A,Proforma!$D53) | G53: =SUMIFS('Cash flow'!D:D,'Cash flow'!$A:$A,Proforma!$D53) | H53: =SUMIFS('Cash flow'!E:E,'Cash flow'!$A:$A,Proforma!$D53) | I53: =SUMIFS('Cash flow'!F:F,'Cash flow'!$A:$A,Proforma!$D53) | J53: =SUMIFS('Cash flow'!G:G,'Cash flow'!$A:$A,Proforma!$D53) | K53: =SUMIFS('Cash flow'!H:H,'Cash flow'!$A:$A,Proforma!$D53) | L53: =SUMIFS('Cash flow'!I:I,'Cash flow'!$A:$A,Proforma!$D53) | M53: =SUMIFS('Cash flow'!J:J,'Cash flow'!$A:$A,Proforma!$D53) | N53: =SUMIFS('Cash flow'!K:K,'Cash flow'!$A:$A,Proforma!$D53) | O53: =SUMIFS('Cash flow'!L:L,'Cash flow'!$A:$A,Proforma!$D53)
D54: Capital Improvements | F54: =SUMIFS('Cash flow'!C:C,'Cash flow'!$A:$A,Proforma!$D54) | G54: =SUMIFS('Cash flow'!D:D,'Cash flow'!$A:$A,Proforma!$D54) | H54: =SUMIFS('Cash flow'!E:E,'Cash flow'!$A:$A,Proforma!$D54) | I54: =SUMIFS('Cash flow'!F:F,'Cash flow'!$A:$A,Proforma!$D54) | J54: =SUMIFS('Cash flow'!G:G,'Cash flow'!$A:$A,Proforma!$D54) | K54: =SUMIFS('Cash flow'!H:H,'Cash flow'!$A:$A,Proforma!$D54) | L54: =SUMIFS('Cash flow'!I:I,'Cash flow'!$A:$A,Proforma!$D54) | M54: =SUMIFS('Cash flow'!J:J,'Cash flow'!$A:$A,Proforma!$D54) | N54: =SUMIFS('Cash flow'!K:K,'Cash flow'!$A:$A,Proforma!$D54) | O54: =SUMIFS('Cash flow'!L:L,'Cash flow'!$A:$A,Proforma!$D54)
D55: Total Capital Expenditures | F55: =SUM(F53:F54) | G55: =SUM(G53:G54) | H55: =SUM(H53:H54) | I55: =SUM(I53:I54) | J55: =SUM(J53:J54) | K55: =SUM(K53:K54) | L55: =SUM(L53:L54) | M55: =SUM(M53:M54) | ... O55: =SUM(O53:O54)
D57: Total Leasing & Capital Costs | F57: =F50+F55 | G57: =G50+G55 | H57: =H50+H55 | I57: =I50+I55 | J57: =J50+J55 | K57: =K50+K55 | L57: =L50+L55 | M57: =M50+M55 | ... O57: =O50+O55
D60: Net Income | F60: =F44-F57 | G60: =G44-G57 | H60: =H44-H57 | I60: =I44-I57 | J60: =J44-J57 | K60: =K44-K57 | L60: =L44-L57 | M60: =M44-M57 | ... O60: =O44-O57
D63: Debt Service:
D64: Interest | F64: =INDEX('Loan Calculation'!$M$16:$M$375,MATCH(Proforma!F$5,'Loan Calculation'!$B$16:$B$375,0)) | G64: =INDEX('Loan Calculation'!$M$16:$M$375,MATCH(Proforma!G$5,'Loan Calculation'!$B$16:$B$375,0)) | H64: =INDEX('Loan Calculation'!$M$16:$M$375,MATCH(Proforma!H$5,'Loan Calculation'!$B$16:$B$375,0)) | I64: =INDEX('Loan Calculation'!$M$16:$M$375,MATCH(Proforma!I$5,'Loan Calculation'!$B$16:$B$375,0)) | J64: =INDEX('Loan Calculation'!$M$16:$M$375,MATCH(Proforma!J$5,'Loan Calculation'!$B$16:$B$375,0)) | K64: =INDEX('Loan Calculation'!$M$16:$M$375,MATCH(Proforma!K$5,'Loan Calculation'!$B$16:$B$375,0)) | L64: =INDEX('Loan Calculation'!$M$16:$M$375,MATCH(Proforma!L$5,'Loan Calculation'!$B$16:$B$375,0)) | M64: =INDEX('Loan Calculation'!$M$16:$M$375,MATCH(Proforma!M$5,'Loan Calculation'!$B$16:$B$375,0)) | ... O64: =INDEX('Loan Calculation'!$M$16:$M$375,MATCH(Proforma!O$5,'Loan Calculation'!$B$16:$B$375,0))
D65: Principal | F65: =INDEX('Loan Calculation'!$L$16:$L$375,MATCH(Proforma!F$5,'Loan Calculation'!$B$16:$B$375,0)) | G65: =INDEX('Loan Calculation'!$L$16:$L$375,MATCH(Proforma!G$5,'Loan Calculation'!$B$16:$B$375,0)) | H65: =INDEX('Loan Calculation'!$L$16:$L$375,MATCH(Proforma!H$5,'Loan Calculation'!$B$16:$B$375,0)) | I65: =INDEX('Loan Calculation'!$L$16:$L$375,MATCH(Proforma!I$5,'Loan Calculation'!$B$16:$B$375,0)) | J65: =INDEX('Loan Calculation'!$L$16:$L$375,MATCH(Proforma!J$5,'Loan Calculation'!$B$16:$B$375,0)) | K65: =INDEX('Loan Calculation'!$L$16:$L$375,MATCH(Proforma!K$5,'Loan Calculation'!$B$16:$B$375,0)) | L65: =INDEX('Loan Calculation'!$L$16:$L$375,MATCH(Proforma!L$5,'Loan Calculation'!$B$16:$B$375,0)) | M65: =INDEX('Loan Calculation'!$L$16:$L$375,MATCH(Proforma!M$5,'Loan Calculation'!$B$16:$B$375,0)) | ... O65: =INDEX('Loan Calculation'!$L$16:$L$375,MATCH(Proforma!O$5,'Loan Calculation'!$B$16:$B$375,0))
D66: Total Debt Service | F66: =SUM(F64:F65) | G66: =SUM(G64:G65) | H66: =SUM(H64:H65) | I66: =SUM(I64:I65) | J66: =SUM(J64:J65) | K66: =SUM(K64:K65) | L66: =SUM(L64:L65) | M66: =SUM(M64:M65) | ... O66: =SUM(O64:O65)
D68: Cash Flow After Debt Service | F68: =F60-F66 | G68: =G60-G66 | H68: =H60-H66 | I68: =I60-I66 | J68: =J60-J66 | K68: =K60-K66 | L68: =L60-L66 | M68: =M60-M66 | ... O68: =O60-O66
F70: =ROUND(F44,-2)=ROUND(SUMIFS('Cash flow'!C:C,'Cash flow'!$A:$A,"Net Operating Income"),-2) | G70: =ROUND(G44,-2)=ROUND(SUMIFS('Cash flow'!D:D,'Cash flow'!$A:$A,"Net Operating Income"),-2) | H70: =ROUND(H44,-3)=ROUND(SUMIFS('Cash flow'!E:E,'Cash flow'!$A:$A,"Net Operating Income"),-3) | I70: =ROUND(I44,-2)=ROUND(SUMIFS('Cash flow'!F:F,'Cash flow'!$A:$A,"Net Operating Income"),-2) | J70: =ROUND(J44,-2)=ROUND(SUMIFS('Cash flow'!G:G,'Cash flow'!$A:$A,"Net Operating Income"),-2) | K70: =ROUND(K44,-2)=ROUND(SUMIFS('Cash flow'!H:H,'Cash flow'!$A:$A,"Net Operating Income"),-2) | L70: =ROUND(L44,-2)=ROUND(SUMIFS('Cash flow'!I:I,'Cash flow'!$A:$A,"Net Operating Income"),-2) | M70: =ROUND(M44,-2)=ROUND(SUMIFS('Cash flow'!J:J,'Cash flow'!$A:$A,"Net Operating Income"),-2) | N70: =ROUND(N44,-2)=ROUND(SUMIFS('Cash flow'!K:K,'Cash flow'!$A:$A,"Net Operating Income"),-2) | O70: =ROUND(O44,-2)=ROUND(SUMIFS('Cash flow'!L:L,'Cash flow'!$A:$A,"Net Operating Income"),-2)
F71: =ROUND(F60,-3)=ROUND(SUMIFS('Cash flow'!C:C,'Cash flow'!$A:$A,"Net Income"),-3) | G71: =ROUND(G60,-2)=ROUND(SUMIFS('Cash flow'!D:D,'Cash flow'!$A:$A,"Net Income"),-2) | H71: =ROUND(H60,-2)=ROUND(SUMIFS('Cash flow'!E:E,'Cash flow'!$A:$A,"Net Income"),-2) | I71: =ROUND(I60,-2)=ROUND(SUMIFS('Cash flow'!F:F,'Cash flow'!$A:$A,"Net Income"),-2) | J71: =ROUND(J60,-2)=ROUND(SUMIFS('Cash flow'!G:G,'Cash flow'!$A:$A,"Net Income"),-2) | K71: =ROUND(K60,-2)=ROUND(SUMIFS('Cash flow'!H:H,'Cash flow'!$A:$A,"Net Income"),-2) | L71: =ROUND(L60,-2)=ROUND(SUMIFS('Cash flow'!I:I,'Cash flow'!$A:$A,"Net Income"),-2) | M71: =ROUND(M60,-2)=ROUND(SUMIFS('Cash flow'!J:J,'Cash flow'!$A:$A,"Net Income"),-2) | N71: =ROUND(N60,-2)=ROUND(SUMIFS('Cash flow'!K:K,'Cash flow'!$A:$A,"Net Income"),-2) | O71: =ROUND(O60,-2)=ROUND(SUMIFS('Cash flow'!L:L,'Cash flow'!$A:$A,"Net Income"),-2)
F72: =ROUND(F68,-2)=ROUND('Exec Summ'!G52,-2) | G72: =ROUND(G68,-2)=ROUND('Exec Summ'!H52,-2) | H72: =ROUND(H68,-2)=ROUND('Exec Summ'!I52,-2) | I72: =ROUND(I68,-2)=ROUND('Exec Summ'!J52,-2) | J72: =ROUND(J68,-2)=ROUND('Exec Summ'!K52,-2) | K72: =ROUND(K68,-2)=ROUND('Exec Summ'!L52,-2) | L72: =ROUND(L68,-3)=ROUND('Exec Summ'!M52,-3) | M72: =ROUND(M68,-2)=ROUND('Exec Summ'!N52,-2) | N72: =ROUND(N68,-2)=ROUND('Exec Summ'!O52,-2) | O72: =ROUND(O68,-3)=ROUND('Exec Summ'!P52,-3)

Sheet Valuation
E2: 1687
C3: VALUATION SUMMARY | H3: =Global!$G$7 | J3: ='Rent Roll-Detailed'!$H$65
C5: Direct Capitalization Valuation
E7: Conservative | F7: Average | G7: Aggressive
D9: Net Operating Income (Year 1 / YE Sep-2027) | E9: =Proforma!$F$44 | F9: =Proforma!$F$44 | G9: =Proforma!$F$44 | J9: Increments:
D10: Cap Rate | E10: 0.0975 | F10: =E10-$J$10 | G10: =F10-$J$10 | J10: 0.005
D11: Implied Valuation | E11: =ROUND(E9/E10,-5) | F11: =ROUND(F9/F10,-4) | G11: =ROUND(G9/G10,-4)
D12: Implied Valuation PSF | E12: =E11/$J$3 | F12: =F11/$J$3 | G12: =G11/$J$3
C14: Summary of Sales Comparables
E16: Low | F16: Average | G16: High
D17: Price PSF | E17: n/a | F17: n/a | G17: n/a
D18: Cap Rate | E18: n/a | F18: n/a | G18: n/a
C21: DCF Valuation
E23: Conservative | F23: Average | G23: Aggressive
D24: Purchase Price | E24: ='Exec Summ'!G21 | F24: ='Exec Summ'!H21 | G24: ='Exec Summ'!I21
D25: Per Square Foot | E25: ='Exec Summ'!G22 | F25: ='Exec Summ'!H22 | G25: ='Exec Summ'!I22
D26: Unlevered IRR (5-Year Hold)* | E26: ='Exec Summ'!G32 | F26: ='Exec Summ'!H32 | G26: ='Exec Summ'!I32
D27: Levered IRR (5-Year Hold)* | E27: ='Exec Summ'!G40 | F27: ='Exec Summ'!H40 | G27: ='Exec Summ'!I40
D28: Average Cash-on-Cash* | E28: =AVERAGE('Sensitivity-Low'!E42:I42) | F28: =AVERAGE('Return Metrics'!H42:L42) | G28: =AVERAGE('Sensitivity-High'!E42:I42)
D29: Cap Rates:
D30: 2026 Budget | E30: ='P&Ls_Con'!$I$37/E24 | F30: ='P&Ls_Con'!$I$37/F24 | G30: ='P&Ls_Con'!$I$37/G24
D31: In-Place (Month 1 Annualized) | E31: ='Exec Summ'!G25 | F31: ='Exec Summ'!H25 | G31: ='Exec Summ'!I25
D32: Year 1 (YE Sep-2027) | E32: ='P&Ls_Con'!$V$37/Valuation!E$24 | F32: ='P&Ls_Con'!$V$37/Valuation!F$24 | G32: ='P&Ls_Con'!$V$37/Valuation!G$24
D33: Stabilized (Year 3) | E33: =Proforma!$H$44/Valuation!E24 | F33: =Proforma!$H$44/Valuation!F24 | G33: =Proforma!$H$44/Valuation!G24
D35: ="*Includes "&TEXT('Exec Summ'!$F$8,"0.0%")&" in closing/acq. costs; assumes loan @ "&TEXT('Exec Summ'!$F$13,"0%")&" LTV, "&'Exec Summ'!$F$16/12&" year-am, "&TEXT('Exec Summ'!$F$17,"0.00%")&" rate, "&'Exec Summ'!$F$18/12&" years IO."

Sheet Sheet1
C4: Water | H4: Pollo Campero
C5: Sewer | H5: Colortyme
C6: Management Fees | E6: Management Fees | H6: VA- 589 Atwells - Eagle 1 - Former VA Office - Vacant
C7: Admin - Office Supplies | E7: Admin - Office Supplies | H7: VA- 623 Atwells - Eagle 2 - Neuro/Eye Clinics
C8: Admin - Postage | E8: Admin - Postage | H8: VA - 623 Atwells - Eagle5 - Audiology
C9: Admin - Travel - Mileage/Tolls | E9: Admin - Travel - Mileage/Tolls | H9: Vacant - 623 Atwells
C10: Admin - Telephone - Wireless | E10: Admin - Telephone - Wireless | H10: Dunkin Donuts
C11: Admin - Office Internet Service | E11: Admin - Office Internet Service | H11: Subway
C12: Admin - Food & Beverages | E12: Admin - Food & Beverages | H12: MadRag
C13: Admin - Miscellaneous | E13: Admin - Miscellaneous | H13: Vacant - 579 Atwells
C14: Administrative Payroll | E14: Administrative Payroll | H14: H&R Block
C15: Administrative Bonuses | E15: Administrative Bonuses | H15: T-Nails
C16: Admin - Miscellaneous | E16: Admin - Miscellaneous | H16: Vasillios Pizza
C17: Uniforms | E17: Uniforms | H17: Vacant - 85 Eagle - C&W Management Office
... C31: Safety & Security - R&M | E31: Parking/Garage - R&M | H31: Current C&W Management Office - NOW WRWC
C32: R&M - Electrical - Bulbs & Ballasts | E32: Repairs & Maintenance Expense
C33: R&M - Electrical | E33: Maintenance Payroll
C34: R&M - Electrical - Supplies | E34: Maintenance Bonuses
C35: R&M - Plumbing | E35: Safety & Security - R&M
C36: R&M - Misc Repairs - Exterior | E36: R&M - Electrical - Bulbs & Ballasts
C37: R&M - Painting/Wallpaper | E37: R&M - Electrical
C38: R&M - Supplies - Maintenance | E38: R&M - Electrical - Supplies | H38: Pollo Campero Insurance
C39: R&M - Roof Repair | E39: R&M - Plumbing | H39: Pollo Campero Real Estate Taxes
C40: R&M - Exterminating | E40: R&M - Misc Repairs - Exterior | H40: Pollo Campero CAM
E41: R&M - Painting/Wallpaper | H41: Colortyme Insurance
E42: R&M - Supplies - Maintenance | H42: Colortyme Real Estate Taxes
E43: R&M - Roof Repair | H43: Colortyme CAM
E44: R&M - Exterminating | H44: Dunkin Donuts Insurance
H45: Dunkin Donuts Real Estate Taxes
H46: Dunkin Donuts CAM
H47: Subway Insurance
E48: Seasonal Planting | H48: MadRag Insurance
E49: Tree Service | H49: MadRag Real Estate Taxes
E50: Landscape - Irrigation Repairs | H50: MadRag CAM
E51: R&M - Plumbing - Supplies | H51: H&R Block Insurance
E52: R&M - Signage | H52: H&R Block Real Estate Taxes
H53: H&R Block CAM
H54: T-Nails Insurance
H55: T-Nails Real Estate Taxes
H56: T-Nails CAM
H57: Rainbow Insurance
H58: Rainbow Real Estate Taxes
H59: Rainbow CAM
H60: Jako Insurance
H61: Jako Real Estate Taxes
H62: Jako CAM
H63: Coast Guard Insurance
H64: Coast Guard Real Estate Taxes
... H194: R&M - Signage

Sheet Sheet2
H7: REVENUE | K7: Account | M7: Account | P7: REVENUE
H8: Rent | K8: REVENUE | M8: REVENUE | P8: RENTAL INCOME
H9: Expense Reimbursements | K9: RENTAL INCOME | M9: RENTAL INCOME | P9: Base Rent
H10: Other Revenue | K10: Base Rent | M10: Base Rent | P10: Less: Concessions
H11: TOTAL REVENUE | K11: Less: Concessions | M11: Less: Concessions | P11: Plus: Prepaid Rent
K12: Plus: Prepaid Rent | M12: Plus: Prepaid Rent | P12: NET RENTAL INCOME
H13: OPERATING EXPENSES | K13: NET RENTAL INCOME | M13: NET RENTAL INCOME | P13: EXPENSE REIMBURSEMENT
H14: Contracts | K14: EXPENSE REIMBURSEMENT | M14: EXPENSE REIMBURSEMENT | P14: Est. NNN Reimbursements
H15: Repairs & Maintenance | K15: Est. NNN Reimbursements | M15: Est. NNN Reimbursements | P15: Est. Electricity Reimb.
H16: Electricity | K16: Est. Electricity Reimb. | M16: Est. Electricity Reimb. | P16: Prior Year Reconciliation
H17: Water/Other Utilities | K17: Prior Year Reconciliation | M17: Prior Year Reconciliation | P17: TOTAL EXPENSE REIMB.
H18: Administrative | K18: TOTAL EXPENSE REIMB. | M18: TOTAL EXPENSE REIMB. | P18: OTHER INCOME
H19: Insurance | K19: OTHER INCOME | M19: OTHER INCOME | P19: Parking Revenue
H20: Property Taxes | K20: Parking Revenue | M20: Parking Revenue | P20: Miscellaneous Income
K21: Miscellaneous Income | M21: Miscellaneous Income | P21: TOTAL OTHER INCOME
K22: TOTAL OTHER INCOME | M22: TOTAL OTHER INCOME | P22: TOTAL REVENUE
K23: TOTAL REVENUE | M23: TOTAL REVENUE
P24: OPERATING EXPENSES
K25: OPERATING EXPENSES | M25: OPERATING EXPENSES | P25: RECOVERABLE EXPENSES
K26: RECOVERABLE EXPENSES | M26: RECOVERABLE EXPENSES | P26: CONTRACTS
K27: CONTRACTS | M27: CONTRACTS | P27: Contract - Janitorial
K28: Contract - Janitorial | M28: Contract - Janitorial | P28: Contract - Janitorial Supplies
K29: Contract - Janitorial Supplies | M29: Contract - Janitorial Supplies | P29: Contract - Day Porter
K30: Contract - Day Porter | M30: Contract - Day Porter | P30: Contract - Sanitization
K31: Contract - Sanitization | M31: Contract - Sanitization | P31: Contract - HVAC
K32: Contract - HVAC | M32: Contract - HVAC | P32: Contract - Elevator
K33: Contract - Elevator | M33: Contract - Elevator | P33: Contract - Exterior Landscaping
K34: Contract - Exterior Landscaping | M34: Contract - Exterior Landscaping | P34: Contract - Interior Landscape
K35: Contract - Interior Landscape | M35: Contract - Interior Landscape | P35: Contract - Pest Control
K36: Contract - Pest Control | M36: Contract - Pest Control | P36: Contract - Mgmt Fees
... K86: TOTAL OPERATING EXPENSES | M86: TOTAL OPERATING EXPENSES | P86: TOTAL OPERATING INCOME
K87: TOTAL OPERATING INCOME | M87: TOTAL OPERATING INCOME
P88: NON-RECOVERABLE EXPENSES
K89: NON-RECOVERABLE EXPENSES | M89: NON-RECOVERABLE EXPENSES | P89: Non Rec - Marketing
K90: Non Rec - Marketing | M90: Non Rec - Marketing | P90: Non Rec - Architectural
K91: Non Rec - Architectural | M91: Non Rec - Architectural | P91: Non Rec - Tenant Improvements
K92: Non Rec - Tenant Improvements | M92: Non Rec - Tenant Improvements | P92: Non Rec - Professional Fees
K93: Non Rec - Professional Fees | M93: Non Rec - Professional Fees | P93: Non Rec - Asset Management Fee
K94: Non Rec - Asset Management Fee | M94: Non Rec - Asset Management Fee | P94: Non Rec - Prior Year Opex
K95: Non Rec - Prior Year Opex | M95: Non Rec - Prior Year Opex | P95: Non Rec - Leasing Commissions
K96: Non Rec - Leasing Commissions | M96: Non Rec - Leasing Commissions | P96: Non Rec - Owner Travel
K97: Non Rec - Owner Travel | M97: Non Rec - Owner Travel | P97: Non Rec - Tenant Reimbursement
K98: Non Rec - Tenant Reimbursement | M98: Non Rec - Tenant Reimbursement | P98: Non Rec - Other
K99: Non Rec - Other | M99: Non Rec - Other | P99: Non Rec - Purchase/Refinance Exp
K100: Non Rec - Purchase/Refinance Exp | M100: Non Rec - Purchase/Refinance Exp | P100: TOTAL NON-RECOVERABLE
K101: TOTAL NON-RECOVERABLE | M101: TOTAL NON-RECOVERABLE
P102: DEBT SERVICE
K103: DEBT SERVICE | M103: DEBT SERVICE | P103: Mortgage Interest
K104: Mortgage Interest | M104: Mortgage Interest | P104: TOTAL DEBT SERVICE
K105: TOTAL DEBT SERVICE | M105: TOTAL DEBT SERVICE
P106: NET INCOME
K107: NET INCOME | M107: NET INCOME

Sheet P&Ls_Detailed
A1: 1603 RIDGESIDE DRIVE
C2: DETAILED INCOME STATEMENT | AP2: =Global!$G$7 | AR2: ='Rent Roll-Detailed'!$H$65
D4: Category | E4: Account | W4: 2025 Actual | X4: 2024 Actual | AO4: Seller Pro Forma
D5: REVENUE
D6: Rental Income | E6: Rental Income | W6: =SUMIFS('2025 P&L (Jan-Dec)'!$B:$B,'2025 P&L (Jan-Dec)'!$A:$A,'P&Ls_Detailed'!$E6) | X6: =SUMIFS('2024 P&L (Jan-Dec)'!$B:$B,'2024 P&L (Jan-Dec)'!$A:$A,'P&Ls_Detailed'!$E6) | AO6: =SUMIFS('Income & Expenses (Seller)'!$B:$B,'Income & Expenses (Seller)'!$A:$A,'P&Ls_Detailed'!$E6)
D7: EXPENSES
D8: Bank Service Charges | E8: Bank Service Charges | W8: =SUMIFS('2025 P&L (Jan-Dec)'!$B:$B,'2025 P&L (Jan-Dec)'!$A:$A,'P&Ls_Detailed'!$E8) | X8: =SUMIFS('2024 P&L (Jan-Dec)'!$B:$B,'2024 P&L (Jan-Dec)'!$A:$A,'P&Ls_Detailed'!$E8) | AO8: =SUMIFS('Income & Expenses (Seller)'!$B:$B,'Income & Expenses (Seller)'!$A:$A,'P&Ls_Detailed'!$E8)
D9: Depreciation Expense | E9: Depreciation Expense | W9: =SUMIFS('2025 P&L (Jan-Dec)'!$B:$B,'2025 P&L (Jan-Dec)'!$A:$A,'P&Ls_Detailed'!$E9) | X9: =SUMIFS('2024 P&L (Jan-Dec)'!$B:$B,'2024 P&L (Jan-Dec)'!$A:$A,'P&Ls_Detailed'!$E9) | AO9: =SUMIFS('Income & Expenses (Seller)'!$B:$B,'Income & Expenses (Seller)'!$A:$A,'P&Ls_Detailed'!$E9)
D10: Donations | E10: Donations | W10: =SUMIFS('2025 P&L (Jan-Dec)'!$B:$B,'2025 P&L (Jan-Dec)'!$A:$A,'P&Ls_Detailed'!$E10) | X10: =SUMIFS('2024 P&L (Jan-Dec)'!$B:$B,'2024 P&L (Jan-Dec)'!$A:$A,'P&Ls_Detailed'!$E10) | AO10: =SUMIFS('Income & Expenses (Seller)'!$B:$B,'Income & Expenses (Seller)'!$A:$A,'P&Ls_Detailed'!$E10)
D11: Insurance Expense | E11: Insurance Expense | W11: =SUMIFS('2025 P&L (Jan-Dec)'!$B:$B,'2025 P&L (Jan-Dec)'!$A:$A,'P&Ls_Detailed'!$E11) | X11: =SUMIFS('2024 P&L (Jan-Dec)'!$B:$B,'2024 P&L (Jan-Dec)'!$A:$A,'P&Ls_Detailed'!$E11) | AO11: =SUMIFS('Income & Expenses (Seller)'!$B:$B,'Income & Expenses (Seller)'!$A:$A,'P&Ls_Detailed'!$E11)
D12: Management Fee | E12: Management Fee | W12: =SUMIFS('2025 P&L (Jan-Dec)'!$B:$B,'2025 P&L (Jan-Dec)'!$A:$A,'P&Ls_Detailed'!$E12) | X12: =SUMIFS('2024 P&L (Jan-Dec)'!$B:$B,'2024 P&L (Jan-Dec)'!$A:$A,'P&Ls_Detailed'!$E12) | AO12: =SUMIFS('Income & Expenses (Seller)'!$B:$B,'Income & Expenses (Seller)'!$A:$A,'P&Ls_Detailed'!$E12)
D13: Professional Fees | E13: Accounting | W13: =SUMIFS('2025 P&L (Jan-Dec)'!$B:$B,'2025 P&L (Jan-Dec)'!$A:$A,'P&Ls_Detailed'!$E13) | X13: =SUMIFS('2024 P&L (Jan-Dec)'!$B:$B,'2024 P&L (Jan-Dec)'!$A:$A,'P&Ls_Detailed'!$E13) | AO13: =SUMIFS('Income & Expenses (Seller)'!$B:$B,'Income & Expenses (Seller)'!$A:$A,'P&Ls_Detailed'!$E13)
D14: Professional Fees | E14: Realtor Lease Fees | W14: =SUMIFS('2025 P&L (Jan-Dec)'!$B:$B,'2025 P&L (Jan-Dec)'!$A:$A,'P&Ls_Detailed'!$E14) | X14: =SUMIFS('2024 P&L (Jan-Dec)'!$B:$B,'2024 P&L (Jan-Dec)'!$A:$A,'P&Ls_Detailed'!$E14) | AO14: =SUMIFS('Income & Expenses (Seller)'!$B:$B,'Income & Expenses (Seller)'!$A:$A,'P&Ls_Detailed'!$E14)
D15: Property Maintenance | E15: Property Maintenance | W15: =SUMIFS('2025 P&L (Jan-Dec)'!$B:$B,'2025 P&L (Jan-Dec)'!$A:$A,'P&Ls_Detailed'!$E15) | X15: =SUMIFS('2024 P&L (Jan-Dec)'!$B:$B,'2024 P&L (Jan-Dec)'!$A:$A,'P&Ls_Detailed'!$E15) | AO15: =SUMIFS('Income & Expenses (Seller)'!$B:$B,'Income & Expenses (Seller)'!$A:$A,'P&Ls_Detailed'!$E15)
D16: Repairs and Maintenance | E16: Repairs and Maintenance | W16: =SUMIFS('2025 P&L (Jan-Dec)'!$B:$B,'2025 P&L (Jan-Dec)'!$A:$A,'P&Ls_Detailed'!$E16) | X16: =SUMIFS('2024 P&L (Jan-Dec)'!$B:$B,'2024 P&L (Jan-Dec)'!$A:$A,'P&Ls_Detailed'!$E16) | AO16: =SUMIFS('Income & Expenses (Seller)'!$B:$B,'Income & Expenses (Seller)'!$A:$A,'P&Ls_Detailed'!$E16)
D17: Security Expense | E17: Security Expense | W17: =SUMIFS('2025 P&L (Jan-Dec)'!$B:$B,'2025 P&L (Jan-Dec)'!$A:$A,'P&Ls_Detailed'!$E17) | X17: =SUMIFS('2024 P&L (Jan-Dec)'!$B:$B,'2024 P&L (Jan-Dec)'!$A:$A,'P&Ls_Detailed'!$E17) | AO17: =SUMIFS('Income & Expenses (Seller)'!$B:$B,'Income & Expenses (Seller)'!$A:$A,'P&Ls_Detailed'!$E17)
D18: State Taxes | E18: State Estimates | W18: =SUMIFS('2025 P&L (Jan-Dec)'!$B:$B,'2025 P&L (Jan-Dec)'!$A:$A,'P&Ls_Detailed'!$E18) | X18: =SUMIFS('2024 P&L (Jan-Dec)'!$B:$B,'2024 P&L (Jan-Dec)'!$A:$A,'P&Ls_Detailed'!$E18) | AO18: =SUMIFS('Income & Expenses (Seller)'!$B:$B,'Income & Expenses (Seller)'!$A:$A,'P&Ls_Detailed'!$E18)
D19: State Taxes | E19: Tax Due | W19: =SUMIFS('2025 P&L (Jan-Dec)'!$B:$B,'2025 P&L (Jan-Dec)'!$A:$A,'P&Ls_Detailed'!$E19) | X19: =SUMIFS('2024 P&L (Jan-Dec)'!$B:$B,'2024 P&L (Jan-Dec)'!$A:$A,'P&Ls_Detailed'!$E19) | AO19: =SUMIFS('Income & Expenses (Seller)'!$B:$B,'Income & Expenses (Seller)'!$A:$A,'P&Ls_Detailed'!$E19)
... D23: Utilities | E23: Utilities | W23: =SUMIFS('2025 P&L (Jan-Dec)'!$B:$B,'2025 P&L (Jan-Dec)'!$A:$A,'P&Ls_Detailed'!$E23) | X23: =SUMIFS('2024 P&L (Jan-Dec)'!$B:$B,'2024 P&L (Jan-Dec)'!$A:$A,'P&Ls_Detailed'!$E23) | AO23: =SUMIFS('Income & Expenses (Seller)'!$B:$B,'Income & Expenses (Seller)'!$A:$A,'P&Ls_Detailed'!$E23)
D25: OTHER INCOME/EXPENSE
D26: Ask My Accountant | E26: Ask My Accountant | W26: =SUMIFS('2025 P&L (Jan-Dec)'!$B:$B,'2025 P&L (Jan-Dec)'!$A:$A,'P&Ls_Detailed'!$E26) | X26: =SUMIFS('2024 P&L (Jan-Dec)'!$B:$B,'2024 P&L (Jan-Dec)'!$A:$A,'P&Ls_Detailed'!$E26) | AO26: =SUMIFS('Income & Expenses (Seller)'!$B:$B,'Income & Expenses (Seller)'!$A:$A,'P&Ls_Detailed'!$E26)
C28: Unified chart of accounts for 1603 Ridgeside Dr / Barnes, Inc., replacing the prior underwriting's Airport Corporate Center chart of accounts and detail rows. 'Category' (col D) is the roll-up key used by P&Ls_Con; 'Account' (col E) is the exact line-item name matched via SUMIFS against the '2025 P&L (Jan-Dec)', '2024 P&L (Jan-Dec)', and 'Income & Expenses (Seller)' source tabs. Blank cells mean that line item did not occur/was not reported in that column's source (e.g. the seller's I&E has no 'Depreciation Expense' or 'Professional Fees' breakdown, and left 'Property Maintenance' and 'State Taxes' unquantified). Columns F:V, Y:AB, and AC:AN are unused (no monthly-level source data exists for this property) and have been hidden rather than deleted, in case monthly actuals become available later.

Sheet P&Ls_Con
A1: Ss | E1: 1687 | G1: 1687 | I1: 1687 | K1: 1687 | M1: 1687 | O1: 1687 | Q1: 1687
C2: OPERATING STATEMENT SUMMARY | AA2: =Global!$G$7 | AC2: ='Rent Roll-Detailed'!$H$65 | AL2: =$AA$2
AL3: =$AA$2
E4: ='P&Ls_Detailed'!W4 | G4: ='P&Ls_Detailed'!X4 | I4: ='P&Ls_Detailed'!AO4 | K4: T-9 | M4: T-6 | O4: T-3 | Q4: T-1 | V4: Year 1 | X4: Year 2 | AL4: =$AA$2
E5: Actual | F5: PSF | G5: Actual | H5: PSF | I5: Actual | J5: PSF | K5: Actual | L5: PSF | M5: Actual | N5: PSF | O5: Actual | P5: PSF | Q5: Actual | R5: PSF | T5: UW | U5: PSF | V5: UW | W5: PSF | X5: UW | Y5: PSF | Z5: Notes | AL5: =$AA$2
AL6: =$AA$2
D7: REVENUE
D8: Rental Income | E8: =SUMIFS('P&Ls_Detailed'!$W:$W,'P&Ls_Detailed'!$D:$D,'P&Ls_Con'!$D8) | F8: =E8/$AC$2 | G8: =SUMIFS('P&Ls_Detailed'!$X:$X,'P&Ls_Detailed'!$D:$D,'P&Ls_Con'!$D8) | H8: =G8/$AC$2 | I8: =SUMIFS('P&Ls_Detailed'!$AO:$AO,'P&Ls_Detailed'!$D:$D,'P&Ls_Con'!$D8) | J8: =I8/$AC$2
D9: Total Income | E9: =SUM(E8:E8) | F9: =E9/$AC$2 | G9: =SUM(G8:G8) | H9: =G9/$AC$2 | I9: =SUM(I8:I8) | J9: =I9/$AC$2
D11: EXPENSES
D12: Bank Service Charges | E12: =SUMIFS('P&Ls_Detailed'!$W:$W,'P&Ls_Detailed'!$D:$D,'P&Ls_Con'!$D12) | F12: =E12/$AC$2 | G12: =SUMIFS('P&Ls_Detailed'!$X:$X,'P&Ls_Detailed'!$D:$D,'P&Ls_Con'!$D12) | H12: =G12/$AC$2 | I12: =SUMIFS('P&Ls_Detailed'!$AO:$AO,'P&Ls_Detailed'!$D:$D,'P&Ls_Con'!$D12) | J12: =I12/$AC$2
D13: Depreciation Expense | E13: =SUMIFS('P&Ls_Detailed'!$W:$W,'P&Ls_Detailed'!$D:$D,'P&Ls_Con'!$D13) | F13: =E13/$AC$2 | G13: =SUMIFS('P&Ls_Detailed'!$X:$X,'P&Ls_Detailed'!$D:$D,'P&Ls_Con'!$D13) | H13: =G13/$AC$2 | I13: =SUMIFS('P&Ls_Detailed'!$AO:$AO,'P&Ls_Detailed'!$D:$D,'P&Ls_Con'!$D13) | J13: =I13/$AC$2
D14: Donations | E14: =SUMIFS('P&Ls_Detailed'!$W:$W,'P&Ls_Detailed'!$D:$D,'P&Ls_Con'!$D14) | F14: =E14/$AC$2 | G14: =SUMIFS('P&Ls_Detailed'!$X:$X,'P&Ls_Detailed'!$D:$D,'P&Ls_Con'!$D14) | H14: =G14/$AC$2 | I14: =SUMIFS('P&Ls_Detailed'!$AO:$AO,'P&Ls_Detailed'!$D:$D,'P&Ls_Con'!$D14) | J14: =I14/$AC$2
D15: Insurance Expense | E15: =SUMIFS('P&Ls_Detailed'!$W:$W,'P&Ls_Detailed'!$D:$D,'P&Ls_Con'!$D15) | F15: =E15/$AC$2 | G15: =SUMIFS('P&Ls_Detailed'!$X:$X,'P&Ls_Detailed'!$D:$D,'P&Ls_Con'!$D15) | H15: =G15/$AC$2 | I15: =SUMIFS('P&Ls_Detailed'!$AO:$AO,'P&Ls_Detailed'!$D:$D,'P&Ls_Con'!$D15) | J15: =I15/$AC$2
D16: Management Fee | E16: =SUMIFS('P&Ls_Detailed'!$W:$W,'P&Ls_Detailed'!$D:$D,'P&Ls_Con'!$D16) | F16: =E16/$AC$2 | G16: =SUMIFS('P&Ls_Detailed'!$X:$X,'P&Ls_Detailed'!$D:$D,'P&Ls_Con'!$D16) | H16: =G16/$AC$2 | I16: =SUMIFS('P&Ls_Detailed'!$AO:$AO,'P&Ls_Detailed'!$D:$D,'P&Ls_Con'!$D16) | J16: =I16/$AC$2
D17: Professional Fees | E17: =SUMIFS('P&Ls_Detailed'!$W:$W,'P&Ls_Detailed'!$D:$D,'P&Ls_Con'!$D17) | F17: =E17/$AC$2 | G17: =SUMIFS('P&Ls_Detailed'!$X:$X,'P&Ls_Detailed'!$D:$D,'P&Ls_Con'!$D17) | H17: =G17/$AC$2 | I17: =SUMIFS('P&Ls_Detailed'!$AO:$AO,'P&Ls_Detailed'!$D:$D,'P&Ls_Con'!$D17) | J17: =I17/$AC$2
D18: Property Maintenance | E18: =SUMIFS('P&Ls_Detailed'!$W:$W,'P&Ls_Detailed'!$D:$D,'P&Ls_Con'!$D18) | F18: =E18/$AC$2 | G18: =SUMIFS('P&Ls_Detailed'!$X:$X,'P&Ls_Detailed'!$D:$D,'P&Ls_Con'!$D18) | H18: =G18/$AC$2 | I18: =SUMIFS('P&Ls_Detailed'!$AO:$AO,'P&Ls_Detailed'!$D:$D,'P&Ls_Con'!$D18) | J18: =I18/$AC$2
D19: Repairs and Maintenance | E19: =SUMIFS('P&Ls_Detailed'!$W:$W,'P&Ls_Detailed'!$D:$D,'P&Ls_Con'!$D19) | F19: =E19/$AC$2 | G19: =SUMIFS('P&Ls_Detailed'!$X:$X,'P&Ls_Detailed'!$D:$D,'P&Ls_Con'!$D19) | H19: =G19/$AC$2 | I19: =SUMIFS('P&Ls_Detailed'!$AO:$AO,'P&Ls_Detailed'!$D:$D,'P&Ls_Con'!$D19) | J19: =I19/$AC$2
D20: Security Expense | E20: =SUMIFS('P&Ls_Detailed'!$W:$W,'P&Ls_Detailed'!$D:$D,'P&Ls_Con'!$D20) | F20: =E20/$AC$2 | G20: =SUMIFS('P&Ls_Detailed'!$X:$X,'P&Ls_Detailed'!$D:$D,'P&Ls_Con'!$D20) | H20: =G20/$AC$2 | I20: =SUMIFS('P&Ls_Detailed'!$AO:$AO,'P&Ls_Detailed'!$D:$D,'P&Ls_Con'!$D20) | J20: =I20/$AC$2
D21: State Taxes | E21: =SUMIFS('P&Ls_Detailed'!$W:$W,'P&Ls_Detailed'!$D:$D,'P&Ls_Con'!$D21) | F21: =E21/$AC$2 | G21: =SUMIFS('P&Ls_Detailed'!$X:$X,'P&Ls_Detailed'!$D:$D,'P&Ls_Con'!$D21) | H21: =G21/$AC$2 | I21: =SUMIFS('P&Ls_Detailed'!$AO:$AO,'P&Ls_Detailed'!$D:$D,'P&Ls_Con'!$D21) | J21: =I21/$AC$2
D22: Taxes - Personal Property | E22: =SUMIFS('P&Ls_Detailed'!$W:$W,'P&Ls_Detailed'!$D:$D,'P&Ls_Con'!$D22) | F22: =E22/$AC$2 | G22: =SUMIFS('P&Ls_Detailed'!$X:$X,'P&Ls_Detailed'!$D:$D,'P&Ls_Con'!$D22) | H22: =G22/$AC$2 | I22: =SUMIFS('P&Ls_Detailed'!$AO:$AO,'P&Ls_Detailed'!$D:$D,'P&Ls_Con'!$D22) | J22: =I22/$AC$2
D23: Taxes - Property | E23: =SUMIFS('P&Ls_Detailed'!$W:$W,'P&Ls_Detailed'!$D:$D,'P&Ls_Con'!$D23) | F23: =E23/$AC$2 | G23: =SUMIFS('P&Ls_Detailed'!$X:$X,'P&Ls_Detailed'!$D:$D,'P&Ls_Con'!$D23) | H23: =G23/$AC$2 | I23: =SUMIFS('P&Ls_Detailed'!$AO:$AO,'P&Ls_Detailed'!$D:$D,'P&Ls_Con'!$D23) | J23: =I23/$AC$2
... D25: Utilities | E25: =SUMIFS('P&Ls_Detailed'!$W:$W,'P&Ls_Detailed'!$D:$D,'P&Ls_Con'!$D25) | F25: =E25/$AC$2 | G25: =SUMIFS('P&Ls_Detailed'!$X:$X,'P&Ls_Detailed'!$D:$D,'P&Ls_Con'!$D25) | H25: =G25/$AC$2 | I25: =SUMIFS('P&Ls_Detailed'!$AO:$AO,'P&Ls_Detailed'!$D:$D,'P&Ls_Con'!$D25) | J25: =I25/$AC$2
D26: Total Expense | E26: =SUM(E12:E25) | F26: =E26/$AC$2 | G26: =SUM(G12:G25) | H26: =G26/$AC$2 | I26: =SUM(I12:I25) | J26: =I26/$AC$2
D27: Net Ordinary Income | E27: =E9-E26 | F27: =E27/$AC$2 | G27: =G9-G26 | H27: =G27/$AC$2 | I27: =I9-I26 | J27: =I27/$AC$2
D29: OTHER INCOME/EXPENSE
D30: Ask My Accountant | E30: =SUMIFS('P&Ls_Detailed'!$W:$W,'P&Ls_Detailed'!$D:$D,'P&Ls_Con'!$D30) | F30: =E30/$AC$2 | G30: =SUMIFS('P&Ls_Detailed'!$X:$X,'P&Ls_Detailed'!$D:$D,'P&Ls_Con'!$D30) | H30: =G30/$AC$2 | I30: =SUMIFS('P&Ls_Detailed'!$AO:$AO,'P&Ls_Detailed'!$D:$D,'P&Ls_Con'!$D30) | J30: =I30/$AC$2
D31: Total Other Expense | E31: =E30 | G31: =G30 | I31: =I30
D32: Net Other Income | E32: =-E31 | G32: =-G31 | I32: =-I31
D33: Net Income | E33: =E27+E32 | F33: =E33/$AC$2 | G33: =G27+G32 | H33: =G33/$AC$2 | I33: =I27+I32 | J33: =I33/$AC$2
C35: Unified operating statement for 1603 Ridgeside Dr / Barnes, Inc., replacing the prior underwriting's Airport Corporate Center rows. Category rows (Rental Income, Professional Fees, State Taxes, etc.) are linked via SUMIFS to 'P&Ls_Detailed' (columns W=2025 Actual, X=2024 Actual, AO=Seller Pro Forma); subtotal rows (Total Income, Total Expense, Net Ordinary Income, Total Other Expense, Net Other Income, Net Income) are computed locally within this tab, consistent with this template's original convention. 'Net Ordinary Income' under the Seller Pro Forma column is not on the same basis as the 2024/2025 columns - the seller's I&E has no Depreciation Expense line and uses the seller's own below-market $550 Management Fee rather than a market rate, so it runs higher than a normalized NOI would. Columns K:R (T-9/T-6/T-3/T-1), T:U (a pre-existing broken reference), and V:Y (Year 1/Year 2 UW, tied to the Airport-specific 'Cash flow' tab) are unused for this property and have been hidden rather than deleted.

Sheet 18203 P&Ls_Con
I2: 1687 | K2: 1687 | M2: 1687 | O2: 1687 | Q2: 1687
C3: OPERATING STATEMENT SUMMARY | V3: =Global!$G$7 | X3: ='Rent Roll-Detailed'!$H$65
V4: =#REF!
E5: YE 2021 | G5: YE 2022 | I5: T-11 Ann | K5: T-9 | M5: T-6 | O5: T-3 | Q5: T-1 | T5: Year 1
E6: Actual | F6: PSF | G6: Actual | H6: PSF | I6: Actual | J6: PSF | K6: Actual | L6: PSF | M6: Actual | N6: PSF | O6: Actual | P6: PSF | Q6: Actual | R6: PSF | T6: UW | U6: PSF
D8: Income:
D9: Potential Rental Income | E9: =SUMIFS('18203 P&Ls_Detailed'!$F:$F,'18203 P&Ls_Detailed'!$D:$D,'18203 P&Ls_Con'!$D9) | F9: =E9/$X$3 | G9: =SUMIFS('18203 P&Ls_Detailed'!$G:$G,'18203 P&Ls_Detailed'!$D:$D,'18203 P&Ls_Con'!$D9) | H9: =G9/$X$3 | I9: =SUMIFS('18203 P&Ls_Detailed'!$S:$S,'18203 P&Ls_Detailed'!$D:$D,'18203 P&Ls_Con'!$D9) | J9: =I9/$X$3 | K9: =SUMIFS('18203 P&Ls_Detailed'!$T:$T,'18203 P&Ls_Detailed'!$D:$D,'18203 P&Ls_Con'!$D9) | L9: =K9/$X$3 | M9: =SUMIFS('18203 P&Ls_Detailed'!$U:$U,'18203 P&Ls_Detailed'!$D:$D,'18203 P&Ls_Con'!$D9) | N9: =M9/$X$3 | O9: =SUMIFS('18203 P&Ls_Detailed'!$V:$V,'18203 P&Ls_Detailed'!$D:$D,'18203 P&Ls_Con'!$D9) | P9: =O9/$X$3 | Q9: =SUMIFS('18203 P&Ls_Detailed'!$W:$W,'18203 P&Ls_Detailed'!$D:$D,'18203 P&Ls_Con'!$D9) | R9: =Q9/$X$3 | T9: =SUMIFS('Cash flow'!$C:$C,'Cash flow'!$A:$A,'18203 P&Ls_Con'!$D9) | U9: =T9/$X$3
D10: Downtime Vacancy | E10: =SUMIFS('18203 P&Ls_Detailed'!$F:$F,'18203 P&Ls_Detailed'!$D:$D,'18203 P&Ls_Con'!$D10) | F10: =E10/$X$3 | G10: =SUMIFS('18203 P&Ls_Detailed'!$G:$G,'18203 P&Ls_Detailed'!$D:$D,'18203 P&Ls_Con'!$D10) | H10: =G10/$X$3 | I10: =SUMIFS('18203 P&Ls_Detailed'!$S:$S,'18203 P&Ls_Detailed'!$D:$D,'18203 P&Ls_Con'!$D10) | J10: =I10/$X$3 | K10: =SUMIFS('18203 P&Ls_Detailed'!$T:$T,'18203 P&Ls_Detailed'!$D:$D,'18203 P&Ls_Con'!$D10) | L10: =K10/$X$3 | M10: =SUMIFS('18203 P&Ls_Detailed'!$U:$U,'18203 P&Ls_Detailed'!$D:$D,'18203 P&Ls_Con'!$D10) | N10: =M10/$X$3 | O10: =SUMIFS('18203 P&Ls_Detailed'!$V:$V,'18203 P&Ls_Detailed'!$D:$D,'18203 P&Ls_Con'!$D10) | P10: =O10/$X$3 | Q10: =SUMIFS('18203 P&Ls_Detailed'!$W:$W,'18203 P&Ls_Detailed'!$D:$D,'18203 P&Ls_Con'!$D10) | R10: =Q10/$X$3 | T10: =SUMIFS('Cash flow'!$C:$C,'Cash flow'!$A:$A,'18203 P&Ls_Con'!$D10) | U10: =T10/$X$3
D11: Free Rent | E11: =SUMIFS('18203 P&Ls_Detailed'!$F:$F,'18203 P&Ls_Detailed'!$D:$D,'18203 P&Ls_Con'!$D11) | F11: =E11/$X$3 | G11: =SUMIFS('18203 P&Ls_Detailed'!$G:$G,'18203 P&Ls_Detailed'!$D:$D,'18203 P&Ls_Con'!$D11) | H11: =G11/$X$3 | I11: =SUMIFS('18203 P&Ls_Detailed'!$S:$S,'18203 P&Ls_Detailed'!$D:$D,'18203 P&Ls_Con'!$D11) | J11: =I11/$X$3 | K11: =SUMIFS('18203 P&Ls_Detailed'!$T:$T,'18203 P&Ls_Detailed'!$D:$D,'18203 P&Ls_Con'!$D11) | L11: =K11/$X$3 | M11: =SUMIFS('18203 P&Ls_Detailed'!$U:$U,'18203 P&Ls_Detailed'!$D:$D,'18203 P&Ls_Con'!$D11) | N11: =M11/$X$3 | O11: =SUMIFS('18203 P&Ls_Detailed'!$V:$V,'18203 P&Ls_Detailed'!$D:$D,'18203 P&Ls_Con'!$D11) | P11: =O11/$X$3 | Q11: =SUMIFS('18203 P&Ls_Detailed'!$W:$W,'18203 P&Ls_Detailed'!$D:$D,'18203 P&Ls_Con'!$D11) | R11: =Q11/$X$3 | T11: =SUMIFS('Cash flow'!$C:$C,'Cash flow'!$A:$A,'18203 P&Ls_Con'!$D11) | U11: =T11/$X$3
D12: Base Rental Income | E12: =SUM(E9:E11) | F12: =E12/$X$3 | G12: =SUM(G9:G11) | H12: =G12/$X$3 | I12: =SUM(I9:I11) | J12: =I12/$X$3 | K12: =SUM(K9:K11) | L12: =K12/$X$3 | M12: =SUM(M9:M11) | N12: =M12/$X$3 | O12: =SUM(O9:O11) | P12: =O12/$X$3 | Q12: =SUM(Q9:Q11) | R12: =Q12/$X$3 | T12: =SUM(T9:T11) | U12: =T12/$X$3
D13: Base Rental Step Revenue | E13: =SUMIFS('18203 P&Ls_Detailed'!$F:$F,'18203 P&Ls_Detailed'!$D:$D,'18203 P&Ls_Con'!$D13) | F13: =E13/$X$3 | G13: =SUMIFS('18203 P&Ls_Detailed'!$G:$G,'18203 P&Ls_Detailed'!$D:$D,'18203 P&Ls_Con'!$D13) | H13: =G13/$X$3 | I13: =SUMIFS('18203 P&Ls_Detailed'!$S:$S,'18203 P&Ls_Detailed'!$D:$D,'18203 P&Ls_Con'!$D13) | J13: =I13/$X$3 | K13: =SUMIFS('18203 P&Ls_Detailed'!$T:$T,'18203 P&Ls_Detailed'!$D:$D,'18203 P&Ls_Con'!$D13) | L13: =K13/$X$3 | M13: =SUMIFS('18203 P&Ls_Detailed'!$U:$U,'18203 P&Ls_Detailed'!$D:$D,'18203 P&Ls_Con'!$D13) | N13: =M13/$X$3 | O13: =SUMIFS('18203 P&Ls_Detailed'!$V:$V,'18203 P&Ls_Detailed'!$D:$D,'18203 P&Ls_Con'!$D13) | P13: =O13/$X$3 | Q13: =SUMIFS('18203 P&Ls_Detailed'!$W:$W,'18203 P&Ls_Detailed'!$D:$D,'18203 P&Ls_Con'!$D13) | R13: =Q13/$X$3 | T13: =SUMIFS('Cash flow'!$C:$C,'Cash flow'!$A:$A,'18203 P&Ls_Con'!$D13) | U13: =T13/$X$3
D14: Total Recovery Income | E14: =SUMIFS('18203 P&Ls_Detailed'!$F:$F,'18203 P&Ls_Detailed'!$D:$D,'18203 P&Ls_Con'!$D14) | F14: =E14/$X$3 | G14: =SUMIFS('18203 P&Ls_Detailed'!$G:$G,'18203 P&Ls_Detailed'!$D:$D,'18203 P&Ls_Con'!$D14) | H14: =G14/$X$3 | I14: =SUMIFS('18203 P&Ls_Detailed'!$S:$S,'18203 P&Ls_Detailed'!$D:$D,'18203 P&Ls_Con'!$D14) | J14: =I14/$X$3 | K14: =SUMIFS('18203 P&Ls_Detailed'!$T:$T,'18203 P&Ls_Detailed'!$D:$D,'18203 P&Ls_Con'!$D14) | L14: =K14/$X$3 | M14: =SUMIFS('18203 P&Ls_Detailed'!$U:$U,'18203 P&Ls_Detailed'!$D:$D,'18203 P&Ls_Con'!$D14) | N14: =M14/$X$3 | O14: =SUMIFS('18203 P&Ls_Detailed'!$V:$V,'18203 P&Ls_Detailed'!$D:$D,'18203 P&Ls_Con'!$D14) | P14: =O14/$X$3 | Q14: =SUMIFS('18203 P&Ls_Detailed'!$W:$W,'18203 P&Ls_Detailed'!$D:$D,'18203 P&Ls_Con'!$D14) | R14: =Q14/$X$3 | T14: =SUMIFS('Cash flow'!$C:$C,'Cash flow'!$A:$A,'18203 P&Ls_Con'!$D14) | U14: =T14/$X$3
